Workbook

Sheet Overview
B1: 🎓 9-Month Study Plan · SDE & Full-Stack Web Developer
B2: Built from the Scaler Academy brochure and the Besant Technologies syllabus · edit the yellow cells to personalise · Developed by Rajesh Kumar Singh
B3: ⚙️ YOUR INPUTS
B4: Plan start date (use a Monday) | C4: 46307 | D4: =IF(WEEKDAY(C4,2)=1,"✔ Monday","⚠ Not a Monday") -> ✔ Monday
B5: Study hours per week | C5: 20 | D5: Compressed plan: aim for 18–22 h/week
B6: Experience level (SDE plan) | C6: Intermediate | D6: Intermediate = 39 wks · Beginner adds 8 wks (≈11 months) · Advanced skips Intermediate DSA
B8: 🧠 SDE Plan
B9: SDE Plan | C9: WEEKS PLANNED | E9: TOTAL HOURS | G9: PLANNED FINISH | I9: PROGRESS
C10: =COUNTIF('SDE Plan'!$B$6:$B$78,"Yes") -> 39 | E10: =COUNTIF('SDE Plan'!$B$6:$B$78,"Yes")*$C$5 -> 780 | G10: =IF(COUNTIF('SDE Plan'!$B$6:$B$78,"Yes")=0,"—",MAX('SDE Plan'!$D$6:$D$78)) -> 46579 | I10: =IF(COUNTIF('SDE Plan'!$B$6:$B$78,"Yes")=0,0,COUNTIFS('SDE Plan'!$B$6:$B$78,"Yes",'SDE Plan'!$L$6:$L$78,"Done")/COUNTIF('SDE Plan'!$B$6:$B$78,"Yes")) -> 0
C12: =ROUND(COUNTIF('SDE Plan'!$B$6:$B$78,"Yes")/4.345,1)&" months"&IF(COUNTIF('SDE Plan'!$B$6:$B$78,"Yes")<=39," ✔ fits 9 mo"," ⚠ over 9 mo") -> 9 months ✔ fits 9 mo | E12: ="at "&$C$5&" h / week" -> at 20 h / week | G12: ="starts "&TEXT($C$4,"dd mmm yyyy") -> starts 12 Oct 2026 | I12: =COUNTIFS('SDE Plan'!$B$6:$B$78,"Yes",'SDE Plan'!$L$6:$L$78,"Done")&" of "&COUNTIF('SDE Plan'!$B$6:$B$78,"Yes")&" weeks done" -> 0 of 39 weeks done
B14: 🌐 Full-Stack Plan
B15: Full-Stack Plan | C15: WEEKS PLANNED | E15: TOTAL HOURS | G15: PLANNED FINISH | I15: PROGRESS
C16: =COUNTIF('FullStack Plan'!$B$6:$B$78,"Yes") -> 39 | E16: =COUNTIF('FullStack Plan'!$B$6:$B$78,"Yes")*$C$5 -> 780 | G16: =IF(COUNTIF('FullStack Plan'!$B$6:$B$78,"Yes")=0,"—",MAX('FullStack Plan'!$D$6:$D$78)) -> 46579 | I16: =IF(COUNTIF('FullStack Plan'!$B$6:$B$78,"Yes")=0,0,COUNTIFS('FullStack Plan'!$B$6:$B$78,"Yes",'FullStack Plan'!$L$6:$L$78,"Done")/COUNTIF('FullStack Plan'!$B$6:$B$78,"Yes")) -> 0
C18: =ROUND(COUNTIF('FullStack Plan'!$B$6:$B$78,"Yes")/4.345,1)&" months"&IF(COUNTIF('FullStack Plan'!$B$6:$B$78,"Yes")<=39," ✔ fits 9 mo"," ⚠ over 9 mo") -> 9 months ✔ fits 9 mo | E18: ="at "&$C$5&" h / week" -> at 20 h / week | G18: ="starts "&TEXT($C$4,"dd mmm yyyy") -> starts 12 Oct 2026 | I18: =COUNTIFS('FullStack Plan'!$B$6:$B$78,"Yes",'FullStack Plan'!$L$6:$L$78,"Done")&" of "&COUNTIF('FullStack Plan'!$B$6:$B$78,"Yes")&" weeks done" -> 0 of 39 weeks done
B20: 📊 WEEKS BY PHASE
B21: Phase | C21: SDE | D21: Full-Stack
B22: 0. 🧱 Foundations | C22: =SUMIFS('Module Summary'!$D$5:$D$43,'Module Summary'!$B$5:$B$43,$B22,'Module Summary'!$A$5:$A$43,"SDE") -> 0 | D22: =SUMIFS('Module Summary'!$D$5:$D$43,'Module Summary'!$B$5:$B$43,$B22,'Module Summary'!$A$5:$A$43,"Full-Stack") -> 0
B23: 1. 🌐 Web Foundations | C23: =SUMIFS('Module Summary'!$D$5:$D$43,'Module Summary'!$B$5:$B$43,$B23,'Module Summary'!$A$5:$A$43,"SDE") -> 0 | D23: =SUMIFS('Module Summary'!$D$5:$D$43,'Module Summary'!$B$5:$B$43,$B23,'Module Summary'!$A$5:$A$43,"Full-Stack") -> 2
B24: 1. 🧩 Problem Solving | C24: =SUMIFS('Module Summary'!$D$5:$D$43,'Module Summary'!$B$5:$B$43,$B24,'Module Summary'!$A$5:$A$43,"SDE") -> 2 | D24: =SUMIFS('Module Summary'!$D$5:$D$43,'Module Summary'!$B$5:$B$43,$B24,'Module Summary'!$A$5:$A$43,"Full-Stack") -> 0
B25: 2. ⚡ JavaScript | C25: =SUMIFS('Module Summary'!$D$5:$D$43,'Module Summary'!$B$5:$B$43,$B25,'Module Summary'!$A$5:$A$43,"SDE") -> 0 | D25: =SUMIFS('Module Summary'!$D$5:$D$43,'Module Summary'!$B$5:$B$43,$B25,'Module Summary'!$A$5:$A$43,"Full-Stack") -> 8
B26: 2. 🤖 AI Skills | C26: =SUMIFS('Module Summary'!$D$5:$D$43,'Module Summary'!$B$5:$B$43,$B26,'Module Summary'!$A$5:$A$43,"SDE") -> 2 | D26: =SUMIFS('Module Summary'!$D$5:$D$43,'Module Summary'!$B$5:$B$43,$B26,'Module Summary'!$A$5:$A$43,"Full-Stack") -> 0
B27: 3. ⚛️ React | C27: =SUMIFS('Module Summary'!$D$5:$D$43,'Module Summary'!$B$5:$B$43,$B27,'Module Summary'!$A$5:$A$43,"SDE") -> 0 | D27: =SUMIFS('Module Summary'!$D$5:$D$43,'Module Summary'!$B$5:$B$43,$B27,'Module Summary'!$A$5:$A$43,"Full-Stack") -> 4
B28: 3. 🧠 DSA | C28: =SUMIFS('Module Summary'!$D$5:$D$43,'Module Summary'!$B$5:$B$43,$B28,'Module Summary'!$A$5:$A$43,"SDE") -> 13 | D28: =SUMIFS('Module Summary'!$D$5:$D$43,'Module Summary'!$B$5:$B$43,$B28,'Module Summary'!$A$5:$A$43,"Full-Stack") -> 0
B29: 4. 🗄️ Databases | C29: =SUMIFS('Module Summary'!$D$5:$D$43,'Module Summary'!$B$5:$B$43,$B29,'Module Summary'!$A$5:$A$43,"SDE") -> 2 | D29: =SUMIFS('Module Summary'!$D$5:$D$43,'Module Summary'!$B$5:$B$43,$B29,'Module Summary'!$A$5:$A$43,"Full-Stack") -> 0
B30: 4. 🛠️ Backend (MERN) | C30: =SUMIFS('Module Summary'!$D$5:$D$43,'Module Summary'!$B$5:$B$43,$B30,'Module Summary'!$A$5:$A$43,"SDE") -> 0 | D30: =SUMIFS('Module Summary'!$D$5:$D$43,'Module Summary'!$B$5:$B$43,$B30,'Module Summary'!$A$5:$A$43,"Full-Stack") -> 10
B31: 5. ⚙️ Backend & LLD | C31: =SUMIFS('Module Summary'!$D$5:$D$43,'Module Summary'!$B$5:$B$43,$B31,'Module Summary'!$A$5:$A$43,"SDE") -> 14 | D31: =SUMIFS('Module Summary'!$D$5:$D$43,'Module Summary'!$B$5:$B$43,$B31,'Module Summary'!$A$5:$A$43,"Full-Stack") -> 0
B32: 5. 🚀 Advanced Frontend | C32: =SUMIFS('Module Summary'!$D$5:$D$43,'Module Summary'!$B$5:$B$43,$B32,'Module Summary'!$A$5:$A$43,"SDE") -> 0 | D32: =SUMIFS('Module Summary'!$D$5:$D$43,'Module Summary'!$B$5:$B$43,$B32,'Module Summary'!$A$5:$A$43,"Full-Stack") -> 6
B33: 6. 🏆 Capstone | C33: =SUMIFS('Module Summary'!$D$5:$D$43,'Module Summary'!$B$5:$B$43,$B33,'Module Summary'!$A$5:$A$43,"SDE") -> 0 | D33: =SUMIFS('Module Summary'!$D$5:$D$43,'Module Summary'!$B$5:$B$43,$B33,'Module Summary'!$A$5:$A$43,"Full-Stack") -> 3
... B38: 8. ✨ Optional extensions | C38: =SUMIFS('Module Summary'!$D$5:$D$43,'Module Summary'!$B$5:$B$43,$B38,'Module Summary'!$A$5:$A$43,"SDE") -> 0 | D38: =SUMIFS('Module Summary'!$D$5:$D$43,'Module Summary'!$B$5:$B$43,$B38,'Module Summary'!$A$5:$A$43,"Full-Stack") -> 0
B39: Total weeks | C39: =SUM(C22:C38) -> 39 | D39: =SUM(D22:D38) -> 39
B41: 🧭 HOW TO USE
B42: 1. Set the start date, weekly hours and level in the yellow cells above.
B43: 2. Open SDE Plan / FullStack Plan – each row is one week: topics, 📖 reading link, ▶ YouTube link, practice & milestone.
B44: 3. Set Include? to No to skip a week or module – dates, Timeline and totals re-flow automatically (grey rows are skipped).
B45: 4. Update Status each week: the cards above, Timeline (dark-green = done) and Module Summary update live.
B46: 5. Month Plan = your 9-month view · Timeline = Gantt chart · Resources = more links · Projects = portfolio tracker.
B47: Legend: blue text = you edit · black = formula · yellow fill = key input · grey rows = skipped. Include? for the first SDE modules follows your level – overwrite with Yes/No to override.
B49: 🎯 WHICH PLAN SHOULD I FOLLOW?
B50: 🧠 SDE Plan → product-company / FAANG-style interviews: DSA, LLD, HLD, Java/Spring backend, AI skills.
B51: 🌐 Full-Stack Plan → web-product roles: HTML/CSS, JavaScript, React, Node/Express/MongoDB, SQL + light DSA.
B52: Doing both? Do Full-Stack first, then switch on Advanced DSA and System Design in it.
B54: Developed by Rajesh Kumar Singh

Sheet Month Plan
A1: 9-Month Roadmap – month by month
A2: Auto-built from the plan sheets (Include? changes flow through). Plan weeks are numbered 1–39; if you pick Beginner or switch on extras, later weeks run past month 9.
A4: Month | B4: Plan weeks | C4: From (wk 1 of month) | D4: SDE focus | E4: Full-Stack focus | F4: Hours (SDE / FS) | G4: Month goal | H4: wk from | I4: wk to
A5: Month 1 | B5: 1–4 | C5: =IFERROR(INDEX('SDE Plan'!$C$6:$C$78,MATCH($H5,'SDE Plan'!$A$6:$A$78,0)),"—") -> 46307 | D5: =IFERROR(IF(INDEX('SDE Plan'!$F$6:$F$78,MATCH($H5,'SDE Plan'!$A$6:$A$78,0))=INDEX('SDE Plan'!$F$6:$F$78,MATCH($I5,'SDE Plan'!$A$6:$A$78,0)),INDEX('SDE Plan'!$F$6:$F$78,MATCH($H5,'SDE Plan'!$A$6:$A$78,0)),INDEX('SDE Plan'!$F$6:$F$78,MATCH($H5,'SDE Plan'!$A$6:$A$78,0))&" → "&INDEX('SDE Plan'!$F$6:$F$78,MATCH($I5,'SDE Plan'!$A$6:$A$78,0))),"—") -> Intermediate DSA: AI-Assisted Problem Solving → Agentic AI: From Talking to AI to Building One | E5: =IFERROR(IF(INDEX('FullStack Plan'!$F$6:$F$78,MATCH($H5,'FullStack Plan'!$A$6:$A$78,0))=INDEX('FullStack Plan'!$F$6:$F$78,MATCH($I5,'FullStack Plan'!$A$6:$A$78,0)),INDEX('FullStack Plan'!$F$6:$F$78,MATCH($H5,'FullStack Plan'!$A$6:$A$78,0)),INDEX('FullStack Plan'!$F$6:$F$78,MATCH($H5,'FullStack Plan'!$A$6:$A$78,0))&" → "&INDEX('FullStack Plan'!$F$6:$F$78,MATCH($I5,'FullStack Plan'!$A$6:$A$78,0))),"—") -> HTML & CSS Foundations → JavaScript Runtime Systems, Browser APIs & Product Labs | F5: =(I5-H5+1)*Overview!$C$5 -> 80 | G5: Checkpoint: first module contest passed + one mini project on GitHub | H5: 1 | I5: 4
A6: Month 2 | B6: 5–9 | C6: =IFERROR(INDEX('SDE Plan'!$C$6:$C$78,MATCH($H6,'SDE Plan'!$A$6:$A$78,0)),"—") -> 46335 | D6: =IFERROR(IF(INDEX('SDE Plan'!$F$6:$F$78,MATCH($H6,'SDE Plan'!$A$6:$A$78,0))=INDEX('SDE Plan'!$F$6:$F$78,MATCH($I6,'SDE Plan'!$A$6:$A$78,0)),INDEX('SDE Plan'!$F$6:$F$78,MATCH($H6,'SDE Plan'!$A$6:$A$78,0)),INDEX('SDE Plan'!$F$6:$F$78,MATCH($H6,'SDE Plan'!$A$6:$A$78,0))&" → "&INDEX('SDE Plan'!$F$6:$F$78,MATCH($I6,'SDE Plan'!$A$6:$A$78,0))),"—") -> Advanced DSA: Foundations – Core Techniques & Optimization → Advanced DSA: Linear & Non-Linear Structures | E6: =IFERROR(IF(INDEX('FullStack Plan'!$F$6:$F$78,MATCH($H6,'FullStack Plan'!$A$6:$A$78,0))=INDEX('FullStack Plan'!$F$6:$F$78,MATCH($I6,'FullStack Plan'!$A$6:$A$78,0)),INDEX('FullStack Plan'!$F$6:$F$78,MATCH($H6,'FullStack Plan'!$A$6:$A$78,0)),INDEX('FullStack Plan'!$F$6:$F$78,MATCH($H6,'FullStack Plan'!$A$6:$A$78,0))&" → "&INDEX('FullStack Plan'!$F$6:$F$78,MATCH($I6,'FullStack Plan'!$A$6:$A$78,0))),"—") -> JavaScript Runtime Systems, Browser APIs & Product Labs → JavaScript Object System & Engineering Patterns | F6: =(I6-H6+1)*Overview!$C$5 -> 100 | G6: Checkpoint: 40+ DSA problems solved; first deployed page/app | H6: 5 | I6: 9
A7: Month 3 | B7: 10–13 | C7: =IFERROR(INDEX('SDE Plan'!$C$6:$C$78,MATCH($H7,'SDE Plan'!$A$6:$A$78,0)),"—") -> 46370 | D7: =IFERROR(IF(INDEX('SDE Plan'!$F$6:$F$78,MATCH($H7,'SDE Plan'!$A$6:$A$78,0))=INDEX('SDE Plan'!$F$6:$F$78,MATCH($I7,'SDE Plan'!$A$6:$A$78,0)),INDEX('SDE Plan'!$F$6:$F$78,MATCH($H7,'SDE Plan'!$A$6:$A$78,0)),INDEX('SDE Plan'!$F$6:$F$78,MATCH($H7,'SDE Plan'!$A$6:$A$78,0))&" → "&INDEX('SDE Plan'!$F$6:$F$78,MATCH($I7,'SDE Plan'!$A$6:$A$78,0))),"—") -> Advanced DSA: Linear & Non-Linear Structures → Advanced DSA: Backtracking & Advanced Trees | E7: =IFERROR(IF(INDEX('FullStack Plan'!$F$6:$F$78,MATCH($H7,'FullStack Plan'!$A$6:$A$78,0))=INDEX('FullStack Plan'!$F$6:$F$78,MATCH($I7,'FullStack Plan'!$A$6:$A$78,0)),INDEX('FullStack Plan'!$F$6:$F$78,MATCH($H7,'FullStack Plan'!$A$6:$A$78,0)),INDEX('FullStack Plan'!$F$6:$F$78,MATCH($H7,'FullStack Plan'!$A$6:$A$78,0))&" → "&INDEX('FullStack Plan'!$F$6:$F$78,MATCH($I7,'FullStack Plan'!$A$6:$A$78,0))),"—") -> JavaScript Object System & Engineering Patterns → React & Frontend Product Architecture Fundamentals | F7: =(I7-H7+1)*Overview!$C$5 -> 80 | G7: Checkpoint: 80+ DSA problems; second project live | H7: 10 | I7: 13
A8: Month 4 | B8: 14–17 | C8: =IFERROR(INDEX('SDE Plan'!$C$6:$C$78,MATCH($H8,'SDE Plan'!$A$6:$A$78,0)),"—") -> 46398 | D8: =IFERROR(IF(INDEX('SDE Plan'!$F$6:$F$78,MATCH($H8,'SDE Plan'!$A$6:$A$78,0))=INDEX('SDE Plan'!$F$6:$F$78,MATCH($I8,'SDE Plan'!$A$6:$A$78,0)),INDEX('SDE Plan'!$F$6:$F$78,MATCH($H8,'SDE Plan'!$A$6:$A$78,0)),INDEX('SDE Plan'!$F$6:$F$78,MATCH($H8,'SDE Plan'!$A$6:$A$78,0))&" → "&INDEX('SDE Plan'!$F$6:$F$78,MATCH($I8,'SDE Plan'!$A$6:$A$78,0))),"—") -> Advanced DSA: DP, Heaps & Graphs – Crack It with AI Edge | E8: =IFERROR(IF(INDEX('FullStack Plan'!$F$6:$F$78,MATCH($H8,'FullStack Plan'!$A$6:$A$78,0))=INDEX('FullStack Plan'!$F$6:$F$78,MATCH($I8,'FullStack Plan'!$A$6:$A$78,0)),INDEX('FullStack Plan'!$F$6:$F$78,MATCH($H8,'FullStack Plan'!$A$6:$A$78,0)),INDEX('FullStack Plan'!$F$6:$F$78,MATCH($H8,'FullStack Plan'!$A$6:$A$78,0))&" → "&INDEX('FullStack Plan'!$F$6:$F$78,MATCH($I8,'FullStack Plan'!$A$6:$A$78,0))),"—") -> React & Frontend Product Architecture Fundamentals → Backend Product Systems, APIs & Production Engineering (MERN) | F8: =(I8-H8+1)*Overview!$C$5 -> 80 | G8: Checkpoint: DSA phase done / React app live; 1 mock interview | H8: 14 | I8: 17
A9: Month 5 | B9: 18–22 | C9: =IFERROR(INDEX('SDE Plan'!$C$6:$C$78,MATCH($H9,'SDE Plan'!$A$6:$A$78,0)),"—") -> 46426 | D9: =IFERROR(IF(INDEX('SDE Plan'!$F$6:$F$78,MATCH($H9,'SDE Plan'!$A$6:$A$78,0))=INDEX('SDE Plan'!$F$6:$F$78,MATCH($I9,'SDE Plan'!$A$6:$A$78,0)),INDEX('SDE Plan'!$F$6:$F$78,MATCH($H9,'SDE Plan'!$A$6:$A$78,0)),INDEX('SDE Plan'!$F$6:$F$78,MATCH($H9,'SDE Plan'!$A$6:$A$78,0))&" → "&INDEX('SDE Plan'!$F$6:$F$78,MATCH($I9,'SDE Plan'!$A$6:$A$78,0))),"—") -> Databases & SQL → Foundations of Object-Oriented Design & Scalable Systems | E9: =IFERROR(IF(INDEX('FullStack Plan'!$F$6:$F$78,MATCH($H9,'FullStack Plan'!$A$6:$A$78,0))=INDEX('FullStack Plan'!$F$6:$F$78,MATCH($I9,'FullStack Plan'!$A$6:$A$78,0)),INDEX('FullStack Plan'!$F$6:$F$78,MATCH($H9,'FullStack Plan'!$A$6:$A$78,0)),INDEX('FullStack Plan'!$F$6:$F$78,MATCH($H9,'FullStack Plan'!$A$6:$A$78,0))&" → "&INDEX('FullStack Plan'!$F$6:$F$78,MATCH($I9,'FullStack Plan'!$A$6:$A$78,0))),"—") -> Backend Product Systems, APIs & Production Engineering (MERN) → Databases & SQL | F9: =(I9-H9+1)*Overview!$C$5 -> 100 | G9: Checkpoint: SQL contest passed; backend API running with a database | H9: 18 | I9: 22
A10: Month 6 | B10: 23–26 | C10: =IFERROR(INDEX('SDE Plan'!$C$6:$C$78,MATCH($H10,'SDE Plan'!$A$6:$A$78,0)),"—") -> 46461 | D10: =IFERROR(IF(INDEX('SDE Plan'!$F$6:$F$78,MATCH($H10,'SDE Plan'!$A$6:$A$78,0))=INDEX('SDE Plan'!$F$6:$F$78,MATCH($I10,'SDE Plan'!$A$6:$A$78,0)),INDEX('SDE Plan'!$F$6:$F$78,MATCH($H10,'SDE Plan'!$A$6:$A$78,0)),INDEX('SDE Plan'!$F$6:$F$78,MATCH($H10,'SDE Plan'!$A$6:$A$78,0))&" → "&INDEX('SDE Plan'!$F$6:$F$78,MATCH($I10,'SDE Plan'!$A$6:$A$78,0))),"—") -> Design Principles & Patterns for Extensible Systems → Applied Design & Machine Coding | E10: =IFERROR(IF(INDEX('FullStack Plan'!$F$6:$F$78,MATCH($H10,'FullStack Plan'!$A$6:$A$78,0))=INDEX('FullStack Plan'!$F$6:$F$78,MATCH($I10,'FullStack Plan'!$A$6:$A$78,0)),INDEX('FullStack Plan'!$F$6:$F$78,MATCH($H10,'FullStack Plan'!$A$6:$A$78,0)),INDEX('FullStack Plan'!$F$6:$F$78,MATCH($H10,'FullStack Plan'!$A$6:$A$78,0))&" → "&INDEX('FullStack Plan'!$F$6:$F$78,MATCH($I10,'FullStack Plan'!$A$6:$A$78,0))),"—") -> Backend Product Systems – Deep Dive → React, TypeScript & Frontend Architecture – Deep Dive (incl. Next.js) | F10: =(I10-H10+1)*Overview!$C$5 -> 80 | G10: Checkpoint: auth + CRUD service built; 120+ DSA problems | H10: 23 | I10: 26
A11: Month 7 | B11: 27–30 | C11: =IFERROR(INDEX('SDE Plan'!$C$6:$C$78,MATCH($H11,'SDE Plan'!$A$6:$A$78,0)),"—") -> 46489 | D11: =IFERROR(IF(INDEX('SDE Plan'!$F$6:$F$78,MATCH($H11,'SDE Plan'!$A$6:$A$78,0))=INDEX('SDE Plan'!$F$6:$F$78,MATCH($I11,'SDE Plan'!$A$6:$A$78,0)),INDEX('SDE Plan'!$F$6:$F$78,MATCH($H11,'SDE Plan'!$A$6:$A$78,0)),INDEX('SDE Plan'!$F$6:$F$78,MATCH($H11,'SDE Plan'!$A$6:$A$78,0))&" → "&INDEX('SDE Plan'!$F$6:$F$78,MATCH($I11,'SDE Plan'!$A$6:$A$78,0))),"—") -> Applied Design & Machine Coding → AI-First Backend Capstone Project – Primer | E11: =IFERROR(IF(INDEX('FullStack Plan'!$F$6:$F$78,MATCH($H11,'FullStack Plan'!$A$6:$A$78,0))=INDEX('FullStack Plan'!$F$6:$F$78,MATCH($I11,'FullStack Plan'!$A$6:$A$78,0)),INDEX('FullStack Plan'!$F$6:$F$78,MATCH($H11,'FullStack Plan'!$A$6:$A$78,0)),INDEX('FullStack Plan'!$F$6:$F$78,MATCH($H11,'FullStack Plan'!$A$6:$A$78,0))&" → "&INDEX('FullStack Plan'!$F$6:$F$78,MATCH($I11,'FullStack Plan'!$A$6:$A$78,0))),"—") -> React, TypeScript & Frontend Architecture – Deep Dive (incl. Next.js) → Foundations of AI-Assisted Full-Stack Development | F11: =(I11-H11+1)*Overview!$C$5 -> 80 | G11: Checkpoint: design patterns / advanced frontend applied in a real project | H11: 27 | I11: 30
A12: Month 8 | B12: 31–35 | C12: =IFERROR(INDEX('SDE Plan'!$C$6:$C$78,MATCH($H12,'SDE Plan'!$A$6:$A$78,0)),"—") -> 46517 | D12: =IFERROR(IF(INDEX('SDE Plan'!$F$6:$F$78,MATCH($H12,'SDE Plan'!$A$6:$A$78,0))=INDEX('SDE Plan'!$F$6:$F$78,MATCH($I12,'SDE Plan'!$A$6:$A$78,0)),INDEX('SDE Plan'!$F$6:$F$78,MATCH($H12,'SDE Plan'!$A$6:$A$78,0)),INDEX('SDE Plan'!$F$6:$F$78,MATCH($H12,'SDE Plan'!$A$6:$A$78,0))&" → "&INDEX('SDE Plan'!$F$6:$F$78,MATCH($I12,'SDE Plan'!$A$6:$A$78,0))),"—") -> AI-First Backend Capstone Project – Advance → Distributed System Design & AI-Integrated Architectures | E12: =IFERROR(IF(INDEX('FullStack Plan'!$F$6:$F$78,MATCH($H12,'FullStack Plan'!$A$6:$A$78,0))=INDEX('FullStack Plan'!$F$6:$F$78,MATCH($I12,'FullStack Plan'!$A$6:$A$78,0)),INDEX('FullStack Plan'!$F$6:$F$78,MATCH($H12,'FullStack Plan'!$A$6:$A$78,0)),INDEX('FullStack Plan'!$F$6:$F$78,MATCH($H12,'FullStack Plan'!$A$6:$A$78,0))&" → "&INDEX('FullStack Plan'!$F$6:$F$78,MATCH($I12,'FullStack Plan'!$A$6:$A$78,0))),"—") -> Full-Stack Capstone Project (suggested) → Intermediate DSA: AI-Assisted Problem Solving | F12: =(I12-H12+1)*Overview!$C$5 -> 100 | G12: Checkpoint: capstone feature-complete; first system-design write-up | H12: 31 | I12: 35
A13: Month 9 | B13: 36–39 | C13: =IFERROR(INDEX('SDE Plan'!$C$6:$C$78,MATCH($H13,'SDE Plan'!$A$6:$A$78,0)),"—") -> 46552 | D13: =IFERROR(IF(INDEX('SDE Plan'!$F$6:$F$78,MATCH($H13,'SDE Plan'!$A$6:$A$78,0))=INDEX('SDE Plan'!$F$6:$F$78,MATCH($I13,'SDE Plan'!$A$6:$A$78,0)),INDEX('SDE Plan'!$F$6:$F$78,MATCH($H13,'SDE Plan'!$A$6:$A$78,0)),INDEX('SDE Plan'!$F$6:$F$78,MATCH($H13,'SDE Plan'!$A$6:$A$78,0))&" → "&INDEX('SDE Plan'!$F$6:$F$78,MATCH($I13,'SDE Plan'!$A$6:$A$78,0))),"—") -> Distributed System Design & AI-Integrated Architectures → Mastering LastMile – Interview Simulation | E13: =IFERROR(IF(INDEX('FullStack Plan'!$F$6:$F$78,MATCH($H13,'FullStack Plan'!$A$6:$A$78,0))=INDEX('FullStack Plan'!$F$6:$F$78,MATCH($I13,'FullStack Plan'!$A$6:$A$78,0)),INDEX('FullStack Plan'!$F$6:$F$78,MATCH($H13,'FullStack Plan'!$A$6:$A$78,0)),INDEX('FullStack Plan'!$F$6:$F$78,MATCH($H13,'FullStack Plan'!$A$6:$A$78,0))&" → "&INDEX('FullStack Plan'!$F$6:$F$78,MATCH($I13,'FullStack Plan'!$A$6:$A$78,0))),"—") -> Intermediate DSA: AI-Assisted Problem Solving → Mastering LastMile – Interview Simulation | F13: =(I13-H13+1)*Overview!$C$5 -> 80 | G13: Final: capstone deployed, 3 mock interviews, resume & LinkedIn updated | H13: 36 | I13: 39

Sheet Timeline
A1: 🗓️ Timeline – Gantt view of the 39-week plan
A2: Bars are formulas: coloured = planned weeks, dark green = weeks marked Done. Skipped (Include? = No) modules show no bar.
A4: Track | B4: Module | C4: Start wk | D4: End wk | E4: Month 1 | I4: Month 2 | N4: Month 3 | R4: Month 4 | V4: Month 5 | AA4: Month 6 | AE4: Month 7 | AI4: Month 8 | AN4: Month 9
E5: 1 | F5: 2 | G5: 3 | H5: 4 | I5: 5 | J5: 6 | K5: 7 | L5: 8 | M5: 9 | N5: 10 | O5: 11 | P5: 12 | Q5: 13 | R5: 14 | S5: 15 | T5: 16 | U5: 17 | V5: 18 | W5: 19 | X5: 20 | Y5: 21 | Z5: 22 | AA5: 23 | AB5: 24 | AC5: 25 | AD5: 26 | AE5: 27 | AF5: 28 | AG5: 29 | AH5: 30 | AI5: 31 | AJ5: 32 | AK5: 33 | AL5: 34 | AM5: 35 | AN5: 36 | AO5: 37 | AP5: 38 | AQ5: 39
A6: 🧠 SDE TRACK
A7: SDE | B7: Programming Fundamentals – Thinking with AI: Logics, Loops & Control Flow | C7: =IF(COUNTIFS('SDE Plan'!$F$6:$F$78,$B7,'SDE Plan'!$B$6:$B$78,"Yes")=0,"",_xlfn.MINIFS('SDE Plan'!$A$6:$A$78,'SDE Plan'!$F$6:$F$78,$B7,'SDE Plan'!$B$6:$B$78,"Yes")) | D7: =IF(COUNTIFS('SDE Plan'!$F$6:$F$78,$B7,'SDE Plan'!$B$6:$B$78,"Yes")=0,"",_xlfn.MAXIFS('SDE Plan'!$A$6:$A$78,'SDE Plan'!$F$6:$F$78,$B7,'SDE Plan'!$B$6:$B$78,"Yes")) | E7: =IF($C7="","",IF(AND(E$5>=$C7,E$5<=$D7),IF(E$5<$C7+COUNTIFS('SDE Plan'!$F$6:$F$78,$B7,'SDE Plan'!$B$6:$B$78,"Yes",'SDE Plan'!$L$6:$L$78,"Done"),2,1),"")) | F7: =IF($C7="","",IF(AND(F$5>=$C7,F$5<=$D7),IF(F$5<$C7+COUNTIFS('SDE Plan'!$F$6:$F$78,$B7,'SDE Plan'!$B$6:$B$78,"Yes",'SDE Plan'!$L$6:$L$78,"Done"),2,1),"")) | G7: =IF($C7="","",IF(AND(G$5>=$C7,G$5<=$D7),IF(G$5<$C7+COUNTIFS('SDE Plan'!$F$6:$F$78,$B7,'SDE Plan'!$B$6:$B$78,"Yes",'SDE Plan'!$L$6:$L$78,"Done"),2,1),"")) | H7: =IF($C7="","",IF(AND(H$5>=$C7,H$5<=$D7),IF(H$5<$C7+COUNTIFS('SDE Plan'!$F$6:$F$78,$B7,'SDE Plan'!$B$6:$B$78,"Yes",'SDE Plan'!$L$6:$L$78,"Done"),2,1),"")) | I7: =IF($C7="","",IF(AND(I$5>=$C7,I$5<=$D7),IF(I$5<$C7+COUNTIFS('SDE Plan'!$F$6:$F$78,$B7,'SDE Plan'!$B$6:$B$78,"Yes",'SDE Plan'!$L$6:$L$78,"Done"),2,1),"")) | J7: =IF($C7="","",IF(AND(J$5>=$C7,J$5<=$D7),IF(J$5<$C7+COUNTIFS('SDE Plan'!$F$6:$F$78,$B7,'SDE Plan'!$B$6:$B$78,"Yes",'SDE Plan'!$L$6:$L$78,"Done"),2,1),"")) | K7: =IF($C7="","",IF(AND(K$5>=$C7,K$5<=$D7),IF(K$5<$C7+COUNTIFS('SDE Plan'!$F$6:$F$78,$B7,'SDE Plan'!$B$6:$B$78,"Yes",'SDE Plan'!$L$6:$L$78,"Done"),2,1),"")) | L7: =IF($C7="","",IF(AND(L$5>=$C7,L$5<=$D7),IF(L$5<$C7+COUNTIFS('SDE Plan'!$F$6:$F$78,$B7,'SDE Plan'!$B$6:$B$78,"Yes",'SDE Plan'!$L$6:$L$78,"Done"),2,1),"")) | ... AQ7: =IF($C7="","",IF(AND(AQ$5>=$C7,AQ$5<=$D7),IF(AQ$5<$C7+COUNTIFS('SDE Plan'!$F$6:$F$78,$B7,'SDE Plan'!$B$6:$B$78,"Yes",'SDE Plan'!$L$6:$L$78,"Done"),2,1),""))
A8: SDE | B8: Programming Fundamentals – Code Smarter with AI: Functions & Arrays | C8: =IF(COUNTIFS('SDE Plan'!$F$6:$F$78,$B8,'SDE Plan'!$B$6:$B$78,"Yes")=0,"",_xlfn.MINIFS('SDE Plan'!$A$6:$A$78,'SDE Plan'!$F$6:$F$78,$B8,'SDE Plan'!$B$6:$B$78,"Yes")) | D8: =IF(COUNTIFS('SDE Plan'!$F$6:$F$78,$B8,'SDE Plan'!$B$6:$B$78,"Yes")=0,"",_xlfn.MAXIFS('SDE Plan'!$A$6:$A$78,'SDE Plan'!$F$6:$F$78,$B8,'SDE Plan'!$B$6:$B$78,"Yes")) | E8: =IF($C8="","",IF(AND(E$5>=$C8,E$5<=$D8),IF(E$5<$C8+COUNTIFS('SDE Plan'!$F$6:$F$78,$B8,'SDE Plan'!$B$6:$B$78,"Yes",'SDE Plan'!$L$6:$L$78,"Done"),2,1),"")) | F8: =IF($C8="","",IF(AND(F$5>=$C8,F$5<=$D8),IF(F$5<$C8+COUNTIFS('SDE Plan'!$F$6:$F$78,$B8,'SDE Plan'!$B$6:$B$78,"Yes",'SDE Plan'!$L$6:$L$78,"Done"),2,1),"")) | G8: =IF($C8="","",IF(AND(G$5>=$C8,G$5<=$D8),IF(G$5<$C8+COUNTIFS('SDE Plan'!$F$6:$F$78,$B8,'SDE Plan'!$B$6:$B$78,"Yes",'SDE Plan'!$L$6:$L$78,"Done"),2,1),"")) | H8: =IF($C8="","",IF(AND(H$5>=$C8,H$5<=$D8),IF(H$5<$C8+COUNTIFS('SDE Plan'!$F$6:$F$78,$B8,'SDE Plan'!$B$6:$B$78,"Yes",'SDE Plan'!$L$6:$L$78,"Done"),2,1),"")) | I8: =IF($C8="","",IF(AND(I$5>=$C8,I$5<=$D8),IF(I$5<$C8+COUNTIFS('SDE Plan'!$F$6:$F$78,$B8,'SDE Plan'!$B$6:$B$78,"Yes",'SDE Plan'!$L$6:$L$78,"Done"),2,1),"")) | J8: =IF($C8="","",IF(AND(J$5>=$C8,J$5<=$D8),IF(J$5<$C8+COUNTIFS('SDE Plan'!$F$6:$F$78,$B8,'SDE Plan'!$B$6:$B$78,"Yes",'SDE Plan'!$L$6:$L$78,"Done"),2,1),"")) | K8: =IF($C8="","",IF(AND(K$5>=$C8,K$5<=$D8),IF(K$5<$C8+COUNTIFS('SDE Plan'!$F$6:$F$78,$B8,'SDE Plan'!$B$6:$B$78,"Yes",'SDE Plan'!$L$6:$L$78,"Done"),2,1),"")) | L8: =IF($C8="","",IF(AND(L$5>=$C8,L$5<=$D8),IF(L$5<$C8+COUNTIFS('SDE Plan'!$F$6:$F$78,$B8,'SDE Plan'!$B$6:$B$78,"Yes",'SDE Plan'!$L$6:$L$78,"Done"),2,1),"")) | ... AQ8: =IF($C8="","",IF(AND(AQ$5>=$C8,AQ$5<=$D8),IF(AQ$5<$C8+COUNTIFS('SDE Plan'!$F$6:$F$78,$B8,'SDE Plan'!$B$6:$B$78,"Yes",'SDE Plan'!$L$6:$L$78,"Done"),2,1),""))
A9: SDE | B9: Intermediate DSA: AI-Assisted Problem Solving | C9: =IF(COUNTIFS('SDE Plan'!$F$6:$F$78,$B9,'SDE Plan'!$B$6:$B$78,"Yes")=0,"",_xlfn.MINIFS('SDE Plan'!$A$6:$A$78,'SDE Plan'!$F$6:$F$78,$B9,'SDE Plan'!$B$6:$B$78,"Yes")) -> 1 | D9: =IF(COUNTIFS('SDE Plan'!$F$6:$F$78,$B9,'SDE Plan'!$B$6:$B$78,"Yes")=0,"",_xlfn.MAXIFS('SDE Plan'!$A$6:$A$78,'SDE Plan'!$F$6:$F$78,$B9,'SDE Plan'!$B$6:$B$78,"Yes")) -> 2 | E9: =IF($C9="","",IF(AND(E$5>=$C9,E$5<=$D9),IF(E$5<$C9+COUNTIFS('SDE Plan'!$F$6:$F$78,$B9,'SDE Plan'!$B$6:$B$78,"Yes",'SDE Plan'!$L$6:$L$78,"Done"),2,1),"")) -> 1 | F9: =IF($C9="","",IF(AND(F$5>=$C9,F$5<=$D9),IF(F$5<$C9+COUNTIFS('SDE Plan'!$F$6:$F$78,$B9,'SDE Plan'!$B$6:$B$78,"Yes",'SDE Plan'!$L$6:$L$78,"Done"),2,1),"")) -> 1 | G9: =IF($C9="","",IF(AND(G$5>=$C9,G$5<=$D9),IF(G$5<$C9+COUNTIFS('SDE Plan'!$F$6:$F$78,$B9,'SDE Plan'!$B$6:$B$78,"Yes",'SDE Plan'!$L$6:$L$78,"Done"),2,1),"")) | H9: =IF($C9="","",IF(AND(H$5>=$C9,H$5<=$D9),IF(H$5<$C9+COUNTIFS('SDE Plan'!$F$6:$F$78,$B9,'SDE Plan'!$B$6:$B$78,"Yes",'SDE Plan'!$L$6:$L$78,"Done"),2,1),"")) | I9: =IF($C9="","",IF(AND(I$5>=$C9,I$5<=$D9),IF(I$5<$C9+COUNTIFS('SDE Plan'!$F$6:$F$78,$B9,'SDE Plan'!$B$6:$B$78,"Yes",'SDE Plan'!$L$6:$L$78,"Done"),2,1),"")) | J9: =IF($C9="","",IF(AND(J$5>=$C9,J$5<=$D9),IF(J$5<$C9+COUNTIFS('SDE Plan'!$F$6:$F$78,$B9,'SDE Plan'!$B$6:$B$78,"Yes",'SDE Plan'!$L$6:$L$78,"Done"),2,1),"")) | K9: =IF($C9="","",IF(AND(K$5>=$C9,K$5<=$D9),IF(K$5<$C9+COUNTIFS('SDE Plan'!$F$6:$F$78,$B9,'SDE Plan'!$B$6:$B$78,"Yes",'SDE Plan'!$L$6:$L$78,"Done"),2,1),"")) | L9: =IF($C9="","",IF(AND(L$5>=$C9,L$5<=$D9),IF(L$5<$C9+COUNTIFS('SDE Plan'!$F$6:$F$78,$B9,'SDE Plan'!$B$6:$B$78,"Yes",'SDE Plan'!$L$6:$L$78,"Done"),2,1),"")) | ... AQ9: =IF($C9="","",IF(AND(AQ$5>=$C9,AQ$5<=$D9),IF(AQ$5<$C9+COUNTIFS('SDE Plan'!$F$6:$F$78,$B9,'SDE Plan'!$B$6:$B$78,"Yes",'SDE Plan'!$L$6:$L$78,"Done"),2,1),""))
A10: SDE | B10: Agentic AI: From Talking to AI to Building One | C10: =IF(COUNTIFS('SDE Plan'!$F$6:$F$78,$B10,'SDE Plan'!$B$6:$B$78,"Yes")=0,"",_xlfn.MINIFS('SDE Plan'!$A$6:$A$78,'SDE Plan'!$F$6:$F$78,$B10,'SDE Plan'!$B$6:$B$78,"Yes")) -> 3 | D10: =IF(COUNTIFS('SDE Plan'!$F$6:$F$78,$B10,'SDE Plan'!$B$6:$B$78,"Yes")=0,"",_xlfn.MAXIFS('SDE Plan'!$A$6:$A$78,'SDE Plan'!$F$6:$F$78,$B10,'SDE Plan'!$B$6:$B$78,"Yes")) -> 4 | E10: =IF($C10="","",IF(AND(E$5>=$C10,E$5<=$D10),IF(E$5<$C10+COUNTIFS('SDE Plan'!$F$6:$F$78,$B10,'SDE Plan'!$B$6:$B$78,"Yes",'SDE Plan'!$L$6:$L$78,"Done"),2,1),"")) | F10: =IF($C10="","",IF(AND(F$5>=$C10,F$5<=$D10),IF(F$5<$C10+COUNTIFS('SDE Plan'!$F$6:$F$78,$B10,'SDE Plan'!$B$6:$B$78,"Yes",'SDE Plan'!$L$6:$L$78,"Done"),2,1),"")) | G10: =IF($C10="","",IF(AND(G$5>=$C10,G$5<=$D10),IF(G$5<$C10+COUNTIFS('SDE Plan'!$F$6:$F$78,$B10,'SDE Plan'!$B$6:$B$78,"Yes",'SDE Plan'!$L$6:$L$78,"Done"),2,1),"")) -> 1 | H10: =IF($C10="","",IF(AND(H$5>=$C10,H$5<=$D10),IF(H$5<$C10+COUNTIFS('SDE Plan'!$F$6:$F$78,$B10,'SDE Plan'!$B$6:$B$78,"Yes",'SDE Plan'!$L$6:$L$78,"Done"),2,1),"")) -> 1 | I10: =IF($C10="","",IF(AND(I$5>=$C10,I$5<=$D10),IF(I$5<$C10+COUNTIFS('SDE Plan'!$F$6:$F$78,$B10,'SDE Plan'!$B$6:$B$78,"Yes",'SDE Plan'!$L$6:$L$78,"Done"),2,1),"")) | J10: =IF($C10="","",IF(AND(J$5>=$C10,J$5<=$D10),IF(J$5<$C10+COUNTIFS('SDE Plan'!$F$6:$F$78,$B10,'SDE Plan'!$B$6:$B$78,"Yes",'SDE Plan'!$L$6:$L$78,"Done"),2,1),"")) | K10: =IF($C10="","",IF(AND(K$5>=$C10,K$5<=$D10),IF(K$5<$C10+COUNTIFS('SDE Plan'!$F$6:$F$78,$B10,'SDE Plan'!$B$6:$B$78,"Yes",'SDE Plan'!$L$6:$L$78,"Done"),2,1),"")) | L10: =IF($C10="","",IF(AND(L$5>=$C10,L$5<=$D10),IF(L$5<$C10+COUNTIFS('SDE Plan'!$F$6:$F$78,$B10,'SDE Plan'!$B$6:$B$78,"Yes",'SDE Plan'!$L$6:$L$78,"Done"),2,1),"")) | ... AQ10: =IF($C10="","",IF(AND(AQ$5>=$C10,AQ$5<=$D10),IF(AQ$5<$C10+COUNTIFS('SDE Plan'!$F$6:$F$78,$B10,'SDE Plan'!$B$6:$B$78,"Yes",'SDE Plan'!$L$6:$L$78,"Done"),2,1),""))
A11: SDE | B11: Advanced DSA: Foundations – Core Techniques & Optimization | C11: =IF(COUNTIFS('SDE Plan'!$F$6:$F$78,$B11,'SDE Plan'!$B$6:$B$78,"Yes")=0,"",_xlfn.MINIFS('SDE Plan'!$A$6:$A$78,'SDE Plan'!$F$6:$F$78,$B11,'SDE Plan'!$B$6:$B$78,"Yes")) -> 5 | D11: =IF(COUNTIFS('SDE Plan'!$F$6:$F$78,$B11,'SDE Plan'!$B$6:$B$78,"Yes")=0,"",_xlfn.MAXIFS('SDE Plan'!$A$6:$A$78,'SDE Plan'!$F$6:$F$78,$B11,'SDE Plan'!$B$6:$B$78,"Yes")) -> 7 | E11: =IF($C11="","",IF(AND(E$5>=$C11,E$5<=$D11),IF(E$5<$C11+COUNTIFS('SDE Plan'!$F$6:$F$78,$B11,'SDE Plan'!$B$6:$B$78,"Yes",'SDE Plan'!$L$6:$L$78,"Done"),2,1),"")) | F11: =IF($C11="","",IF(AND(F$5>=$C11,F$5<=$D11),IF(F$5<$C11+COUNTIFS('SDE Plan'!$F$6:$F$78,$B11,'SDE Plan'!$B$6:$B$78,"Yes",'SDE Plan'!$L$6:$L$78,"Done"),2,1),"")) | G11: =IF($C11="","",IF(AND(G$5>=$C11,G$5<=$D11),IF(G$5<$C11+COUNTIFS('SDE Plan'!$F$6:$F$78,$B11,'SDE Plan'!$B$6:$B$78,"Yes",'SDE Plan'!$L$6:$L$78,"Done"),2,1),"")) | H11: =IF($C11="","",IF(AND(H$5>=$C11,H$5<=$D11),IF(H$5<$C11+COUNTIFS('SDE Plan'!$F$6:$F$78,$B11,'SDE Plan'!$B$6:$B$78,"Yes",'SDE Plan'!$L$6:$L$78,"Done"),2,1),"")) | I11: =IF($C11="","",IF(AND(I$5>=$C11,I$5<=$D11),IF(I$5<$C11+COUNTIFS('SDE Plan'!$F$6:$F$78,$B11,'SDE Plan'!$B$6:$B$78,"Yes",'SDE Plan'!$L$6:$L$78,"Done"),2,1),"")) -> 1 | J11: =IF($C11="","",IF(AND(J$5>=$C11,J$5<=$D11),IF(J$5<$C11+COUNTIFS('SDE Plan'!$F$6:$F$78,$B11,'SDE Plan'!$B$6:$B$78,"Yes",'SDE Plan'!$L$6:$L$78,"Done"),2,1),"")) -> 1 | K11: =IF($C11="","",IF(AND(K$5>=$C11,K$5<=$D11),IF(K$5<$C11+COUNTIFS('SDE Plan'!$F$6:$F$78,$B11,'SDE Plan'!$B$6:$B$78,"Yes",'SDE Plan'!$L$6:$L$78,"Done"),2,1),"")) -> 1 | L11: =IF($C11="","",IF(AND(L$5>=$C11,L$5<=$D11),IF(L$5<$C11+COUNTIFS('SDE Plan'!$F$6:$F$78,$B11,'SDE Plan'!$B$6:$B$78,"Yes",'SDE Plan'!$L$6:$L$78,"Done"),2,1),"")) | ... AQ11: =IF($C11="","",IF(AND(AQ$5>=$C11,AQ$5<=$D11),IF(AQ$5<$C11+COUNTIFS('SDE Plan'!$F$6:$F$78,$B11,'SDE Plan'!$B$6:$B$78,"Yes",'SDE Plan'!$L$6:$L$78,"Done"),2,1),""))
A12: SDE | B12: Advanced DSA: Linear & Non-Linear Structures | C12: =IF(COUNTIFS('SDE Plan'!$F$6:$F$78,$B12,'SDE Plan'!$B$6:$B$78,"Yes")=0,"",_xlfn.MINIFS('SDE Plan'!$A$6:$A$78,'SDE Plan'!$F$6:$F$78,$B12,'SDE Plan'!$B$6:$B$78,"Yes")) -> 8 | D12: =IF(COUNTIFS('SDE Plan'!$F$6:$F$78,$B12,'SDE Plan'!$B$6:$B$78,"Yes")=0,"",_xlfn.MAXIFS('SDE Plan'!$A$6:$A$78,'SDE Plan'!$F$6:$F$78,$B12,'SDE Plan'!$B$6:$B$78,"Yes")) -> 10 | E12: =IF($C12="","",IF(AND(E$5>=$C12,E$5<=$D12),IF(E$5<$C12+COUNTIFS('SDE Plan'!$F$6:$F$78,$B12,'SDE Plan'!$B$6:$B$78,"Yes",'SDE Plan'!$L$6:$L$78,"Done"),2,1),"")) | F12: =IF($C12="","",IF(AND(F$5>=$C12,F$5<=$D12),IF(F$5<$C12+COUNTIFS('SDE Plan'!$F$6:$F$78,$B12,'SDE Plan'!$B$6:$B$78,"Yes",'SDE Plan'!$L$6:$L$78,"Done"),2,1),"")) | G12: =IF($C12="","",IF(AND(G$5>=$C12,G$5<=$D12),IF(G$5<$C12+COUNTIFS('SDE Plan'!$F$6:$F$78,$B12,'SDE Plan'!$B$6:$B$78,"Yes",'SDE Plan'!$L$6:$L$78,"Done"),2,1),"")) | H12: =IF($C12="","",IF(AND(H$5>=$C12,H$5<=$D12),IF(H$5<$C12+COUNTIFS('SDE Plan'!$F$6:$F$78,$B12,'SDE Plan'!$B$6:$B$78,"Yes",'SDE Plan'!$L$6:$L$78,"Done"),2,1),"")) | I12: =IF($C12="","",IF(AND(I$5>=$C12,I$5<=$D12),IF(I$5<$C12+COUNTIFS('SDE Plan'!$F$6:$F$78,$B12,'SDE Plan'!$B$6:$B$78,"Yes",'SDE Plan'!$L$6:$L$78,"Done"),2,1),"")) | J12: =IF($C12="","",IF(AND(J$5>=$C12,J$5<=$D12),IF(J$5<$C12+COUNTIFS('SDE Plan'!$F$6:$F$78,$B12,'SDE Plan'!$B$6:$B$78,"Yes",'SDE Plan'!$L$6:$L$78,"Done"),2,1),"")) | K12: =IF($C12="","",IF(AND(K$5>=$C12,K$5<=$D12),IF(K$5<$C12+COUNTIFS('SDE Plan'!$F$6:$F$78,$B12,'SDE Plan'!$B$6:$B$78,"Yes",'SDE Plan'!$L$6:$L$78,"Done"),2,1),"")) | L12: =IF($C12="","",IF(AND(L$5>=$C12,L$5<=$D12),IF(L$5<$C12+COUNTIFS('SDE Plan'!$F$6:$F$78,$B12,'SDE Plan'!$B$6:$B$78,"Yes",'SDE Plan'!$L$6:$L$78,"Done"),2,1),"")) -> 1 | ... AQ12: =IF($C12="","",IF(AND(AQ$5>=$C12,AQ$5<=$D12),IF(AQ$5<$C12+COUNTIFS('SDE Plan'!$F$6:$F$78,$B12,'SDE Plan'!$B$6:$B$78,"Yes",'SDE Plan'!$L$6:$L$78,"Done"),2,1),""))
A13: SDE | B13: Advanced DSA: Backtracking & Advanced Trees | C13: =IF(COUNTIFS('SDE Plan'!$F$6:$F$78,$B13,'SDE Plan'!$B$6:$B$78,"Yes")=0,"",_xlfn.MINIFS('SDE Plan'!$A$6:$A$78,'SDE Plan'!$F$6:$F$78,$B13,'SDE Plan'!$B$6:$B$78,"Yes")) -> 11 | D13: =IF(COUNTIFS('SDE Plan'!$F$6:$F$78,$B13,'SDE Plan'!$B$6:$B$78,"Yes")=0,"",_xlfn.MAXIFS('SDE Plan'!$A$6:$A$78,'SDE Plan'!$F$6:$F$78,$B13,'SDE Plan'!$B$6:$B$78,"Yes")) -> 13 | E13: =IF($C13="","",IF(AND(E$5>=$C13,E$5<=$D13),IF(E$5<$C13+COUNTIFS('SDE Plan'!$F$6:$F$78,$B13,'SDE Plan'!$B$6:$B$78,"Yes",'SDE Plan'!$L$6:$L$78,"Done"),2,1),"")) | F13: =IF($C13="","",IF(AND(F$5>=$C13,F$5<=$D13),IF(F$5<$C13+COUNTIFS('SDE Plan'!$F$6:$F$78,$B13,'SDE Plan'!$B$6:$B$78,"Yes",'SDE Plan'!$L$6:$L$78,"Done"),2,1),"")) | G13: =IF($C13="","",IF(AND(G$5>=$C13,G$5<=$D13),IF(G$5<$C13+COUNTIFS('SDE Plan'!$F$6:$F$78,$B13,'SDE Plan'!$B$6:$B$78,"Yes",'SDE Plan'!$L$6:$L$78,"Done"),2,1),"")) | H13: =IF($C13="","",IF(AND(H$5>=$C13,H$5<=$D13),IF(H$5<$C13+COUNTIFS('SDE Plan'!$F$6:$F$78,$B13,'SDE Plan'!$B$6:$B$78,"Yes",'SDE Plan'!$L$6:$L$78,"Done"),2,1),"")) | I13: =IF($C13="","",IF(AND(I$5>=$C13,I$5<=$D13),IF(I$5<$C13+COUNTIFS('SDE Plan'!$F$6:$F$78,$B13,'SDE Plan'!$B$6:$B$78,"Yes",'SDE Plan'!$L$6:$L$78,"Done"),2,1),"")) | J13: =IF($C13="","",IF(AND(J$5>=$C13,J$5<=$D13),IF(J$5<$C13+COUNTIFS('SDE Plan'!$F$6:$F$78,$B13,'SDE Plan'!$B$6:$B$78,"Yes",'SDE Plan'!$L$6:$L$78,"Done"),2,1),"")) | K13: =IF($C13="","",IF(AND(K$5>=$C13,K$5<=$D13),IF(K$5<$C13+COUNTIFS('SDE Plan'!$F$6:$F$78,$B13,'SDE Plan'!$B$6:$B$78,"Yes",'SDE Plan'!$L$6:$L$78,"Done"),2,1),"")) | L13: =IF($C13="","",IF(AND(L$5>=$C13,L$5<=$D13),IF(L$5<$C13+COUNTIFS('SDE Plan'!$F$6:$F$78,$B13,'SDE Plan'!$B$6:$B$78,"Yes",'SDE Plan'!$L$6:$L$78,"Done"),2,1),"")) | ... AQ13: =IF($C13="","",IF(AND(AQ$5>=$C13,AQ$5<=$D13),IF(AQ$5<$C13+COUNTIFS('SDE Plan'!$F$6:$F$78,$B13,'SDE Plan'!$B$6:$B$78,"Yes",'SDE Plan'!$L$6:$L$78,"Done"),2,1),""))
A14: SDE | B14: Advanced DSA: DP, Heaps & Graphs – Crack It with AI Edge | C14: =IF(COUNTIFS('SDE Plan'!$F$6:$F$78,$B14,'SDE Plan'!$B$6:$B$78,"Yes")=0,"",_xlfn.MINIFS('SDE Plan'!$A$6:$A$78,'SDE Plan'!$F$6:$F$78,$B14,'SDE Plan'!$B$6:$B$78,"Yes")) -> 14 | D14: =IF(COUNTIFS('SDE Plan'!$F$6:$F$78,$B14,'SDE Plan'!$B$6:$B$78,"Yes")=0,"",_xlfn.MAXIFS('SDE Plan'!$A$6:$A$78,'SDE Plan'!$F$6:$F$78,$B14,'SDE Plan'!$B$6:$B$78,"Yes")) -> 17 | E14: =IF($C14="","",IF(AND(E$5>=$C14,E$5<=$D14),IF(E$5<$C14+COUNTIFS('SDE Plan'!$F$6:$F$78,$B14,'SDE Plan'!$B$6:$B$78,"Yes",'SDE Plan'!$L$6:$L$78,"Done"),2,1),"")) | F14: =IF($C14="","",IF(AND(F$5>=$C14,F$5<=$D14),IF(F$5<$C14+COUNTIFS('SDE Plan'!$F$6:$F$78,$B14,'SDE Plan'!$B$6:$B$78,"Yes",'SDE Plan'!$L$6:$L$78,"Done"),2,1),"")) | G14: =IF($C14="","",IF(AND(G$5>=$C14,G$5<=$D14),IF(G$5<$C14+COUNTIFS('SDE Plan'!$F$6:$F$78,$B14,'SDE Plan'!$B$6:$B$78,"Yes",'SDE Plan'!$L$6:$L$78,"Done"),2,1),"")) | H14: =IF($C14="","",IF(AND(H$5>=$C14,H$5<=$D14),IF(H$5<$C14+COUNTIFS('SDE Plan'!$F$6:$F$78,$B14,'SDE Plan'!$B$6:$B$78,"Yes",'SDE Plan'!$L$6:$L$78,"Done"),2,1),"")) | I14: =IF($C14="","",IF(AND(I$5>=$C14,I$5<=$D14),IF(I$5<$C14+COUNTIFS('SDE Plan'!$F$6:$F$78,$B14,'SDE Plan'!$B$6:$B$78,"Yes",'SDE Plan'!$L$6:$L$78,"Done"),2,1),"")) | J14: =IF($C14="","",IF(AND(J$5>=$C14,J$5<=$D14),IF(J$5<$C14+COUNTIFS('SDE Plan'!$F$6:$F$78,$B14,'SDE Plan'!$B$6:$B$78,"Yes",'SDE Plan'!$L$6:$L$78,"Done"),2,1),"")) | K14: =IF($C14="","",IF(AND(K$5>=$C14,K$5<=$D14),IF(K$5<$C14+COUNTIFS('SDE Plan'!$F$6:$F$78,$B14,'SDE Plan'!$B$6:$B$78,"Yes",'SDE Plan'!$L$6:$L$78,"Done"),2,1),"")) | L14: =IF($C14="","",IF(AND(L$5>=$C14,L$5<=$D14),IF(L$5<$C14+COUNTIFS('SDE Plan'!$F$6:$F$78,$B14,'SDE Plan'!$B$6:$B$78,"Yes",'SDE Plan'!$L$6:$L$78,"Done"),2,1),"")) | ... AQ14: =IF($C14="","",IF(AND(AQ$5>=$C14,AQ$5<=$D14),IF(AQ$5<$C14+COUNTIFS('SDE Plan'!$F$6:$F$78,$B14,'SDE Plan'!$B$6:$B$78,"Yes",'SDE Plan'!$L$6:$L$78,"Done"),2,1),""))
A15: SDE | B15: Databases & SQL | C15: =IF(COUNTIFS('SDE Plan'!$F$6:$F$78,$B15,'SDE Plan'!$B$6:$B$78,"Yes")=0,"",_xlfn.MINIFS('SDE Plan'!$A$6:$A$78,'SDE Plan'!$F$6:$F$78,$B15,'SDE Plan'!$B$6:$B$78,"Yes")) -> 18 | D15: =IF(COUNTIFS('SDE Plan'!$F$6:$F$78,$B15,'SDE Plan'!$B$6:$B$78,"Yes")=0,"",_xlfn.MAXIFS('SDE Plan'!$A$6:$A$78,'SDE Plan'!$F$6:$F$78,$B15,'SDE Plan'!$B$6:$B$78,"Yes")) -> 19 | E15: =IF($C15="","",IF(AND(E$5>=$C15,E$5<=$D15),IF(E$5<$C15+COUNTIFS('SDE Plan'!$F$6:$F$78,$B15,'SDE Plan'!$B$6:$B$78,"Yes",'SDE Plan'!$L$6:$L$78,"Done"),2,1),"")) | F15: =IF($C15="","",IF(AND(F$5>=$C15,F$5<=$D15),IF(F$5<$C15+COUNTIFS('SDE Plan'!$F$6:$F$78,$B15,'SDE Plan'!$B$6:$B$78,"Yes",'SDE Plan'!$L$6:$L$78,"Done"),2,1),"")) | G15: =IF($C15="","",IF(AND(G$5>=$C15,G$5<=$D15),IF(G$5<$C15+COUNTIFS('SDE Plan'!$F$6:$F$78,$B15,'SDE Plan'!$B$6:$B$78,"Yes",'SDE Plan'!$L$6:$L$78,"Done"),2,1),"")) | H15: =IF($C15="","",IF(AND(H$5>=$C15,H$5<=$D15),IF(H$5<$C15+COUNTIFS('SDE Plan'!$F$6:$F$78,$B15,'SDE Plan'!$B$6:$B$78,"Yes",'SDE Plan'!$L$6:$L$78,"Done"),2,1),"")) | I15: =IF($C15="","",IF(AND(I$5>=$C15,I$5<=$D15),IF(I$5<$C15+COUNTIFS('SDE Plan'!$F$6:$F$78,$B15,'SDE Plan'!$B$6:$B$78,"Yes",'SDE Plan'!$L$6:$L$78,"Done"),2,1),"")) | J15: =IF($C15="","",IF(AND(J$5>=$C15,J$5<=$D15),IF(J$5<$C15+COUNTIFS('SDE Plan'!$F$6:$F$78,$B15,'SDE Plan'!$B$6:$B$78,"Yes",'SDE Plan'!$L$6:$L$78,"Done"),2,1),"")) | K15: =IF($C15="","",IF(AND(K$5>=$C15,K$5<=$D15),IF(K$5<$C15+COUNTIFS('SDE Plan'!$F$6:$F$78,$B15,'SDE Plan'!$B$6:$B$78,"Yes",'SDE Plan'!$L$6:$L$78,"Done"),2,1),"")) | L15: =IF($C15="","",IF(AND(L$5>=$C15,L$5<=$D15),IF(L$5<$C15+COUNTIFS('SDE Plan'!$F$6:$F$78,$B15,'SDE Plan'!$B$6:$B$78,"Yes",'SDE Plan'!$L$6:$L$78,"Done"),2,1),"")) | ... AQ15: =IF($C15="","",IF(AND(AQ$5>=$C15,AQ$5<=$D15),IF(AQ$5<$C15+COUNTIFS('SDE Plan'!$F$6:$F$78,$B15,'SDE Plan'!$B$6:$B$78,"Yes",'SDE Plan'!$L$6:$L$78,"Done"),2,1),""))
A16: SDE | B16: Foundations of Object-Oriented Design & Scalable Systems | C16: =IF(COUNTIFS('SDE Plan'!$F$6:$F$78,$B16,'SDE Plan'!$B$6:$B$78,"Yes")=0,"",_xlfn.MINIFS('SDE Plan'!$A$6:$A$78,'SDE Plan'!$F$6:$F$78,$B16,'SDE Plan'!$B$6:$B$78,"Yes")) -> 20 | D16: =IF(COUNTIFS('SDE Plan'!$F$6:$F$78,$B16,'SDE Plan'!$B$6:$B$78,"Yes")=0,"",_xlfn.MAXIFS('SDE Plan'!$A$6:$A$78,'SDE Plan'!$F$6:$F$78,$B16,'SDE Plan'!$B$6:$B$78,"Yes")) -> 22 | E16: =IF($C16="","",IF(AND(E$5>=$C16,E$5<=$D16),IF(E$5<$C16+COUNTIFS('SDE Plan'!$F$6:$F$78,$B16,'SDE Plan'!$B$6:$B$78,"Yes",'SDE Plan'!$L$6:$L$78,"Done"),2,1),"")) | F16: =IF($C16="","",IF(AND(F$5>=$C16,F$5<=$D16),IF(F$5<$C16+COUNTIFS('SDE Plan'!$F$6:$F$78,$B16,'SDE Plan'!$B$6:$B$78,"Yes",'SDE Plan'!$L$6:$L$78,"Done"),2,1),"")) | G16: =IF($C16="","",IF(AND(G$5>=$C16,G$5<=$D16),IF(G$5<$C16+COUNTIFS('SDE Plan'!$F$6:$F$78,$B16,'SDE Plan'!$B$6:$B$78,"Yes",'SDE Plan'!$L$6:$L$78,"Done"),2,1),"")) | H16: =IF($C16="","",IF(AND(H$5>=$C16,H$5<=$D16),IF(H$5<$C16+COUNTIFS('SDE Plan'!$F$6:$F$78,$B16,'SDE Plan'!$B$6:$B$78,"Yes",'SDE Plan'!$L$6:$L$78,"Done"),2,1),"")) | I16: =IF($C16="","",IF(AND(I$5>=$C16,I$5<=$D16),IF(I$5<$C16+COUNTIFS('SDE Plan'!$F$6:$F$78,$B16,'SDE Plan'!$B$6:$B$78,"Yes",'SDE Plan'!$L$6:$L$78,"Done"),2,1),"")) | J16: =IF($C16="","",IF(AND(J$5>=$C16,J$5<=$D16),IF(J$5<$C16+COUNTIFS('SDE Plan'!$F$6:$F$78,$B16,'SDE Plan'!$B$6:$B$78,"Yes",'SDE Plan'!$L$6:$L$78,"Done"),2,1),"")) | K16: =IF($C16="","",IF(AND(K$5>=$C16,K$5<=$D16),IF(K$5<$C16+COUNTIFS('SDE Plan'!$F$6:$F$78,$B16,'SDE Plan'!$B$6:$B$78,"Yes",'SDE Plan'!$L$6:$L$78,"Done"),2,1),"")) | L16: =IF($C16="","",IF(AND(L$5>=$C16,L$5<=$D16),IF(L$5<$C16+COUNTIFS('SDE Plan'!$F$6:$F$78,$B16,'SDE Plan'!$B$6:$B$78,"Yes",'SDE Plan'!$L$6:$L$78,"Done"),2,1),"")) | ... AQ16: =IF($C16="","",IF(AND(AQ$5>=$C16,AQ$5<=$D16),IF(AQ$5<$C16+COUNTIFS('SDE Plan'!$F$6:$F$78,$B16,'SDE Plan'!$B$6:$B$78,"Yes",'SDE Plan'!$L$6:$L$78,"Done"),2,1),""))
A17: SDE | B17: Design Principles & Patterns for Extensible Systems | C17: =IF(COUNTIFS('SDE Plan'!$F$6:$F$78,$B17,'SDE Plan'!$B$6:$B$78,"Yes")=0,"",_xlfn.MINIFS('SDE Plan'!$A$6:$A$78,'SDE Plan'!$F$6:$F$78,$B17,'SDE Plan'!$B$6:$B$78,"Yes")) -> 23 | D17: =IF(COUNTIFS('SDE Plan'!$F$6:$F$78,$B17,'SDE Plan'!$B$6:$B$78,"Yes")=0,"",_xlfn.MAXIFS('SDE Plan'!$A$6:$A$78,'SDE Plan'!$F$6:$F$78,$B17,'SDE Plan'!$B$6:$B$78,"Yes")) -> 24 | E17: =IF($C17="","",IF(AND(E$5>=$C17,E$5<=$D17),IF(E$5<$C17+COUNTIFS('SDE Plan'!$F$6:$F$78,$B17,'SDE Plan'!$B$6:$B$78,"Yes",'SDE Plan'!$L$6:$L$78,"Done"),2,1),"")) | F17: =IF($C17="","",IF(AND(F$5>=$C17,F$5<=$D17),IF(F$5<$C17+COUNTIFS('SDE Plan'!$F$6:$F$78,$B17,'SDE Plan'!$B$6:$B$78,"Yes",'SDE Plan'!$L$6:$L$78,"Done"),2,1),"")) | G17: =IF($C17="","",IF(AND(G$5>=$C17,G$5<=$D17),IF(G$5<$C17+COUNTIFS('SDE Plan'!$F$6:$F$78,$B17,'SDE Plan'!$B$6:$B$78,"Yes",'SDE Plan'!$L$6:$L$78,"Done"),2,1),"")) | H17: =IF($C17="","",IF(AND(H$5>=$C17,H$5<=$D17),IF(H$5<$C17+COUNTIFS('SDE Plan'!$F$6:$F$78,$B17,'SDE Plan'!$B$6:$B$78,"Yes",'SDE Plan'!$L$6:$L$78,"Done"),2,1),"")) | I17: =IF($C17="","",IF(AND(I$5>=$C17,I$5<=$D17),IF(I$5<$C17+COUNTIFS('SDE Plan'!$F$6:$F$78,$B17,'SDE Plan'!$B$6:$B$78,"Yes",'SDE Plan'!$L$6:$L$78,"Done"),2,1),"")) | J17: =IF($C17="","",IF(AND(J$5>=$C17,J$5<=$D17),IF(J$5<$C17+COUNTIFS('SDE Plan'!$F$6:$F$78,$B17,'SDE Plan'!$B$6:$B$78,"Yes",'SDE Plan'!$L$6:$L$78,"Done"),2,1),"")) | K17: =IF($C17="","",IF(AND(K$5>=$C17,K$5<=$D17),IF(K$5<$C17+COUNTIFS('SDE Plan'!$F$6:$F$78,$B17,'SDE Plan'!$B$6:$B$78,"Yes",'SDE Plan'!$L$6:$L$78,"Done"),2,1),"")) | L17: =IF($C17="","",IF(AND(L$5>=$C17,L$5<=$D17),IF(L$5<$C17+COUNTIFS('SDE Plan'!$F$6:$F$78,$B17,'SDE Plan'!$B$6:$B$78,"Yes",'SDE Plan'!$L$6:$L$78,"Done"),2,1),"")) | ... AQ17: =IF($C17="","",IF(AND(AQ$5>=$C17,AQ$5<=$D17),IF(AQ$5<$C17+COUNTIFS('SDE Plan'!$F$6:$F$78,$B17,'SDE Plan'!$B$6:$B$78,"Yes",'SDE Plan'!$L$6:$L$78,"Done"),2,1),""))
A18: SDE | B18: Applied Design & Machine Coding | C18: =IF(COUNTIFS('SDE Plan'!$F$6:$F$78,$B18,'SDE Plan'!$B$6:$B$78,"Yes")=0,"",_xlfn.MINIFS('SDE Plan'!$A$6:$A$78,'SDE Plan'!$F$6:$F$78,$B18,'SDE Plan'!$B$6:$B$78,"Yes")) -> 25 | D18: =IF(COUNTIFS('SDE Plan'!$F$6:$F$78,$B18,'SDE Plan'!$B$6:$B$78,"Yes")=0,"",_xlfn.MAXIFS('SDE Plan'!$A$6:$A$78,'SDE Plan'!$F$6:$F$78,$B18,'SDE Plan'!$B$6:$B$78,"Yes")) -> 27 | E18: =IF($C18="","",IF(AND(E$5>=$C18,E$5<=$D18),IF(E$5<$C18+COUNTIFS('SDE Plan'!$F$6:$F$78,$B18,'SDE Plan'!$B$6:$B$78,"Yes",'SDE Plan'!$L$6:$L$78,"Done"),2,1),"")) | F18: =IF($C18="","",IF(AND(F$5>=$C18,F$5<=$D18),IF(F$5<$C18+COUNTIFS('SDE Plan'!$F$6:$F$78,$B18,'SDE Plan'!$B$6:$B$78,"Yes",'SDE Plan'!$L$6:$L$78,"Done"),2,1),"")) | G18: =IF($C18="","",IF(AND(G$5>=$C18,G$5<=$D18),IF(G$5<$C18+COUNTIFS('SDE Plan'!$F$6:$F$78,$B18,'SDE Plan'!$B$6:$B$78,"Yes",'SDE Plan'!$L$6:$L$78,"Done"),2,1),"")) | H18: =IF($C18="","",IF(AND(H$5>=$C18,H$5<=$D18),IF(H$5<$C18+COUNTIFS('SDE Plan'!$F$6:$F$78,$B18,'SDE Plan'!$B$6:$B$78,"Yes",'SDE Plan'!$L$6:$L$78,"Done"),2,1),"")) | I18: =IF($C18="","",IF(AND(I$5>=$C18,I$5<=$D18),IF(I$5<$C18+COUNTIFS('SDE Plan'!$F$6:$F$78,$B18,'SDE Plan'!$B$6:$B$78,"Yes",'SDE Plan'!$L$6:$L$78,"Done"),2,1),"")) | J18: =IF($C18="","",IF(AND(J$5>=$C18,J$5<=$D18),IF(J$5<$C18+COUNTIFS('SDE Plan'!$F$6:$F$78,$B18,'SDE Plan'!$B$6:$B$78,"Yes",'SDE Plan'!$L$6:$L$78,"Done"),2,1),"")) | K18: =IF($C18="","",IF(AND(K$5>=$C18,K$5<=$D18),IF(K$5<$C18+COUNTIFS('SDE Plan'!$F$6:$F$78,$B18,'SDE Plan'!$B$6:$B$78,"Yes",'SDE Plan'!$L$6:$L$78,"Done"),2,1),"")) | L18: =IF($C18="","",IF(AND(L$5>=$C18,L$5<=$D18),IF(L$5<$C18+COUNTIFS('SDE Plan'!$F$6:$F$78,$B18,'SDE Plan'!$B$6:$B$78,"Yes",'SDE Plan'!$L$6:$L$78,"Done"),2,1),"")) | ... AQ18: =IF($C18="","",IF(AND(AQ$5>=$C18,AQ$5<=$D18),IF(AQ$5<$C18+COUNTIFS('SDE Plan'!$F$6:$F$78,$B18,'SDE Plan'!$B$6:$B$78,"Yes",'SDE Plan'!$L$6:$L$78,"Done"),2,1),""))
... A27: SDE | B27: Product Management for Engineers | C27: =IF(COUNTIFS('SDE Plan'!$F$6:$F$78,$B27,'SDE Plan'!$B$6:$B$78,"Yes")=0,"",_xlfn.MINIFS('SDE Plan'!$A$6:$A$78,'SDE Plan'!$F$6:$F$78,$B27,'SDE Plan'!$B$6:$B$78,"Yes")) | D27: =IF(COUNTIFS('SDE Plan'!$F$6:$F$78,$B27,'SDE Plan'!$B$6:$B$78,"Yes")=0,"",_xlfn.MAXIFS('SDE Plan'!$A$6:$A$78,'SDE Plan'!$F$6:$F$78,$B27,'SDE Plan'!$B$6:$B$78,"Yes")) | E27: =IF($C27="","",IF(AND(E$5>=$C27,E$5<=$D27),IF(E$5<$C27+COUNTIFS('SDE Plan'!$F$6:$F$78,$B27,'SDE Plan'!$B$6:$B$78,"Yes",'SDE Plan'!$L$6:$L$78,"Done"),2,1),"")) | F27: =IF($C27="","",IF(AND(F$5>=$C27,F$5<=$D27),IF(F$5<$C27+COUNTIFS('SDE Plan'!$F$6:$F$78,$B27,'SDE Plan'!$B$6:$B$78,"Yes",'SDE Plan'!$L$6:$L$78,"Done"),2,1),"")) | G27: =IF($C27="","",IF(AND(G$5>=$C27,G$5<=$D27),IF(G$5<$C27+COUNTIFS('SDE Plan'!$F$6:$F$78,$B27,'SDE Plan'!$B$6:$B$78,"Yes",'SDE Plan'!$L$6:$L$78,"Done"),2,1),"")) | H27: =IF($C27="","",IF(AND(H$5>=$C27,H$5<=$D27),IF(H$5<$C27+COUNTIFS('SDE Plan'!$F$6:$F$78,$B27,'SDE Plan'!$B$6:$B$78,"Yes",'SDE Plan'!$L$6:$L$78,"Done"),2,1),"")) | I27: =IF($C27="","",IF(AND(I$5>=$C27,I$5<=$D27),IF(I$5<$C27+COUNTIFS('SDE Plan'!$F$6:$F$78,$B27,'SDE Plan'!$B$6:$B$78,"Yes",'SDE Plan'!$L$6:$L$78,"Done"),2,1),"")) | J27: =IF($C27="","",IF(AND(J$5>=$C27,J$5<=$D27),IF(J$5<$C27+COUNTIFS('SDE Plan'!$F$6:$F$78,$B27,'SDE Plan'!$B$6:$B$78,"Yes",'SDE Plan'!$L$6:$L$78,"Done"),2,1),"")) | K27: =IF($C27="","",IF(AND(K$5>=$C27,K$5<=$D27),IF(K$5<$C27+COUNTIFS('SDE Plan'!$F$6:$F$78,$B27,'SDE Plan'!$B$6:$B$78,"Yes",'SDE Plan'!$L$6:$L$78,"Done"),2,1),"")) | L27: =IF($C27="","",IF(AND(L$5>=$C27,L$5<=$D27),IF(L$5<$C27+COUNTIFS('SDE Plan'!$F$6:$F$78,$B27,'SDE Plan'!$B$6:$B$78,"Yes",'SDE Plan'!$L$6:$L$78,"Done"),2,1),"")) | ... AQ27: =IF($C27="","",IF(AND(AQ$5>=$C27,AQ$5<=$D27),IF(AQ$5<$C27+COUNTIFS('SDE Plan'!$F$6:$F$78,$B27,'SDE Plan'!$B$6:$B$78,"Yes",'SDE Plan'!$L$6:$L$78,"Done"),2,1),""))
A29: 🌐 FULL-STACK TRACK
A30: Full-Stack | B30: HTML & CSS Foundations | C30: =IF(COUNTIFS('FullStack Plan'!$F$6:$F$78,$B30,'FullStack Plan'!$B$6:$B$78,"Yes")=0,"",_xlfn.MINIFS('FullStack Plan'!$A$6:$A$78,'FullStack Plan'!$F$6:$F$78,$B30,'FullStack Plan'!$B$6:$B$78,"Yes")) -> 1 | D30: =IF(COUNTIFS('FullStack Plan'!$F$6:$F$78,$B30,'FullStack Plan'!$B$6:$B$78,"Yes")=0,"",_xlfn.MAXIFS('FullStack Plan'!$A$6:$A$78,'FullStack Plan'!$F$6:$F$78,$B30,'FullStack Plan'!$B$6:$B$78,"Yes")) -> 2 | E30: =IF($C30="","",IF(AND(E$5>=$C30,E$5<=$D30),IF(E$5<$C30+COUNTIFS('FullStack Plan'!$F$6:$F$78,$B30,'FullStack Plan'!$B$6:$B$78,"Yes",'FullStack Plan'!$L$6:$L$78,"Done"),2,1),"")) -> 1 | F30: =IF($C30="","",IF(AND(F$5>=$C30,F$5<=$D30),IF(F$5<$C30+COUNTIFS('FullStack Plan'!$F$6:$F$78,$B30,'FullStack Plan'!$B$6:$B$78,"Yes",'FullStack Plan'!$L$6:$L$78,"Done"),2,1),"")) -> 1 | G30: =IF($C30="","",IF(AND(G$5>=$C30,G$5<=$D30),IF(G$5<$C30+COUNTIFS('FullStack Plan'!$F$6:$F$78,$B30,'FullStack Plan'!$B$6:$B$78,"Yes",'FullStack Plan'!$L$6:$L$78,"Done"),2,1),"")) | H30: =IF($C30="","",IF(AND(H$5>=$C30,H$5<=$D30),IF(H$5<$C30+COUNTIFS('FullStack Plan'!$F$6:$F$78,$B30,'FullStack Plan'!$B$6:$B$78,"Yes",'FullStack Plan'!$L$6:$L$78,"Done"),2,1),"")) | I30: =IF($C30="","",IF(AND(I$5>=$C30,I$5<=$D30),IF(I$5<$C30+COUNTIFS('FullStack Plan'!$F$6:$F$78,$B30,'FullStack Plan'!$B$6:$B$78,"Yes",'FullStack Plan'!$L$6:$L$78,"Done"),2,1),"")) | J30: =IF($C30="","",IF(AND(J$5>=$C30,J$5<=$D30),IF(J$5<$C30+COUNTIFS('FullStack Plan'!$F$6:$F$78,$B30,'FullStack Plan'!$B$6:$B$78,"Yes",'FullStack Plan'!$L$6:$L$78,"Done"),2,1),"")) | K30: =IF($C30="","",IF(AND(K$5>=$C30,K$5<=$D30),IF(K$5<$C30+COUNTIFS('FullStack Plan'!$F$6:$F$78,$B30,'FullStack Plan'!$B$6:$B$78,"Yes",'FullStack Plan'!$L$6:$L$78,"Done"),2,1),"")) | L30: =IF($C30="","",IF(AND(L$5>=$C30,L$5<=$D30),IF(L$5<$C30+COUNTIFS('FullStack Plan'!$F$6:$F$78,$B30,'FullStack Plan'!$B$6:$B$78,"Yes",'FullStack Plan'!$L$6:$L$78,"Done"),2,1),"")) | ... AQ30: =IF($C30="","",IF(AND(AQ$5>=$C30,AQ$5<=$D30),IF(AQ$5<$C30+COUNTIFS('FullStack Plan'!$F$6:$F$78,$B30,'FullStack Plan'!$B$6:$B$78,"Yes",'FullStack Plan'!$L$6:$L$78,"Done"),2,1),""))
A31: Full-Stack | B31: Bootstrap (supplementary) | C31: =IF(COUNTIFS('FullStack Plan'!$F$6:$F$78,$B31,'FullStack Plan'!$B$6:$B$78,"Yes")=0,"",_xlfn.MINIFS('FullStack Plan'!$A$6:$A$78,'FullStack Plan'!$F$6:$F$78,$B31,'FullStack Plan'!$B$6:$B$78,"Yes")) | D31: =IF(COUNTIFS('FullStack Plan'!$F$6:$F$78,$B31,'FullStack Plan'!$B$6:$B$78,"Yes")=0,"",_xlfn.MAXIFS('FullStack Plan'!$A$6:$A$78,'FullStack Plan'!$F$6:$F$78,$B31,'FullStack Plan'!$B$6:$B$78,"Yes")) | E31: =IF($C31="","",IF(AND(E$5>=$C31,E$5<=$D31),IF(E$5<$C31+COUNTIFS('FullStack Plan'!$F$6:$F$78,$B31,'FullStack Plan'!$B$6:$B$78,"Yes",'FullStack Plan'!$L$6:$L$78,"Done"),2,1),"")) | F31: =IF($C31="","",IF(AND(F$5>=$C31,F$5<=$D31),IF(F$5<$C31+COUNTIFS('FullStack Plan'!$F$6:$F$78,$B31,'FullStack Plan'!$B$6:$B$78,"Yes",'FullStack Plan'!$L$6:$L$78,"Done"),2,1),"")) | G31: =IF($C31="","",IF(AND(G$5>=$C31,G$5<=$D31),IF(G$5<$C31+COUNTIFS('FullStack Plan'!$F$6:$F$78,$B31,'FullStack Plan'!$B$6:$B$78,"Yes",'FullStack Plan'!$L$6:$L$78,"Done"),2,1),"")) | H31: =IF($C31="","",IF(AND(H$5>=$C31,H$5<=$D31),IF(H$5<$C31+COUNTIFS('FullStack Plan'!$F$6:$F$78,$B31,'FullStack Plan'!$B$6:$B$78,"Yes",'FullStack Plan'!$L$6:$L$78,"Done"),2,1),"")) | I31: =IF($C31="","",IF(AND(I$5>=$C31,I$5<=$D31),IF(I$5<$C31+COUNTIFS('FullStack Plan'!$F$6:$F$78,$B31,'FullStack Plan'!$B$6:$B$78,"Yes",'FullStack Plan'!$L$6:$L$78,"Done"),2,1),"")) | J31: =IF($C31="","",IF(AND(J$5>=$C31,J$5<=$D31),IF(J$5<$C31+COUNTIFS('FullStack Plan'!$F$6:$F$78,$B31,'FullStack Plan'!$B$6:$B$78,"Yes",'FullStack Plan'!$L$6:$L$78,"Done"),2,1),"")) | K31: =IF($C31="","",IF(AND(K$5>=$C31,K$5<=$D31),IF(K$5<$C31+COUNTIFS('FullStack Plan'!$F$6:$F$78,$B31,'FullStack Plan'!$B$6:$B$78,"Yes",'FullStack Plan'!$L$6:$L$78,"Done"),2,1),"")) | L31: =IF($C31="","",IF(AND(L$5>=$C31,L$5<=$D31),IF(L$5<$C31+COUNTIFS('FullStack Plan'!$F$6:$F$78,$B31,'FullStack Plan'!$B$6:$B$78,"Yes",'FullStack Plan'!$L$6:$L$78,"Done"),2,1),"")) | ... AQ31: =IF($C31="","",IF(AND(AQ$5>=$C31,AQ$5<=$D31),IF(AQ$5<$C31+COUNTIFS('FullStack Plan'!$F$6:$F$78,$B31,'FullStack Plan'!$B$6:$B$78,"Yes",'FullStack Plan'!$L$6:$L$78,"Done"),2,1),""))
A32: Full-Stack | B32: JavaScript Runtime Systems, Browser APIs & Product Labs | C32: =IF(COUNTIFS('FullStack Plan'!$F$6:$F$78,$B32,'FullStack Plan'!$B$6:$B$78,"Yes")=0,"",_xlfn.MINIFS('FullStack Plan'!$A$6:$A$78,'FullStack Plan'!$F$6:$F$78,$B32,'FullStack Plan'!$B$6:$B$78,"Yes")) -> 3 | D32: =IF(COUNTIFS('FullStack Plan'!$F$6:$F$78,$B32,'FullStack Plan'!$B$6:$B$78,"Yes")=0,"",_xlfn.MAXIFS('FullStack Plan'!$A$6:$A$78,'FullStack Plan'!$F$6:$F$78,$B32,'FullStack Plan'!$B$6:$B$78,"Yes")) -> 8 | E32: =IF($C32="","",IF(AND(E$5>=$C32,E$5<=$D32),IF(E$5<$C32+COUNTIFS('FullStack Plan'!$F$6:$F$78,$B32,'FullStack Plan'!$B$6:$B$78,"Yes",'FullStack Plan'!$L$6:$L$78,"Done"),2,1),"")) | F32: =IF($C32="","",IF(AND(F$5>=$C32,F$5<=$D32),IF(F$5<$C32+COUNTIFS('FullStack Plan'!$F$6:$F$78,$B32,'FullStack Plan'!$B$6:$B$78,"Yes",'FullStack Plan'!$L$6:$L$78,"Done"),2,1),"")) | G32: =IF($C32="","",IF(AND(G$5>=$C32,G$5<=$D32),IF(G$5<$C32+COUNTIFS('FullStack Plan'!$F$6:$F$78,$B32,'FullStack Plan'!$B$6:$B$78,"Yes",'FullStack Plan'!$L$6:$L$78,"Done"),2,1),"")) -> 1 | H32: =IF($C32="","",IF(AND(H$5>=$C32,H$5<=$D32),IF(H$5<$C32+COUNTIFS('FullStack Plan'!$F$6:$F$78,$B32,'FullStack Plan'!$B$6:$B$78,"Yes",'FullStack Plan'!$L$6:$L$78,"Done"),2,1),"")) -> 1 | I32: =IF($C32="","",IF(AND(I$5>=$C32,I$5<=$D32),IF(I$5<$C32+COUNTIFS('FullStack Plan'!$F$6:$F$78,$B32,'FullStack Plan'!$B$6:$B$78,"Yes",'FullStack Plan'!$L$6:$L$78,"Done"),2,1),"")) -> 1 | J32: =IF($C32="","",IF(AND(J$5>=$C32,J$5<=$D32),IF(J$5<$C32+COUNTIFS('FullStack Plan'!$F$6:$F$78,$B32,'FullStack Plan'!$B$6:$B$78,"Yes",'FullStack Plan'!$L$6:$L$78,"Done"),2,1),"")) -> 1 | K32: =IF($C32="","",IF(AND(K$5>=$C32,K$5<=$D32),IF(K$5<$C32+COUNTIFS('FullStack Plan'!$F$6:$F$78,$B32,'FullStack Plan'!$B$6:$B$78,"Yes",'FullStack Plan'!$L$6:$L$78,"Done"),2,1),"")) -> 1 | L32: =IF($C32="","",IF(AND(L$5>=$C32,L$5<=$D32),IF(L$5<$C32+COUNTIFS('FullStack Plan'!$F$6:$F$78,$B32,'FullStack Plan'!$B$6:$B$78,"Yes",'FullStack Plan'!$L$6:$L$78,"Done"),2,1),"")) -> 1 | ... AQ32: =IF($C32="","",IF(AND(AQ$5>=$C32,AQ$5<=$D32),IF(AQ$5<$C32+COUNTIFS('FullStack Plan'!$F$6:$F$78,$B32,'FullStack Plan'!$B$6:$B$78,"Yes",'FullStack Plan'!$L$6:$L$78,"Done"),2,1),""))
A33: Full-Stack | B33: JavaScript Object System & Engineering Patterns | C33: =IF(COUNTIFS('FullStack Plan'!$F$6:$F$78,$B33,'FullStack Plan'!$B$6:$B$78,"Yes")=0,"",_xlfn.MINIFS('FullStack Plan'!$A$6:$A$78,'FullStack Plan'!$F$6:$F$78,$B33,'FullStack Plan'!$B$6:$B$78,"Yes")) -> 9 | D33: =IF(COUNTIFS('FullStack Plan'!$F$6:$F$78,$B33,'FullStack Plan'!$B$6:$B$78,"Yes")=0,"",_xlfn.MAXIFS('FullStack Plan'!$A$6:$A$78,'FullStack Plan'!$F$6:$F$78,$B33,'FullStack Plan'!$B$6:$B$78,"Yes")) -> 10 | E33: =IF($C33="","",IF(AND(E$5>=$C33,E$5<=$D33),IF(E$5<$C33+COUNTIFS('FullStack Plan'!$F$6:$F$78,$B33,'FullStack Plan'!$B$6:$B$78,"Yes",'FullStack Plan'!$L$6:$L$78,"Done"),2,1),"")) | F33: =IF($C33="","",IF(AND(F$5>=$C33,F$5<=$D33),IF(F$5<$C33+COUNTIFS('FullStack Plan'!$F$6:$F$78,$B33,'FullStack Plan'!$B$6:$B$78,"Yes",'FullStack Plan'!$L$6:$L$78,"Done"),2,1),"")) | G33: =IF($C33="","",IF(AND(G$5>=$C33,G$5<=$D33),IF(G$5<$C33+COUNTIFS('FullStack Plan'!$F$6:$F$78,$B33,'FullStack Plan'!$B$6:$B$78,"Yes",'FullStack Plan'!$L$6:$L$78,"Done"),2,1),"")) | H33: =IF($C33="","",IF(AND(H$5>=$C33,H$5<=$D33),IF(H$5<$C33+COUNTIFS('FullStack Plan'!$F$6:$F$78,$B33,'FullStack Plan'!$B$6:$B$78,"Yes",'FullStack Plan'!$L$6:$L$78,"Done"),2,1),"")) | I33: =IF($C33="","",IF(AND(I$5>=$C33,I$5<=$D33),IF(I$5<$C33+COUNTIFS('FullStack Plan'!$F$6:$F$78,$B33,'FullStack Plan'!$B$6:$B$78,"Yes",'FullStack Plan'!$L$6:$L$78,"Done"),2,1),"")) | J33: =IF($C33="","",IF(AND(J$5>=$C33,J$5<=$D33),IF(J$5<$C33+COUNTIFS('FullStack Plan'!$F$6:$F$78,$B33,'FullStack Plan'!$B$6:$B$78,"Yes",'FullStack Plan'!$L$6:$L$78,"Done"),2,1),"")) | K33: =IF($C33="","",IF(AND(K$5>=$C33,K$5<=$D33),IF(K$5<$C33+COUNTIFS('FullStack Plan'!$F$6:$F$78,$B33,'FullStack Plan'!$B$6:$B$78,"Yes",'FullStack Plan'!$L$6:$L$78,"Done"),2,1),"")) | L33: =IF($C33="","",IF(AND(L$5>=$C33,L$5<=$D33),IF(L$5<$C33+COUNTIFS('FullStack Plan'!$F$6:$F$78,$B33,'FullStack Plan'!$B$6:$B$78,"Yes",'FullStack Plan'!$L$6:$L$78,"Done"),2,1),"")) | ... AQ33: =IF($C33="","",IF(AND(AQ$5>=$C33,AQ$5<=$D33),IF(AQ$5<$C33+COUNTIFS('FullStack Plan'!$F$6:$F$78,$B33,'FullStack Plan'!$B$6:$B$78,"Yes",'FullStack Plan'!$L$6:$L$78,"Done"),2,1),""))
A34: Full-Stack | B34: jQuery (legacy, optional) | C34: =IF(COUNTIFS('FullStack Plan'!$F$6:$F$78,$B34,'FullStack Plan'!$B$6:$B$78,"Yes")=0,"",_xlfn.MINIFS('FullStack Plan'!$A$6:$A$78,'FullStack Plan'!$F$6:$F$78,$B34,'FullStack Plan'!$B$6:$B$78,"Yes")) | D34: =IF(COUNTIFS('FullStack Plan'!$F$6:$F$78,$B34,'FullStack Plan'!$B$6:$B$78,"Yes")=0,"",_xlfn.MAXIFS('FullStack Plan'!$A$6:$A$78,'FullStack Plan'!$F$6:$F$78,$B34,'FullStack Plan'!$B$6:$B$78,"Yes")) | E34: =IF($C34="","",IF(AND(E$5>=$C34,E$5<=$D34),IF(E$5<$C34+COUNTIFS('FullStack Plan'!$F$6:$F$78,$B34,'FullStack Plan'!$B$6:$B$78,"Yes",'FullStack Plan'!$L$6:$L$78,"Done"),2,1),"")) | F34: =IF($C34="","",IF(AND(F$5>=$C34,F$5<=$D34),IF(F$5<$C34+COUNTIFS('FullStack Plan'!$F$6:$F$78,$B34,'FullStack Plan'!$B$6:$B$78,"Yes",'FullStack Plan'!$L$6:$L$78,"Done"),2,1),"")) | G34: =IF($C34="","",IF(AND(G$5>=$C34,G$5<=$D34),IF(G$5<$C34+COUNTIFS('FullStack Plan'!$F$6:$F$78,$B34,'FullStack Plan'!$B$6:$B$78,"Yes",'FullStack Plan'!$L$6:$L$78,"Done"),2,1),"")) | H34: =IF($C34="","",IF(AND(H$5>=$C34,H$5<=$D34),IF(H$5<$C34+COUNTIFS('FullStack Plan'!$F$6:$F$78,$B34,'FullStack Plan'!$B$6:$B$78,"Yes",'FullStack Plan'!$L$6:$L$78,"Done"),2,1),"")) | I34: =IF($C34="","",IF(AND(I$5>=$C34,I$5<=$D34),IF(I$5<$C34+COUNTIFS('FullStack Plan'!$F$6:$F$78,$B34,'FullStack Plan'!$B$6:$B$78,"Yes",'FullStack Plan'!$L$6:$L$78,"Done"),2,1),"")) | J34: =IF($C34="","",IF(AND(J$5>=$C34,J$5<=$D34),IF(J$5<$C34+COUNTIFS('FullStack Plan'!$F$6:$F$78,$B34,'FullStack Plan'!$B$6:$B$78,"Yes",'FullStack Plan'!$L$6:$L$78,"Done"),2,1),"")) | K34: =IF($C34="","",IF(AND(K$5>=$C34,K$5<=$D34),IF(K$5<$C34+COUNTIFS('FullStack Plan'!$F$6:$F$78,$B34,'FullStack Plan'!$B$6:$B$78,"Yes",'FullStack Plan'!$L$6:$L$78,"Done"),2,1),"")) | L34: =IF($C34="","",IF(AND(L$5>=$C34,L$5<=$D34),IF(L$5<$C34+COUNTIFS('FullStack Plan'!$F$6:$F$78,$B34,'FullStack Plan'!$B$6:$B$78,"Yes",'FullStack Plan'!$L$6:$L$78,"Done"),2,1),"")) | ... AQ34: =IF($C34="","",IF(AND(AQ$5>=$C34,AQ$5<=$D34),IF(AQ$5<$C34+COUNTIFS('FullStack Plan'!$F$6:$F$78,$B34,'FullStack Plan'!$B$6:$B$78,"Yes",'FullStack Plan'!$L$6:$L$78,"Done"),2,1),""))
A35: Full-Stack | B35: React & Frontend Product Architecture Fundamentals | C35: =IF(COUNTIFS('FullStack Plan'!$F$6:$F$78,$B35,'FullStack Plan'!$B$6:$B$78,"Yes")=0,"",_xlfn.MINIFS('FullStack Plan'!$A$6:$A$78,'FullStack Plan'!$F$6:$F$78,$B35,'FullStack Plan'!$B$6:$B$78,"Yes")) -> 11 | D35: =IF(COUNTIFS('FullStack Plan'!$F$6:$F$78,$B35,'FullStack Plan'!$B$6:$B$78,"Yes")=0,"",_xlfn.MAXIFS('FullStack Plan'!$A$6:$A$78,'FullStack Plan'!$F$6:$F$78,$B35,'FullStack Plan'!$B$6:$B$78,"Yes")) -> 14 | E35: =IF($C35="","",IF(AND(E$5>=$C35,E$5<=$D35),IF(E$5<$C35+COUNTIFS('FullStack Plan'!$F$6:$F$78,$B35,'FullStack Plan'!$B$6:$B$78,"Yes",'FullStack Plan'!$L$6:$L$78,"Done"),2,1),"")) | F35: =IF($C35="","",IF(AND(F$5>=$C35,F$5<=$D35),IF(F$5<$C35+COUNTIFS('FullStack Plan'!$F$6:$F$78,$B35,'FullStack Plan'!$B$6:$B$78,"Yes",'FullStack Plan'!$L$6:$L$78,"Done"),2,1),"")) | G35: =IF($C35="","",IF(AND(G$5>=$C35,G$5<=$D35),IF(G$5<$C35+COUNTIFS('FullStack Plan'!$F$6:$F$78,$B35,'FullStack Plan'!$B$6:$B$78,"Yes",'FullStack Plan'!$L$6:$L$78,"Done"),2,1),"")) | H35: =IF($C35="","",IF(AND(H$5>=$C35,H$5<=$D35),IF(H$5<$C35+COUNTIFS('FullStack Plan'!$F$6:$F$78,$B35,'FullStack Plan'!$B$6:$B$78,"Yes",'FullStack Plan'!$L$6:$L$78,"Done"),2,1),"")) | I35: =IF($C35="","",IF(AND(I$5>=$C35,I$5<=$D35),IF(I$5<$C35+COUNTIFS('FullStack Plan'!$F$6:$F$78,$B35,'FullStack Plan'!$B$6:$B$78,"Yes",'FullStack Plan'!$L$6:$L$78,"Done"),2,1),"")) | J35: =IF($C35="","",IF(AND(J$5>=$C35,J$5<=$D35),IF(J$5<$C35+COUNTIFS('FullStack Plan'!$F$6:$F$78,$B35,'FullStack Plan'!$B$6:$B$78,"Yes",'FullStack Plan'!$L$6:$L$78,"Done"),2,1),"")) | K35: =IF($C35="","",IF(AND(K$5>=$C35,K$5<=$D35),IF(K$5<$C35+COUNTIFS('FullStack Plan'!$F$6:$F$78,$B35,'FullStack Plan'!$B$6:$B$78,"Yes",'FullStack Plan'!$L$6:$L$78,"Done"),2,1),"")) | L35: =IF($C35="","",IF(AND(L$5>=$C35,L$5<=$D35),IF(L$5<$C35+COUNTIFS('FullStack Plan'!$F$6:$F$78,$B35,'FullStack Plan'!$B$6:$B$78,"Yes",'FullStack Plan'!$L$6:$L$78,"Done"),2,1),"")) | ... AQ35: =IF($C35="","",IF(AND(AQ$5>=$C35,AQ$5<=$D35),IF(AQ$5<$C35+COUNTIFS('FullStack Plan'!$F$6:$F$78,$B35,'FullStack Plan'!$B$6:$B$78,"Yes",'FullStack Plan'!$L$6:$L$78,"Done"),2,1),""))
A36: Full-Stack | B36: Backend Product Systems, APIs & Production Engineering (MERN) | C36: =IF(COUNTIFS('FullStack Plan'!$F$6:$F$78,$B36,'FullStack Plan'!$B$6:$B$78,"Yes")=0,"",_xlfn.MINIFS('FullStack Plan'!$A$6:$A$78,'FullStack Plan'!$F$6:$F$78,$B36,'FullStack Plan'!$B$6:$B$78,"Yes")) -> 15 | D36: =IF(COUNTIFS('FullStack Plan'!$F$6:$F$78,$B36,'FullStack Plan'!$B$6:$B$78,"Yes")=0,"",_xlfn.MAXIFS('FullStack Plan'!$A$6:$A$78,'FullStack Plan'!$F$6:$F$78,$B36,'FullStack Plan'!$B$6:$B$78,"Yes")) -> 18 | E36: =IF($C36="","",IF(AND(E$5>=$C36,E$5<=$D36),IF(E$5<$C36+COUNTIFS('FullStack Plan'!$F$6:$F$78,$B36,'FullStack Plan'!$B$6:$B$78,"Yes",'FullStack Plan'!$L$6:$L$78,"Done"),2,1),"")) | F36: =IF($C36="","",IF(AND(F$5>=$C36,F$5<=$D36),IF(F$5<$C36+COUNTIFS('FullStack Plan'!$F$6:$F$78,$B36,'FullStack Plan'!$B$6:$B$78,"Yes",'FullStack Plan'!$L$6:$L$78,"Done"),2,1),"")) | G36: =IF($C36="","",IF(AND(G$5>=$C36,G$5<=$D36),IF(G$5<$C36+COUNTIFS('FullStack Plan'!$F$6:$F$78,$B36,'FullStack Plan'!$B$6:$B$78,"Yes",'FullStack Plan'!$L$6:$L$78,"Done"),2,1),"")) | H36: =IF($C36="","",IF(AND(H$5>=$C36,H$5<=$D36),IF(H$5<$C36+COUNTIFS('FullStack Plan'!$F$6:$F$78,$B36,'FullStack Plan'!$B$6:$B$78,"Yes",'FullStack Plan'!$L$6:$L$78,"Done"),2,1),"")) | I36: =IF($C36="","",IF(AND(I$5>=$C36,I$5<=$D36),IF(I$5<$C36+COUNTIFS('FullStack Plan'!$F$6:$F$78,$B36,'FullStack Plan'!$B$6:$B$78,"Yes",'FullStack Plan'!$L$6:$L$78,"Done"),2,1),"")) | J36: =IF($C36="","",IF(AND(J$5>=$C36,J$5<=$D36),IF(J$5<$C36+COUNTIFS('FullStack Plan'!$F$6:$F$78,$B36,'FullStack Plan'!$B$6:$B$78,"Yes",'FullStack Plan'!$L$6:$L$78,"Done"),2,1),"")) | K36: =IF($C36="","",IF(AND(K$5>=$C36,K$5<=$D36),IF(K$5<$C36+COUNTIFS('FullStack Plan'!$F$6:$F$78,$B36,'FullStack Plan'!$B$6:$B$78,"Yes",'FullStack Plan'!$L$6:$L$78,"Done"),2,1),"")) | L36: =IF($C36="","",IF(AND(L$5>=$C36,L$5<=$D36),IF(L$5<$C36+COUNTIFS('FullStack Plan'!$F$6:$F$78,$B36,'FullStack Plan'!$B$6:$B$78,"Yes",'FullStack Plan'!$L$6:$L$78,"Done"),2,1),"")) | ... AQ36: =IF($C36="","",IF(AND(AQ$5>=$C36,AQ$5<=$D36),IF(AQ$5<$C36+COUNTIFS('FullStack Plan'!$F$6:$F$78,$B36,'FullStack Plan'!$B$6:$B$78,"Yes",'FullStack Plan'!$L$6:$L$78,"Done"),2,1),""))
A37: Full-Stack | B37: Databases & SQL | C37: =IF(COUNTIFS('FullStack Plan'!$F$6:$F$78,$B37,'FullStack Plan'!$B$6:$B$78,"Yes")=0,"",_xlfn.MINIFS('FullStack Plan'!$A$6:$A$78,'FullStack Plan'!$F$6:$F$78,$B37,'FullStack Plan'!$B$6:$B$78,"Yes")) -> 19 | D37: =IF(COUNTIFS('FullStack Plan'!$F$6:$F$78,$B37,'FullStack Plan'!$B$6:$B$78,"Yes")=0,"",_xlfn.MAXIFS('FullStack Plan'!$A$6:$A$78,'FullStack Plan'!$F$6:$F$78,$B37,'FullStack Plan'!$B$6:$B$78,"Yes")) -> 22 | E37: =IF($C37="","",IF(AND(E$5>=$C37,E$5<=$D37),IF(E$5<$C37+COUNTIFS('FullStack Plan'!$F$6:$F$78,$B37,'FullStack Plan'!$B$6:$B$78,"Yes",'FullStack Plan'!$L$6:$L$78,"Done"),2,1),"")) | F37: =IF($C37="","",IF(AND(F$5>=$C37,F$5<=$D37),IF(F$5<$C37+COUNTIFS('FullStack Plan'!$F$6:$F$78,$B37,'FullStack Plan'!$B$6:$B$78,"Yes",'FullStack Plan'!$L$6:$L$78,"Done"),2,1),"")) | G37: =IF($C37="","",IF(AND(G$5>=$C37,G$5<=$D37),IF(G$5<$C37+COUNTIFS('FullStack Plan'!$F$6:$F$78,$B37,'FullStack Plan'!$B$6:$B$78,"Yes",'FullStack Plan'!$L$6:$L$78,"Done"),2,1),"")) | H37: =IF($C37="","",IF(AND(H$5>=$C37,H$5<=$D37),IF(H$5<$C37+COUNTIFS('FullStack Plan'!$F$6:$F$78,$B37,'FullStack Plan'!$B$6:$B$78,"Yes",'FullStack Plan'!$L$6:$L$78,"Done"),2,1),"")) | I37: =IF($C37="","",IF(AND(I$5>=$C37,I$5<=$D37),IF(I$5<$C37+COUNTIFS('FullStack Plan'!$F$6:$F$78,$B37,'FullStack Plan'!$B$6:$B$78,"Yes",'FullStack Plan'!$L$6:$L$78,"Done"),2,1),"")) | J37: =IF($C37="","",IF(AND(J$5>=$C37,J$5<=$D37),IF(J$5<$C37+COUNTIFS('FullStack Plan'!$F$6:$F$78,$B37,'FullStack Plan'!$B$6:$B$78,"Yes",'FullStack Plan'!$L$6:$L$78,"Done"),2,1),"")) | K37: =IF($C37="","",IF(AND(K$5>=$C37,K$5<=$D37),IF(K$5<$C37+COUNTIFS('FullStack Plan'!$F$6:$F$78,$B37,'FullStack Plan'!$B$6:$B$78,"Yes",'FullStack Plan'!$L$6:$L$78,"Done"),2,1),"")) | L37: =IF($C37="","",IF(AND(L$5>=$C37,L$5<=$D37),IF(L$5<$C37+COUNTIFS('FullStack Plan'!$F$6:$F$78,$B37,'FullStack Plan'!$B$6:$B$78,"Yes",'FullStack Plan'!$L$6:$L$78,"Done"),2,1),"")) | ... AQ37: =IF($C37="","",IF(AND(AQ$5>=$C37,AQ$5<=$D37),IF(AQ$5<$C37+COUNTIFS('FullStack Plan'!$F$6:$F$78,$B37,'FullStack Plan'!$B$6:$B$78,"Yes",'FullStack Plan'!$L$6:$L$78,"Done"),2,1),""))
A38: Full-Stack | B38: Backend Product Systems – Deep Dive | C38: =IF(COUNTIFS('FullStack Plan'!$F$6:$F$78,$B38,'FullStack Plan'!$B$6:$B$78,"Yes")=0,"",_xlfn.MINIFS('FullStack Plan'!$A$6:$A$78,'FullStack Plan'!$F$6:$F$78,$B38,'FullStack Plan'!$B$6:$B$78,"Yes")) -> 23 | D38: =IF(COUNTIFS('FullStack Plan'!$F$6:$F$78,$B38,'FullStack Plan'!$B$6:$B$78,"Yes")=0,"",_xlfn.MAXIFS('FullStack Plan'!$A$6:$A$78,'FullStack Plan'!$F$6:$F$78,$B38,'FullStack Plan'!$B$6:$B$78,"Yes")) -> 24 | E38: =IF($C38="","",IF(AND(E$5>=$C38,E$5<=$D38),IF(E$5<$C38+COUNTIFS('FullStack Plan'!$F$6:$F$78,$B38,'FullStack Plan'!$B$6:$B$78,"Yes",'FullStack Plan'!$L$6:$L$78,"Done"),2,1),"")) | F38: =IF($C38="","",IF(AND(F$5>=$C38,F$5<=$D38),IF(F$5<$C38+COUNTIFS('FullStack Plan'!$F$6:$F$78,$B38,'FullStack Plan'!$B$6:$B$78,"Yes",'FullStack Plan'!$L$6:$L$78,"Done"),2,1),"")) | G38: =IF($C38="","",IF(AND(G$5>=$C38,G$5<=$D38),IF(G$5<$C38+COUNTIFS('FullStack Plan'!$F$6:$F$78,$B38,'FullStack Plan'!$B$6:$B$78,"Yes",'FullStack Plan'!$L$6:$L$78,"Done"),2,1),"")) | H38: =IF($C38="","",IF(AND(H$5>=$C38,H$5<=$D38),IF(H$5<$C38+COUNTIFS('FullStack Plan'!$F$6:$F$78,$B38,'FullStack Plan'!$B$6:$B$78,"Yes",'FullStack Plan'!$L$6:$L$78,"Done"),2,1),"")) | I38: =IF($C38="","",IF(AND(I$5>=$C38,I$5<=$D38),IF(I$5<$C38+COUNTIFS('FullStack Plan'!$F$6:$F$78,$B38,'FullStack Plan'!$B$6:$B$78,"Yes",'FullStack Plan'!$L$6:$L$78,"Done"),2,1),"")) | J38: =IF($C38="","",IF(AND(J$5>=$C38,J$5<=$D38),IF(J$5<$C38+COUNTIFS('FullStack Plan'!$F$6:$F$78,$B38,'FullStack Plan'!$B$6:$B$78,"Yes",'FullStack Plan'!$L$6:$L$78,"Done"),2,1),"")) | K38: =IF($C38="","",IF(AND(K$5>=$C38,K$5<=$D38),IF(K$5<$C38+COUNTIFS('FullStack Plan'!$F$6:$F$78,$B38,'FullStack Plan'!$B$6:$B$78,"Yes",'FullStack Plan'!$L$6:$L$78,"Done"),2,1),"")) | L38: =IF($C38="","",IF(AND(L$5>=$C38,L$5<=$D38),IF(L$5<$C38+COUNTIFS('FullStack Plan'!$F$6:$F$78,$B38,'FullStack Plan'!$B$6:$B$78,"Yes",'FullStack Plan'!$L$6:$L$78,"Done"),2,1),"")) | ... AQ38: =IF($C38="","",IF(AND(AQ$5>=$C38,AQ$5<=$D38),IF(AQ$5<$C38+COUNTIFS('FullStack Plan'!$F$6:$F$78,$B38,'FullStack Plan'!$B$6:$B$78,"Yes",'FullStack Plan'!$L$6:$L$78,"Done"),2,1),""))
A39: Full-Stack | B39: React, TypeScript & Frontend Architecture – Deep Dive (incl. Next.js) | C39: =IF(COUNTIFS('FullStack Plan'!$F$6:$F$78,$B39,'FullStack Plan'!$B$6:$B$78,"Yes")=0,"",_xlfn.MINIFS('FullStack Plan'!$A$6:$A$78,'FullStack Plan'!$F$6:$F$78,$B39,'FullStack Plan'!$B$6:$B$78,"Yes")) -> 25 | D39: =IF(COUNTIFS('FullStack Plan'!$F$6:$F$78,$B39,'FullStack Plan'!$B$6:$B$78,"Yes")=0,"",_xlfn.MAXIFS('FullStack Plan'!$A$6:$A$78,'FullStack Plan'!$F$6:$F$78,$B39,'FullStack Plan'!$B$6:$B$78,"Yes")) -> 28 | E39: =IF($C39="","",IF(AND(E$5>=$C39,E$5<=$D39),IF(E$5<$C39+COUNTIFS('FullStack Plan'!$F$6:$F$78,$B39,'FullStack Plan'!$B$6:$B$78,"Yes",'FullStack Plan'!$L$6:$L$78,"Done"),2,1),"")) | F39: =IF($C39="","",IF(AND(F$5>=$C39,F$5<=$D39),IF(F$5<$C39+COUNTIFS('FullStack Plan'!$F$6:$F$78,$B39,'FullStack Plan'!$B$6:$B$78,"Yes",'FullStack Plan'!$L$6:$L$78,"Done"),2,1),"")) | G39: =IF($C39="","",IF(AND(G$5>=$C39,G$5<=$D39),IF(G$5<$C39+COUNTIFS('FullStack Plan'!$F$6:$F$78,$B39,'FullStack Plan'!$B$6:$B$78,"Yes",'FullStack Plan'!$L$6:$L$78,"Done"),2,1),"")) | H39: =IF($C39="","",IF(AND(H$5>=$C39,H$5<=$D39),IF(H$5<$C39+COUNTIFS('FullStack Plan'!$F$6:$F$78,$B39,'FullStack Plan'!$B$6:$B$78,"Yes",'FullStack Plan'!$L$6:$L$78,"Done"),2,1),"")) | I39: =IF($C39="","",IF(AND(I$5>=$C39,I$5<=$D39),IF(I$5<$C39+COUNTIFS('FullStack Plan'!$F$6:$F$78,$B39,'FullStack Plan'!$B$6:$B$78,"Yes",'FullStack Plan'!$L$6:$L$78,"Done"),2,1),"")) | J39: =IF($C39="","",IF(AND(J$5>=$C39,J$5<=$D39),IF(J$5<$C39+COUNTIFS('FullStack Plan'!$F$6:$F$78,$B39,'FullStack Plan'!$B$6:$B$78,"Yes",'FullStack Plan'!$L$6:$L$78,"Done"),2,1),"")) | K39: =IF($C39="","",IF(AND(K$5>=$C39,K$5<=$D39),IF(K$5<$C39+COUNTIFS('FullStack Plan'!$F$6:$F$78,$B39,'FullStack Plan'!$B$6:$B$78,"Yes",'FullStack Plan'!$L$6:$L$78,"Done"),2,1),"")) | L39: =IF($C39="","",IF(AND(L$5>=$C39,L$5<=$D39),IF(L$5<$C39+COUNTIFS('FullStack Plan'!$F$6:$F$78,$B39,'FullStack Plan'!$B$6:$B$78,"Yes",'FullStack Plan'!$L$6:$L$78,"Done"),2,1),"")) | ... AQ39: =IF($C39="","",IF(AND(AQ$5>=$C39,AQ$5<=$D39),IF(AQ$5<$C39+COUNTIFS('FullStack Plan'!$F$6:$F$78,$B39,'FullStack Plan'!$B$6:$B$78,"Yes",'FullStack Plan'!$L$6:$L$78,"Done"),2,1),""))
A40: Full-Stack | B40: Foundations of AI-Assisted Full-Stack Development | C40: =IF(COUNTIFS('FullStack Plan'!$F$6:$F$78,$B40,'FullStack Plan'!$B$6:$B$78,"Yes")=0,"",_xlfn.MINIFS('FullStack Plan'!$A$6:$A$78,'FullStack Plan'!$F$6:$F$78,$B40,'FullStack Plan'!$B$6:$B$78,"Yes")) -> 29 | D40: =IF(COUNTIFS('FullStack Plan'!$F$6:$F$78,$B40,'FullStack Plan'!$B$6:$B$78,"Yes")=0,"",_xlfn.MAXIFS('FullStack Plan'!$A$6:$A$78,'FullStack Plan'!$F$6:$F$78,$B40,'FullStack Plan'!$B$6:$B$78,"Yes")) -> 30 | E40: =IF($C40="","",IF(AND(E$5>=$C40,E$5<=$D40),IF(E$5<$C40+COUNTIFS('FullStack Plan'!$F$6:$F$78,$B40,'FullStack Plan'!$B$6:$B$78,"Yes",'FullStack Plan'!$L$6:$L$78,"Done"),2,1),"")) | F40: =IF($C40="","",IF(AND(F$5>=$C40,F$5<=$D40),IF(F$5<$C40+COUNTIFS('FullStack Plan'!$F$6:$F$78,$B40,'FullStack Plan'!$B$6:$B$78,"Yes",'FullStack Plan'!$L$6:$L$78,"Done"),2,1),"")) | G40: =IF($C40="","",IF(AND(G$5>=$C40,G$5<=$D40),IF(G$5<$C40+COUNTIFS('FullStack Plan'!$F$6:$F$78,$B40,'FullStack Plan'!$B$6:$B$78,"Yes",'FullStack Plan'!$L$6:$L$78,"Done"),2,1),"")) | H40: =IF($C40="","",IF(AND(H$5>=$C40,H$5<=$D40),IF(H$5<$C40+COUNTIFS('FullStack Plan'!$F$6:$F$78,$B40,'FullStack Plan'!$B$6:$B$78,"Yes",'FullStack Plan'!$L$6:$L$78,"Done"),2,1),"")) | I40: =IF($C40="","",IF(AND(I$5>=$C40,I$5<=$D40),IF(I$5<$C40+COUNTIFS('FullStack Plan'!$F$6:$F$78,$B40,'FullStack Plan'!$B$6:$B$78,"Yes",'FullStack Plan'!$L$6:$L$78,"Done"),2,1),"")) | J40: =IF($C40="","",IF(AND(J$5>=$C40,J$5<=$D40),IF(J$5<$C40+COUNTIFS('FullStack Plan'!$F$6:$F$78,$B40,'FullStack Plan'!$B$6:$B$78,"Yes",'FullStack Plan'!$L$6:$L$78,"Done"),2,1),"")) | K40: =IF($C40="","",IF(AND(K$5>=$C40,K$5<=$D40),IF(K$5<$C40+COUNTIFS('FullStack Plan'!$F$6:$F$78,$B40,'FullStack Plan'!$B$6:$B$78,"Yes",'FullStack Plan'!$L$6:$L$78,"Done"),2,1),"")) | L40: =IF($C40="","",IF(AND(L$5>=$C40,L$5<=$D40),IF(L$5<$C40+COUNTIFS('FullStack Plan'!$F$6:$F$78,$B40,'FullStack Plan'!$B$6:$B$78,"Yes",'FullStack Plan'!$L$6:$L$78,"Done"),2,1),"")) | ... AQ40: =IF($C40="","",IF(AND(AQ$5>=$C40,AQ$5<=$D40),IF(AQ$5<$C40+COUNTIFS('FullStack Plan'!$F$6:$F$78,$B40,'FullStack Plan'!$B$6:$B$78,"Yes",'FullStack Plan'!$L$6:$L$78,"Done"),2,1),""))
A41: Full-Stack | B41: Full-Stack Capstone Project (suggested) | C41: =IF(COUNTIFS('FullStack Plan'!$F$6:$F$78,$B41,'FullStack Plan'!$B$6:$B$78,"Yes")=0,"",_xlfn.MINIFS('FullStack Plan'!$A$6:$A$78,'FullStack Plan'!$F$6:$F$78,$B41,'FullStack Plan'!$B$6:$B$78,"Yes")) -> 31 | D41: =IF(COUNTIFS('FullStack Plan'!$F$6:$F$78,$B41,'FullStack Plan'!$B$6:$B$78,"Yes")=0,"",_xlfn.MAXIFS('FullStack Plan'!$A$6:$A$78,'FullStack Plan'!$F$6:$F$78,$B41,'FullStack Plan'!$B$6:$B$78,"Yes")) -> 33 | E41: =IF($C41="","",IF(AND(E$5>=$C41,E$5<=$D41),IF(E$5<$C41+COUNTIFS('FullStack Plan'!$F$6:$F$78,$B41,'FullStack Plan'!$B$6:$B$78,"Yes",'FullStack Plan'!$L$6:$L$78,"Done"),2,1),"")) | F41: =IF($C41="","",IF(AND(F$5>=$C41,F$5<=$D41),IF(F$5<$C41+COUNTIFS('FullStack Plan'!$F$6:$F$78,$B41,'FullStack Plan'!$B$6:$B$78,"Yes",'FullStack Plan'!$L$6:$L$78,"Done"),2,1),"")) | G41: =IF($C41="","",IF(AND(G$5>=$C41,G$5<=$D41),IF(G$5<$C41+COUNTIFS('FullStack Plan'!$F$6:$F$78,$B41,'FullStack Plan'!$B$6:$B$78,"Yes",'FullStack Plan'!$L$6:$L$78,"Done"),2,1),"")) | H41: =IF($C41="","",IF(AND(H$5>=$C41,H$5<=$D41),IF(H$5<$C41+COUNTIFS('FullStack Plan'!$F$6:$F$78,$B41,'FullStack Plan'!$B$6:$B$78,"Yes",'FullStack Plan'!$L$6:$L$78,"Done"),2,1),"")) | I41: =IF($C41="","",IF(AND(I$5>=$C41,I$5<=$D41),IF(I$5<$C41+COUNTIFS('FullStack Plan'!$F$6:$F$78,$B41,'FullStack Plan'!$B$6:$B$78,"Yes",'FullStack Plan'!$L$6:$L$78,"Done"),2,1),"")) | J41: =IF($C41="","",IF(AND(J$5>=$C41,J$5<=$D41),IF(J$5<$C41+COUNTIFS('FullStack Plan'!$F$6:$F$78,$B41,'FullStack Plan'!$B$6:$B$78,"Yes",'FullStack Plan'!$L$6:$L$78,"Done"),2,1),"")) | K41: =IF($C41="","",IF(AND(K$5>=$C41,K$5<=$D41),IF(K$5<$C41+COUNTIFS('FullStack Plan'!$F$6:$F$78,$B41,'FullStack Plan'!$B$6:$B$78,"Yes",'FullStack Plan'!$L$6:$L$78,"Done"),2,1),"")) | L41: =IF($C41="","",IF(AND(L$5>=$C41,L$5<=$D41),IF(L$5<$C41+COUNTIFS('FullStack Plan'!$F$6:$F$78,$B41,'FullStack Plan'!$B$6:$B$78,"Yes",'FullStack Plan'!$L$6:$L$78,"Done"),2,1),"")) | ... AQ41: =IF($C41="","",IF(AND(AQ$5>=$C41,AQ$5<=$D41),IF(AQ$5<$C41+COUNTIFS('FullStack Plan'!$F$6:$F$78,$B41,'FullStack Plan'!$B$6:$B$78,"Yes",'FullStack Plan'!$L$6:$L$78,"Done"),2,1),""))
... A47: Full-Stack | B47: PHP, MySQL & Laravel (alternative) | C47: =IF(COUNTIFS('FullStack Plan'!$F$6:$F$78,$B47,'FullStack Plan'!$B$6:$B$78,"Yes")=0,"",_xlfn.MINIFS('FullStack Plan'!$A$6:$A$78,'FullStack Plan'!$F$6:$F$78,$B47,'FullStack Plan'!$B$6:$B$78,"Yes")) | D47: =IF(COUNTIFS('FullStack Plan'!$F$6:$F$78,$B47,'FullStack Plan'!$B$6:$B$78,"Yes")=0,"",_xlfn.MAXIFS('FullStack Plan'!$A$6:$A$78,'FullStack Plan'!$F$6:$F$78,$B47,'FullStack Plan'!$B$6:$B$78,"Yes")) | E47: =IF($C47="","",IF(AND(E$5>=$C47,E$5<=$D47),IF(E$5<$C47+COUNTIFS('FullStack Plan'!$F$6:$F$78,$B47,'FullStack Plan'!$B$6:$B$78,"Yes",'FullStack Plan'!$L$6:$L$78,"Done"),2,1),"")) | F47: =IF($C47="","",IF(AND(F$5>=$C47,F$5<=$D47),IF(F$5<$C47+COUNTIFS('FullStack Plan'!$F$6:$F$78,$B47,'FullStack Plan'!$B$6:$B$78,"Yes",'FullStack Plan'!$L$6:$L$78,"Done"),2,1),"")) | G47: =IF($C47="","",IF(AND(G$5>=$C47,G$5<=$D47),IF(G$5<$C47+COUNTIFS('FullStack Plan'!$F$6:$F$78,$B47,'FullStack Plan'!$B$6:$B$78,"Yes",'FullStack Plan'!$L$6:$L$78,"Done"),2,1),"")) | H47: =IF($C47="","",IF(AND(H$5>=$C47,H$5<=$D47),IF(H$5<$C47+COUNTIFS('FullStack Plan'!$F$6:$F$78,$B47,'FullStack Plan'!$B$6:$B$78,"Yes",'FullStack Plan'!$L$6:$L$78,"Done"),2,1),"")) | I47: =IF($C47="","",IF(AND(I$5>=$C47,I$5<=$D47),IF(I$5<$C47+COUNTIFS('FullStack Plan'!$F$6:$F$78,$B47,'FullStack Plan'!$B$6:$B$78,"Yes",'FullStack Plan'!$L$6:$L$78,"Done"),2,1),"")) | J47: =IF($C47="","",IF(AND(J$5>=$C47,J$5<=$D47),IF(J$5<$C47+COUNTIFS('FullStack Plan'!$F$6:$F$78,$B47,'FullStack Plan'!$B$6:$B$78,"Yes",'FullStack Plan'!$L$6:$L$78,"Done"),2,1),"")) | K47: =IF($C47="","",IF(AND(K$5>=$C47,K$5<=$D47),IF(K$5<$C47+COUNTIFS('FullStack Plan'!$F$6:$F$78,$B47,'FullStack Plan'!$B$6:$B$78,"Yes",'FullStack Plan'!$L$6:$L$78,"Done"),2,1),"")) | L47: =IF($C47="","",IF(AND(L$5>=$C47,L$5<=$D47),IF(L$5<$C47+COUNTIFS('FullStack Plan'!$F$6:$F$78,$B47,'FullStack Plan'!$B$6:$B$78,"Yes",'FullStack Plan'!$L$6:$L$78,"Done"),2,1),"")) | ... AQ47: =IF($C47="","",IF(AND(AQ$5>=$C47,AQ$5<=$D47),IF(AQ$5<$C47+COUNTIFS('FullStack Plan'!$F$6:$F$78,$B47,'FullStack Plan'!$B$6:$B$78,"Yes",'FullStack Plan'!$L$6:$L$78,"Done"),2,1),""))

Sheet SDE Plan
A1: 9-Month SDE Study Plan – DSA · LLD · HLD · Backend · AI (39 weeks)
A2: Scaler curriculum compressed to 39 weeks (Intermediate level): AI → DSA → SQL → LLD/backend → system design → interview prep. Electives are off.
A3: Edit the blue cells: Include?, Status, Notes. Start date, hours & level live on Overview. Links: 📖 opens a docs/tutorial page, ▶ opens a YouTube search for that week's first topic.
A5: Plan Wk | B5: Include? | C5: Start (Mon) | D5: End (Sun) | E5: Phase | F5: Module | G5: Topics this week | H5: 📖 Where to read | I5: ▶ YouTube (this week) | J5: Practice & milestone | K5: Hrs target | L5: Status | M5: Notes
A6: =IF(B6="Yes",COUNTIF(B$6:B6,"Yes"),"—") -> — | B6: =IF(Overview!$C$6="Beginner","Yes","No") -> No | C6: =IF(B6="Yes",Overview!$C$4+7*(COUNTIF(B$6:B6,"Yes")-1),"—") -> — | D6: =IF(B6="Yes",C6+6,"—") -> — | E6: 0. 🧱 Foundations | F6: Programming Fundamentals – Thinking with AI: Logics, Loops & Control Flow | G6: • Programming foundations & AI awareness • Operators & expression evaluation using AI | H6: 📖 freeCodeCamp Learn | I6: ▶ Programming foundations & AI aware… | J6: 3–4 problems/day on conditions, loops & patterns in your chosen language | K6: =IF(B6="Yes",Overview!$C$5,0) -> 0 | L6: Not Started
A7: =IF(B7="Yes",COUNTIF(B$6:B7,"Yes"),"—") -> — | B7: =IF(Overview!$C$6="Beginner","Yes","No") -> No | C7: =IF(B7="Yes",Overview!$C$4+7*(COUNTIF(B$6:B7,"Yes")-1),"—") -> — | D7: =IF(B7="Yes",C7+6,"—") -> — | E7: 0. 🧱 Foundations | F7: Programming Fundamentals – Thinking with AI: Logics, Loops & Control Flow | G7: • Data types 1 & 2 + reading inputs • If-Else & AI edge-case thinking • Lab: If-Else | H7: 📖 Java tutorials (dev.java) | I7: ▶ Data types 1 & 2 + reading inputs | J7: 3–4 problems/day on conditions, loops & patterns in your chosen language | K7: =IF(B7="Yes",Overview!$C$5,0) -> 0 | L7: Not Started
A8: =IF(B8="Yes",COUNTIF(B$6:B8,"Yes"),"—") -> — | B8: =IF(Overview!$C$6="Beginner","Yes","No") -> No | C8: =IF(B8="Yes",Overview!$C$4+7*(COUNTIF(B$6:B8,"Yes")-1),"—") -> — | D8: =IF(B8="Yes",C8+6,"—") -> — | E8: 0. 🧱 Foundations | F8: Programming Fundamentals – Thinking with AI: Logics, Loops & Control Flow | G8: • Loops & iteration analysis by AI • Lab: Loops | H8: 📖 GeeksforGeeks | I8: ▶ Loops & iteration analysis by AI | J8: 3–4 problems/day on conditions, loops & patterns in your chosen language | K8: =IF(B8="Yes",Overview!$C$5,0) -> 0 | L8: Not Started
A9: =IF(B9="Yes",COUNTIF(B$6:B9,"Yes"),"—") -> — | B9: =IF(Overview!$C$6="Beginner","Yes","No") -> No | C9: =IF(B9="Yes",Overview!$C$4+7*(COUNTIF(B$6:B9,"Yes")-1),"—") -> — | D9: =IF(B9="Yes",C9+6,"—") -> — | E9: 0. 🧱 Foundations | F9: Programming Fundamentals – Thinking with AI: Logics, Loops & Control Flow | G9: • More problems on loops & patterns • Lab: Patterns • Proctored contest: data types, if-else, loops + discussion | H9: 📖 freeCodeCamp Learn | I9: ▶ More problems on loops & patterns | J9: 3–4 problems/day on conditions, loops & patterns in your chosen language ★ Milestone: Pass the loops/patterns contest | K9: =IF(B9="Yes",Overview!$C$5,0) -> 0 | L9: Not Started
A10: =IF(B10="Yes",COUNTIF(B$6:B10,"Yes"),"—") -> — | B10: =IF(Overview!$C$6="Beginner","Yes","No") -> No | C10: =IF(B10="Yes",Overview!$C$4+7*(COUNTIF(B$6:B10,"Yes")-1),"—") -> — | D10: =IF(B10="Yes",C10+6,"—") -> — | E10: 0. 🧱 Foundations | F10: Programming Fundamentals – Code Smarter with AI: Functions & Arrays | G10: • Functions & modularity: designing code with AI • Lab: Functions | H10: 📖 freeCodeCamp Learn | I10: ▶ designing code with AI | J10: 3–4 problems/day on arrays, strings & functions | K10: =IF(B10="Yes",Overview!$C$5,0) -> 0 | L10: Not Started
A11: =IF(B11="Yes",COUNTIF(B$6:B11,"Yes"),"—") -> — | B11: =IF(Overview!$C$6="Beginner","Yes","No") -> No | C11: =IF(B11="Yes",Overview!$C$4+7*(COUNTIF(B$6:B11,"Yes")-1),"—") -> — | D11: =IF(B11="Yes",C11+6,"—") -> — | E11: 0. 🧱 Foundations | F11: Programming Fundamentals – Code Smarter with AI: Functions & Arrays | G11: • Introduction to strings • 1D arrays + labs 1 & 2 | H11: 📖 Java tutorials (dev.java) | I11: ▶ Introduction to strings | J11: 3–4 problems/day on arrays, strings & functions | K11: =IF(B11="Yes",Overview!$C$5,0) -> 0 | L11: Not Started
A12: =IF(B12="Yes",COUNTIF(B$6:B12,"Yes"),"—") -> — | B12: =IF(Overview!$C$6="Beginner","Yes","No") -> No | C12: =IF(B12="Yes",Overview!$C$4+7*(COUNTIF(B$6:B12,"Yes")-1),"—") -> — | D12: =IF(B12="Yes",C12+6,"—") -> — | E12: 0. 🧱 Foundations | F12: Programming Fundamentals – Code Smarter with AI: Functions & Arrays | G12: • 2D arrays 1 + labs 1 & 2 • Strings in memory: visualising with AI | H12: 📖 GeeksforGeeks | I12: ▶ 2D arrays 1 + labs 1 & 2 | J12: 3–4 problems/day on arrays, strings & functions | K12: =IF(B12="Yes",Overview!$C$5,0) -> 0 | L12: Not Started
A13: =IF(B13="Yes",COUNTIF(B$6:B13,"Yes"),"—") -> — | B13: =IF(Overview!$C$6="Beginner","Yes","No") -> No | C13: =IF(B13="Yes",Overview!$C$4+7*(COUNTIF(B$6:B13,"Yes")-1),"—") -> — | D13: =IF(B13="Yes",C13+6,"—") -> — | E13: 0. 🧱 Foundations | F13: Programming Fundamentals – Code Smarter with AI: Functions & Arrays | G13: • Maths basics & calculating iterations • Revision: language • Contest 2: Functions & Arrays | H13: 📖 freeCodeCamp Learn | I13: ▶ Maths basics & calculating iterati… | J13: 3–4 problems/day on arrays, strings & functions ★ Milestone: Pass Contest 2 | K13: =IF(B13="Yes",Overview!$C$5,0) -> 0 | L13: Not Started
A14: =IF(B14="Yes",COUNTIF(B$6:B14,"Yes"),"—") -> 1 | B14: =IF(Overview!$C$6="Advanced","No","Yes") -> Yes | C14: =IF(B14="Yes",Overview!$C$4+7*(COUNTIF(B$6:B14,"Yes")-1),"—") -> 46307 | D14: =IF(B14="Yes",C14+6,"—") -> 46313 | E14: 1. 🧩 Problem Solving | F14: Intermediate DSA: AI-Assisted Problem Solving | G14: • Time complexity • Intro to arrays & basics of AI • Lab: TC, SC, output & debugging • Arrays: prefix sum & carry forward (AI-assisted) • Lab: prefix sum & carry forward • Array techniques & smart prompting | H14: 📖 NeetCode roadmap | I14: ▶ Time complexity | J14: 5–6 array/string problems/week; write TC/SC for each solution | K14: =IF(B14="Yes",Overview!$C$5,0) -> 20 | L14: Not Started | M14: Compressed from 4 wks (9-month plan)
A15: =IF(B15="Yes",COUNTIF(B$6:B15,"Yes"),"—") -> 2 | B15: =IF(Overview!$C$6="Advanced","No","Yes") -> Yes | C15: =IF(B15="Yes",Overview!$C$4+7*(COUNTIF(B$6:B15,"Yes")-1),"—") -> 46314 | D15: =IF(B15="Yes",C15+6,"—") -> 46320 | E15: 1. 🧩 Problem Solving | F15: Intermediate DSA: AI-Assisted Problem Solving | G15: • Lab: memory management & sorting basics • Bit manipulation basics • Lab: 2D matrices • Strings & immutability (AI visualisations) • Lab: matrix & strings using AI • Contest | H15: 📖 GeeksforGeeks DSA | I15: ▶ memory management & sorting basics | J15: 5–6 array/string problems/week; write TC/SC for each solution ★ Milestone: Pass the module contest | K15: =IF(B15="Yes",Overview!$C$5,0) -> 20 | L15: Not Started | M15: Compressed from 4 wks (9-month plan)
A16: =IF(B16="Yes",COUNTIF(B$6:B16,"Yes"),"—") -> 3 | B16: Yes | C16: =IF(B16="Yes",Overview!$C$4+7*(COUNTIF(B$6:B16,"Yes")-1),"—") -> 46321 | D16: =IF(B16="Yes",C16+6,"—") -> 46327 | E16: 2. 🤖 AI Skills | F16: Agentic AI: From Talking to AI to Building One | G16: • GenAI world & LLM landscape • Prompt engineering basics • Advanced prompting & AI safety basics • LLM built-in power tools • RAG | H16: 📖 n8n docs | I16: ▶ GenAI world & LLM landscape | J16: Build 1 small automation or agent per week; keep a prompt journal | K16: =IF(B16="Yes",Overview!$C$5,0) -> 20 | L16: Not Started | M16: Compressed from 4 wks (9-month plan)
A17: =IF(B17="Yes",COUNTIF(B$6:B17,"Yes"),"—") -> 4 | B17: Yes | C17: =IF(B17="Yes",Overview!$C$4+7*(COUNTIF(B$6:B17,"Yes")-1),"—") -> 46328 | D17: =IF(B17="Yes",C17+6,"—") -> 46334 | E17: 2. 🤖 AI Skills | F17: Agentic AI: From Talking to AI to Building One | G17: • n8n automation workflow • What is an AI agent? • Building agents with n8n • OpenClaw: personal 24/7 AI agent • Multi-agent systems • Debugging AI | H17: 📖 Prompt engineering guide (Anthropic) | I17: ▶ n8n automation workflow | J17: Build 1 small automation or agent per week; keep a prompt journal ★ Milestone: Working n8n agent demo | K17: =IF(B17="Yes",Overview!$C$5,0) -> 20 | L17: Not Started | M17: Compressed from 4 wks (9-month plan)
A18: =IF(B18="Yes",COUNTIF(B$6:B18,"Yes"),"—") -> 5 | B18: Yes | C18: =IF(B18="Yes",Overview!$C$4+7*(COUNTIF(B$6:B18,"Yes")-1),"—") -> 46335 | D18: =IF(B18="Yes",C18+6,"—") -> 46341 | E18: 3. 🧠 DSA | F18: Advanced DSA: Foundations – Core Techniques & Optimization | G18: • Time complexity • Arrays 1 (1D) & Arrays 2 (2D) • Lab: Arrays | H18: 📖 GeeksforGeeks DSA | I18: ▶ Time complexity | J18: 8–10 problems/week (LeetCode/InterviewBit); redo failed ones after 3 days | K18: =IF(B18="Yes",Overview!$C$5,0) -> 20 | L18: Not Started | M18: Compressed from 4 wks (9-month plan)
A19: =IF(B19="Yes",COUNTIF(B$6:B19,"Yes"),"—") -> 6 | B19: Yes | C19: =IF(B19="Yes",Overview!$C$4+7*(COUNTIF(B$6:B19,"Yes")-1),"—") -> 46342 | D19: =IF(B19="Yes",C19+6,"—") -> 46348 | E19: 3. 🧠 DSA | F19: Advanced DSA: Foundations – Core Techniques & Optimization | G19: • Bit manipulation + lab • Recursion + lab • Maths: modular arithmetic & GCD • Hashing + lab | H19: 📖 CP-Algorithms | I19: ▶ Bit manipulation + lab | J19: 8–10 problems/week (LeetCode/InterviewBit); redo failed ones after 3 days | K19: =IF(B19="Yes",Overview!$C$5,0) -> 20 | L19: Not Started | M19: Compressed from 4 wks (9-month plan)
A20: =IF(B20="Yes",COUNTIF(B$6:B20,"Yes"),"—") -> 7 | B20: Yes | C20: =IF(B20="Yes",Overview!$C$4+7*(COUNTIF(B$6:B20,"Yes")-1),"—") -> 46349 | D20: =IF(B20="Yes",C20+6,"—") -> 46355 | E20: 3. 🧠 DSA | F20: Advanced DSA: Foundations – Core Techniques & Optimization | G20: • Sorting 1: count sort & merge sort • Sorting 2: quick sort & comparator problems • Sample contest (dual-camera proctoring) • Contest 1: arrays, bits, recursion, math, hashing & sorting | H20: 📖 LeetCode problems | I20: ▶ count sort & merge sort | J20: 8–10 problems/week (LeetCode/InterviewBit); redo failed ones after 3 days ★ Milestone: Pass Contest 1 | K20: =IF(B20="Yes",Overview!$C$5,0) -> 20 | L20: Not Started | M20: Compressed from 4 wks (9-month plan)
A21: =IF(B21="Yes",COUNTIF(B$6:B21,"Yes"),"—") -> 8 | B21: Yes | C21: =IF(B21="Yes",Overview!$C$4+7*(COUNTIF(B$6:B21,"Yes")-1),"—") -> 46356 | D21: =IF(B21="Yes",C21+6,"—") -> 46362 | E21: 3. 🧠 DSA | F21: Advanced DSA: Linear & Non-Linear Structures | G21: • Searching 1: binary search on array • Searching 2: binary search on answer • Lab: Searching • Classes, objects & linked list intro | H21: 📖 GeeksforGeeks DSA | I21: ▶ binary search on array | J21: 8–10 problems/week; implement stack/queue/BST from scratch once | K21: =IF(B21="Yes",Overview!$C$5,0) -> 20 | L21: Not Started | M21: Compressed from 4 wks (9-month plan)
A22: =IF(B22="Yes",COUNTIF(B$6:B22,"Yes"),"—") -> 9 | B22: Yes | C22: =IF(B22="Yes",Overview!$C$4+7*(COUNTIF(B$6:B22,"Yes")-1),"—") -> 46363 | D22: =IF(B22="Yes",C22+6,"—") -> 46369 | E22: 3. 🧠 DSA | F22: Advanced DSA: Linear & Non-Linear Structures | G22: • Linked list: basic problems • Stacks + lab • Queues: implementation & problems • Trees 1: structure & traversal | H22: 📖 NeetCode roadmap | I22: ▶ basic problems | J22: 8–10 problems/week; implement stack/queue/BST from scratch once | K22: =IF(B22="Yes",Overview!$C$5,0) -> 20 | L22: Not Started | M22: Compressed from 4 wks (9-month plan)
A23: =IF(B23="Yes",COUNTIF(B$6:B23,"Yes"),"—") -> 10 | B23: Yes | C23: =IF(B23="Yes",Overview!$C$4+7*(COUNTIF(B$6:B23,"Yes")-1),"—") -> 46370 | D23: =IF(B23="Yes",C23+6,"—") -> 46376 | E23: 3. 🧠 DSA | F23: Advanced DSA: Linear & Non-Linear Structures | G23: • Trees 2: BST • Lab: Binary trees • Revision of DSA 1 & 2 • Contest 2: searching, linked list, stacks, queues & trees | H23: 📖 LeetCode problems | I23: ▶ Trees 2: BST | J23: 8–10 problems/week; implement stack/queue/BST from scratch once ★ Milestone: Pass Contest 2 | K23: =IF(B23="Yes",Overview!$C$5,0) -> 20 | L23: Not Started | M23: Compressed from 4 wks (9-month plan)
A24: =IF(B24="Yes",COUNTIF(B$6:B24,"Yes"),"—") -> 11 | B24: Yes | C24: =IF(B24="Yes",Overview!$C$4+7*(COUNTIF(B$6:B24,"Yes")-1),"—") -> 46377 | D24: =IF(B24="Yes",C24+6,"—") -> 46383 | E24: 3. 🧠 DSA | F24: Advanced DSA: Backtracking & Advanced Trees | G24: • Maths: combinatorics basics & prime numbers • Lab: prime numbers, 2 pointers & maths • Backtracking + lab | H24: 📖 GeeksforGeeks DSA | I24: ▶ combinatorics basics & prime numbe… | J24: 8–10 problems/week; solve every backtracking problem with a recursion tree sketch | K24: =IF(B24="Yes",Overview!$C$5,0) -> 20 | L24: Not Started | M24: Compressed from 4 wks (9-month plan)
A25: =IF(B25="Yes",COUNTIF(B$6:B25,"Yes"),"—") -> 12 | B25: Yes | C25: =IF(B25="Yes",Overview!$C$4+7*(COUNTIF(B$6:B25,"Yes")-1),"—") -> 46384 | D25: =IF(B25="Yes",C25+6,"—") -> 46390 | E25: 3. 🧠 DSA | F25: Advanced DSA: Backtracking & Advanced Trees | G25: • Linked list: sorting & problems • Linked list: doubly linked list & detecting loop • Trees 4: Morris inorder traversal + LCA | H25: 📖 CP-Algorithms | I25: ▶ sorting & problems | J25: 8–10 problems/week; solve every backtracking problem with a recursion tree sketch | K25: =IF(B25="Yes",Overview!$C$5,0) -> 20 | L25: Not Started | M25: Compressed from 4 wks (9-month plan)
A26: =IF(B26="Yes",COUNTIF(B$6:B26,"Yes"),"—") -> 13 | B26: Yes | C26: =IF(B26="Yes",Overview!$C$4+7*(COUNTIF(B$6:B26,"Yes")-1),"—") -> 46391 | D26: =IF(B26="Yes",C26+6,"—") -> 46397 | E26: 3. 🧠 DSA | F26: Advanced DSA: Backtracking & Advanced Trees | G26: • Lab: Binary trees 2 • Hashing 3: internal implementation & problems • Contest 3: math, two pointers, backtracking, linked list & trees | H26: 📖 LeetCode problems | I26: ▶ Binary trees 2 | J26: 8–10 problems/week; solve every backtracking problem with a recursion tree sketch ★ Milestone: Pass Contest 3 | K26: =IF(B26="Yes",Overview!$C$5,0) -> 20 | L26: Not Started | M26: Compressed from 4 wks (9-month plan)
A27: =IF(B27="Yes",COUNTIF(B$6:B27,"Yes"),"—") -> 14 | B27: Yes | C27: =IF(B27="Yes",Overview!$C$4+7*(COUNTIF(B$6:B27,"Yes")-1),"—") -> 46398 | D27: =IF(B27="Yes",C27+6,"—") -> 46404 | E27: 3. 🧠 DSA | F27: Advanced DSA: DP, Heaps & Graphs – Crack It with AI Edge | G27: • Heaps: introduction • Heap sort & greedy + lab • Lab: interview problems 1 | H27: 📖 CP-Algorithms | I27: ▶ introduction | J27: 10 problems/week incl. 3 DP + 3 graph; timed 45-min mock once a week | K27: =IF(B27="Yes",Overview!$C$5,0) -> 20 | L27: Not Started
A28: =IF(B28="Yes",COUNTIF(B$6:B28,"Yes"),"—") -> 15 | B28: Yes | C28: =IF(B28="Yes",Overview!$C$4+7*(COUNTIF(B$6:B28,"Yes")-1),"—") -> 46405 | D28: =IF(B28="Yes",C28+6,"—") -> 46411 | E28: 3. 🧠 DSA | F28: Advanced DSA: DP, Heaps & Graphs – Crack It with AI Edge | G28: • DP 1: one-dimensional • DP 2: two-dimensional • DP 3: knapsack + lab on applications • Graphs 1: intro, DFS & cycle detection | H28: 📖 NeetCode roadmap | I28: ▶ one-dimensional | J28: 10 problems/week incl. 3 DP + 3 graph; timed 45-min mock once a week | K28: =IF(B28="Yes",Overview!$C$5,0) -> 20 | L28: Not Started
A29: =IF(B29="Yes",COUNTIF(B$6:B29,"Yes"),"—") -> 16 | B29: Yes | C29: =IF(B29="Yes",Overview!$C$4+7*(COUNTIF(B$6:B29,"Yes")-1),"—") -> 46412 | D29: =IF(B29="Yes",C29+6,"—") -> 46418 | E29: 3. 🧠 DSA | F29: Advanced DSA: DP, Heaps & Graphs – Crack It with AI Edge | G29: • Graphs 2: BFS & MST • Graphs 3: Dijkstra & topological sort • Lab: interview problems 2 | H29: 📖 LeetCode problems | I29: ▶ Graphs 2: BFS & MST | J29: 10 problems/week incl. 3 DP + 3 graph; timed 45-min mock once a week | K29: =IF(B29="Yes",Overview!$C$5,0) -> 20 | L29: Not Started
A30: =IF(B30="Yes",COUNTIF(B$6:B30,"Yes"),"—") -> 17 | B30: Yes | C30: =IF(B30="Yes",Overview!$C$4+7*(COUNTIF(B$6:B30,"Yes")-1),"—") -> 46419 | D30: =IF(B30="Yes",C30+6,"—") -> 46425 | E30: 3. 🧠 DSA | F30: Advanced DSA: DP, Heaps & Graphs – Crack It with AI Edge | G30: • Revision of DSA 3 & 4 • Contest 4: heaps, greedy, DP & graphs • Mandatory DSA skill-evaluation test + discussion • Real-world projects: Social Network Analyzer & Invoice Merger | H30: 📖 CP-Algorithms | I30: ▶ Revision of DSA 3 & 4 | J30: 10 problems/week incl. 3 DP + 3 graph; timed 45-min mock once a week ★ Milestone: Pass the DSA Skill Evaluation Test; ship both DSA projects | K30: =IF(B30="Yes",Overview!$C$5,0) -> 20 | L30: Not Started
A31: =IF(B31="Yes",COUNTIF(B$6:B31,"Yes"),"—") -> 18 | B31: Yes | C31: =IF(B31="Yes",Overview!$C$4+7*(COUNTIF(B$6:B31,"Yes")-1),"—") -> 46426 | D31: =IF(B31="Yes",C31+6,"—") -> 46432 | E31: 4. 🗄️ Databases | F31: Databases & SQL | G31: • Intro to DBMS & keys • CRUD operations 1 & 2 • Joins • Aggregate queries • Joins & aggregates working session | H31: 📖 SQLBolt interactive | I31: ▶ Intro to DBMS & keys | J31: 10 SQL problems/week (joins, window functions); design 1 schema on paper per week | K31: =IF(B31="Yes",Overview!$C$5,0) -> 20 | L31: Not Started | M31: Compressed from 4 wks (9-month plan)
A32: =IF(B32="Yes",COUNTIF(B$6:B32,"Yes"),"—") -> 19 | B32: Yes | C32: =IF(B32="Yes",Overview!$C$4+7*(COUNTIF(B$6:B32,"Yes")-1),"—") -> 46433 | D32: =IF(B32="Yes",C32+6,"—") -> 46439 | E32: 4. 🗄️ Databases | F32: Databases & SQL | G32: • Subqueries & views • Indexing • Transactions • Window functions • Schema design 1 & 2 • Contest: SQL & schema design | H32: 📖 W3Schools SQL | I32: ▶ Subqueries & views | J32: 10 SQL problems/week (joins, window functions); design 1 schema on paper per week ★ Milestone: Pass the SQL & schema-design contest | K32: =IF(B32="Yes",Overview!$C$5,0) -> 20 | L32: Not Started | M32: Compressed from 4 wks (9-month plan)
A33: =IF(B33="Yes",COUNTIF(B$6:B33,"Yes"),"—") -> 20 | B33: Yes | C33: =IF(B33="Yes",Overview!$C$4+7*(COUNTIF(B$6:B33,"Yes")-1),"—") -> 46440 | D33: =IF(B33="Yes",C33+6,"—") -> 46446 | E33: 5. ⚙️ Backend & LLD | F33: Foundations of Object-Oriented Design & Scalable Systems | G33: • Intro to LLD for scalable & AI-ready systems • OOP-1: intro to OOP lab • OOP-2: access modifiers & constructors • OOP-3: inheritance & polymorphism | H33: 📖 Java tutorials (dev.java) | I33: ▶ Intro to LLD for scalable & AI-rea… | J33: Code along in Java daily; write a thread-safe producer–consumer | K33: =IF(B33="Yes",Overview!$C$5,0) -> 20 | L33: Not Started | M33: Compressed from 4 wks (9-month plan)
A34: =IF(B34="Yes",COUNTIF(B$6:B34,"Yes"),"—") -> 21 | B34: Yes | C34: =IF(B34="Yes",Overview!$C$4+7*(COUNTIF(B$6:B34,"Yes")-1),"—") -> 46447 | D34: =IF(B34="Yes",C34+6,"—") -> 46453 | E34: 5. ⚙️ Backend & LLD | F34: Foundations of Object-Oriented Design & Scalable Systems | G34: • OOP-4: interfaces & abstract classes • Concurrency 1: processes & threads • Concurrency 2: executors & callables • Concurrency 3: synchronization • Concurrency 4: semaphores | H34: 📖 Oracle: Java concurrency | I34: ▶ interfaces & abstract classes | J34: Code along in Java daily; write a thread-safe producer–consumer | K34: =IF(B34="Yes",Overview!$C$5,0) -> 20 | L34: Not Started | M34: Compressed from 4 wks (9-month plan)
A35: =IF(B35="Yes",COUNTIF(B$6:B35,"Yes"),"—") -> 22 | B35: Yes | C35: =IF(B35="Yes",Overview!$C$4+7*(COUNTIF(B$6:B35,"Yes")-1),"—") -> 46454 | D35: =IF(B35="Yes",C35+6,"—") -> 46460 | E35: 5. ⚙️ Backend & LLD | F35: Foundations of Object-Oriented Design & Scalable Systems | G35: • Java advanced 1: generics • Java advanced 2: generics & collections lab • Java advanced 3: streams & lambdas • Java advanced 4: exception handling & misc • Contest 1: Java, OOP & concurrency | H35: 📖 Refactoring Guru | I35: ▶ Java advanced 1: generics | J35: Code along in Java daily; write a thread-safe producer–consumer ★ Milestone: Pass Contest 1 | K35: =IF(B35="Yes",Overview!$C$5,0) -> 20 | L35: Not Started | M35: Compressed from 4 wks (9-month plan)
A36: =IF(B36="Yes",COUNTIF(B$6:B36,"Yes"),"—") -> 23 | B36: Yes | C36: =IF(B36="Yes",Overview!$C$4+7*(COUNTIF(B$6:B36,"Yes")-1),"—") -> 46461 | D36: =IF(B36="Yes",C36+6,"—") -> 46467 | E36: 5. ⚙️ Backend & LLD | F36: Design Principles & Patterns for Extensible Systems | G36: • SOLID principles with AI integrations • Design patterns: intro & Singleton • Builder • Prototype & Registry • Factory for service abstraction (APIs & AI services) | H36: 📖 Refactoring Guru patterns | I36: ▶ SOLID principles with AI integrati… | J36: Refactor one old project using 2 patterns; draw UML for each | K36: =IF(B36="Yes",Overview!$C$5,0) -> 20 | L36: Not Started | M36: Compressed from 4 wks (9-month plan)
A37: =IF(B37="Yes",COUNTIF(B$6:B37,"Yes"),"—") -> 24 | B37: Yes | C37: =IF(B37="Yes",Overview!$C$4+7*(COUNTIF(B$6:B37,"Yes")-1),"—") -> 46468 | D37: =IF(B37="Yes",C37+6,"—") -> 46474 | E37: 5. ⚙️ Backend & LLD | F37: Design Principles & Patterns for Extensible Systems | G37: • Adapter & Facade • Decorator & Flyweight • Behavioural patterns • UML diagrams • Contest 2: principles & patterns | H37: 📖 Refactoring Guru SOLID | I37: ▶ Adapter & Facade | J37: Refactor one old project using 2 patterns; draw UML for each ★ Milestone: Pass Contest 2 | K37: =IF(B37="Yes",Overview!$C$5,0) -> 20 | L37: Not Started | M37: Compressed from 4 wks (9-month plan)
A38: =IF(B38="Yes",COUNTIF(B$6:B38,"Yes"),"—") -> 25 | B38: Yes | C38: =IF(B38="Yes",Overview!$C$4+7*(COUNTIF(B$6:B38,"Yes")-1),"—") -> 46475 | D38: =IF(B38="Yes",C38+6,"—") -> 46481 | E38: 5. ⚙️ Backend & LLD | F38: Applied Design & Machine Coding | G38: • How to approach design problems • Design + code TicTacToe (2 sessions) | H38: 📖 Refactoring Guru patterns | I38: ▶ How to approach design problems | J38: Re-implement each LLD problem from a blank file in 90 minutes | K38: =IF(B38="Yes",Overview!$C$5,0) -> 20 | L38: Not Started | M38: Compressed from 4 wks (9-month plan)
A39: =IF(B39="Yes",COUNTIF(B$6:B39,"Yes"),"—") -> 26 | B39: Yes | C39: =IF(B39="Yes",Overview!$C$4+7*(COUNTIF(B$6:B39,"Yes")-1),"—") -> 46482 | D39: =IF(B39="Yes",C39+6,"—") -> 46488 | E39: 5. ⚙️ Backend & LLD | F39: Applied Design & Machine Coding | G39: • Design + code Parking Lot • Design BookMyShow • Code BookMyShow 1, 2 & 3 | H39: 📖 Java tutorials (dev.java) | I39: ▶ Design + code Parking Lot | J39: Re-implement each LLD problem from a blank file in 90 minutes | K39: =IF(B39="Yes",Overview!$C$5,0) -> 20 | L39: Not Started | M39: Compressed from 4 wks (9-month plan)
A40: =IF(B40="Yes",COUNTIF(B$6:B40,"Yes"),"—") -> 27 | B40: Yes | C40: =IF(B40="Yes",Overview!$C$4+7*(COUNTIF(B$6:B40,"Yes")-1),"—") -> 46489 | D40: =IF(B40="Yes",C40+6,"—") -> 46495 | E40: 5. ⚙️ Backend & LLD | F40: Applied Design & Machine Coding | G40: • Design Splitwise • Code Splitwise 1 & 2 • Machine coding | H40: 📖 InterviewBit | I40: ▶ Design Splitwise | J40: Re-implement each LLD problem from a blank file in 90 minutes ★ Milestone: Machine-coding round done in <90 min | K40: =IF(B40="Yes",Overview!$C$5,0) -> 20 | L40: Not Started | M40: Compressed from 4 wks (9-month plan)
A41: =IF(B41="Yes",COUNTIF(B$6:B41,"Yes"),"—") -> 28 | B41: Yes | C41: =IF(B41="Yes",Overview!$C$4+7*(COUNTIF(B$6:B41,"Yes")-1),"—") -> 46496 | D41: =IF(B41="Yes",C41+6,"—") -> 46502 | E41: 5. ⚙️ Backend & LLD | F41: AI-First Backend Capstone Project – Primer | G41: • Intro to backend systems & AI-augmented development • Version control & Git; Git commands & AI dev tools • Intro to Spring & building APIs | H41: 📖 Spring guides | I41: ▶ Intro to backend systems & AI-augm… | J41: Commit to Git daily; build the capstone service incrementally | K41: =IF(B41="Yes",Overview!$C$5,0) -> 20 | L41: Not Started | M41: Compressed from 4 wks (9-month plan)
A42: =IF(B42="Yes",COUNTIF(B$6:B42,"Yes"),"—") -> 29 | B42: Yes | C42: =IF(B42="Yes",Overview!$C$4+7*(COUNTIF(B$6:B42,"Yes")-1),"—") -> 46503 | D42: =IF(B42="Yes",C42+6,"—") -> 46509 | E42: 5. ⚙️ Backend & LLD | F42: AI-First Backend Capstone Project – Primer | G42: • MVC, requests in Spring & first microservice (AI integration) • Calling 3rd-party APIs & LLM/AI services • Intro to Spring Data JPA • JPA queries & repositories | H42: 📖 Git book | I42: ▶ MVC, requests in Spring & first mi… | J42: Commit to Git daily; build the capstone service incrementally | K42: =IF(B42="Yes",Overview!$C$5,0) -> 20 | L42: Not Started | M42: Compressed from 4 wks (9-month plan)
... A50: =IF(B50="Yes",COUNTIF(B$6:B50,"Yes"),"—") -> 37 | B50: Yes | C50: =IF(B50="Yes",Overview!$C$4+7*(COUNTIF(B$6:B50,"Yes")-1),"—") -> 46559 | D50: =IF(B50="Yes",C50+6,"—") -> 46565 | E50: 6. 🏗️ System Design | F50: Distributed System Design & AI-Integrated Architectures | G50: • Case study: Uber (nearest-neighbour search) • Case study: rate limiter + unique-ID generator • Case study: OTT platform • Microservices 1 & 2 • Case study: e-commerce platform | H50: 📖 System Design Primer | I50: ▶ Uber (nearest-neighbour search) | J50: Design 1 system/week on paper in 45 min; estimate QPS, storage & bandwidth ★ Milestone: 3 full HLD write-ups for your portfolio | K50: =IF(B50="Yes",Overview!$C$5,0) -> 20 | L50: Not Started | M50: Compressed from 6 wks (9-month plan)
A51: =IF(B51="Yes",COUNTIF(B$6:B51,"Yes"),"—") -> 38 | B51: Yes | C51: =IF(B51="Yes",Overview!$C$4+7*(COUNTIF(B$6:B51,"Yes")-1),"—") -> 46566 | D51: =IF(B51="Yes",C51+6,"—") -> 46572 | E51: 7. 🎯 Interview Prep | F51: Mastering LastMile – Interview Simulation | G51: • DSA interview simulation: problem solving & thinking under pressure | H51: 📖 InterviewBit | I51: ▶ problem solving & thinking under p… | J51: 2 mock interviews/week (peer, Pramp or Scaler); polish resume & LinkedIn | K51: =IF(B51="Yes",Overview!$C$5,0) -> 20 | L51: Not Started
A52: =IF(B52="Yes",COUNTIF(B$6:B52,"Yes"),"—") -> 39 | B52: Yes | C52: =IF(B52="Yes",Overview!$C$4+7*(COUNTIF(B$6:B52,"Yes")-1),"—") -> 46573 | D52: =IF(B52="Yes",C52+6,"—") -> 46579 | E52: 7. 🎯 Interview Prep | F52: Mastering LastMile – Interview Simulation | G52: • LLD interview simulation: structuring scalable solutions • HLD interview simulation: designing systems & communicating trade-offs | H52: 📖 LeetCode | I52: ▶ structuring scalable solutions | J52: 2 mock interviews/week (peer, Pramp or Scaler); polish resume & LinkedIn ★ Milestone: Offer-ready: resume, GitHub & 3 mock interviews done | K52: =IF(B52="Yes",Overview!$C$5,0) -> 20 | L52: Not Started
A53: =IF(B53="Yes",COUNTIF(B$6:B53,"Yes"),"—") -> — | B53: No | C53: =IF(B53="Yes",Overview!$C$4+7*(COUNTIF(B$6:B53,"Yes")-1),"—") -> — | D53: =IF(B53="Yes",C53+6,"—") -> — | E53: 8. ✨ Electives (optional) | F53: Build a Production-Ready AI-Enabled System | G53: • Intro to LLMs for backend engineers & prompt engineering for APIs | H53: 📖 OpenAI docs | I53: ▶ Intro to LLMs for backend engineer… | J53: Ship both AI projects with a public demo | K53: =IF(B53="Yes",Overview!$C$5,0) -> 0 | L53: Not Started
A54: =IF(B54="Yes",COUNTIF(B$6:B54,"Yes"),"—") -> — | B54: No | C54: =IF(B54="Yes",Overview!$C$4+7*(COUNTIF(B$6:B54,"Yes")-1),"—") -> — | D54: =IF(B54="Yes",C54+6,"—") -> — | E54: 8. ✨ Electives (optional) | F54: Build a Production-Ready AI-Enabled System | G54: • Build BookMyShow chat agent 1, 2 & 3 | H54: 📖 Anthropic docs | I54: ▶ Build BookMyShow chat agent 1, 2 &… | J54: Ship both AI projects with a public demo | K54: =IF(B54="Yes",Overview!$C$5,0) -> 0 | L54: Not Started
A55: =IF(B55="Yes",COUNTIF(B$6:B55,"Yes"),"—") -> — | B55: No | C55: =IF(B55="Yes",Overview!$C$4+7*(COUNTIF(B$6:B55,"Yes")-1),"—") -> — | D55: =IF(B55="Yes",C55+6,"—") -> — | E55: 8. ✨ Electives (optional) | F55: Build a Production-Ready AI-Enabled System | G55: • Build Splitwise AI receipt processor 1, 2 & 3 | H55: 📖 LangChain docs | I55: ▶ Build Splitwise AI receipt process… | J55: Ship both AI projects with a public demo | K55: =IF(B55="Yes",Overview!$C$5,0) -> 0 | L55: Not Started
A56: =IF(B56="Yes",COUNTIF(B$6:B56,"Yes"),"—") -> — | B56: No | C56: =IF(B56="Yes",Overview!$C$4+7*(COUNTIF(B$6:B56,"Yes")-1),"—") -> — | D56: =IF(B56="Yes",C56+6,"—") -> — | E56: 8. ✨ Electives (optional) | F56: Build a Production-Ready AI-Enabled System | G56: • Backend capstone project contest | H56: 📖 OpenAI docs | I56: ▶ Backend capstone project contest | J56: Ship both AI projects with a public demo ★ Milestone: Two deployed AI-enabled systems | K56: =IF(B56="Yes",Overview!$C$5,0) -> 0 | L56: Not Started
A57: =IF(B57="Yes",COUNTIF(B$6:B57,"Yes"),"—") -> — | B57: No | C57: =IF(B57="Yes",Overview!$C$4+7*(COUNTIF(B$6:B57,"Yes")-1),"—") -> — | D57: =IF(B57="Yes",C57+6,"—") -> — | E57: 8. ✨ Electives (optional) | F57: DSA Edge: Advanced Patterns & Interview Techniques | G57: • Townhall + revision of DSA topics • Maths: inverse mod & problems | H57: 📖 CP-Algorithms | I57: ▶ Townhall + revision of DSA topics | J57: 10–12 hard problems/week; weekly full-length timed contest | K57: =IF(B57="Yes",Overview!$C$5,0) -> 0 | L57: Not Started
A58: =IF(B58="Yes",COUNTIF(B$6:B58,"Yes"),"—") -> — | B58: No | C58: =IF(B58="Yes",Overview!$C$4+7*(COUNTIF(B$6:B58,"Yes")-1),"—") -> — | D58: =IF(B58="Yes",C58+6,"—") -> — | E58: 8. ✨ Electives (optional) | F58: DSA Edge: Advanced Patterns & Interview Techniques | G58: • Backtracking: famous problems • Tries 1 (characters) & Tries 2 (bits) + tree problems | H58: 📖 NeetCode roadmap | I58: ▶ famous problems | J58: 10–12 hard problems/week; weekly full-length timed contest | K58: =IF(B58="Yes",Overview!$C$5,0) -> 0 | L58: Not Started
A59: =IF(B59="Yes",COUNTIF(B$6:B59,"Yes"),"—") -> — | B59: No | C59: =IF(B59="Yes",Overview!$C$4+7*(COUNTIF(B$6:B59,"Yes")-1),"—") -> — | D59: =IF(B59="Yes",C59+6,"—") -> — | E59: 8. ✨ Electives (optional) | F59: DSA Edge: Advanced Patterns & Interview Techniques | G59: • String pattern matching • DP on strings & famous DP problems | H59: 📖 LeetCode problems | I59: ▶ String pattern matching | J59: 10–12 hard problems/week; weekly full-length timed contest | K59: =IF(B59="Yes",Overview!$C$5,0) -> 0 | L59: Not Started
A60: =IF(B60="Yes",COUNTIF(B$6:B60,"Yes"),"—") -> — | B60: No | C60: =IF(B60="Yes",Overview!$C$4+7*(COUNTIF(B$6:B60,"Yes")-1),"—") -> — | D60: =IF(B60="Yes",C60+6,"—") -> — | E60: 8. ✨ Electives (optional) | F60: DSA Edge: Advanced Patterns & Interview Techniques | G60: • Graphs: bipartite, Bellman-Ford & Floyd-Warshall • Advanced interview problems • Mandatory full-syllabus contest + discussion | H60: 📖 CP-Algorithms | I60: ▶ bipartite, Bellman-Ford & Floyd-Wa… | J60: 10–12 hard problems/week; weekly full-length timed contest ★ Milestone: Pass the full-syllabus contest | K60: =IF(B60="Yes",Overview!$C$5,0) -> 0 | L60: Not Started
A61: =IF(B61="Yes",COUNTIF(B$6:B61,"Yes"),"—") -> — | B61: No | C61: =IF(B61="Yes",Overview!$C$4+7*(COUNTIF(B$6:B61,"Yes")-1),"—") -> — | D61: =IF(B61="Yes",C61+6,"—") -> — | E61: 8. ✨ Electives (optional) | F61: Gen AI for Software Engineers | G61: • Intro to AI engineering • Refresher: modern text & image AI model architectures | H61: 📖 Hugging Face learn | I61: ▶ Intro to AI engineering | J61: Build one RAG app and one agent; write evals for both | K61: =IF(B61="Yes",Overview!$C$5,0) -> 0 | L61: Not Started
A62: =IF(B62="Yes",COUNTIF(B$6:B62,"Yes"),"—") -> — | B62: No | C62: =IF(B62="Yes",Overview!$C$4+7*(COUNTIF(B$6:B62,"Yes")-1),"—") -> — | D62: =IF(B62="Yes",C62+6,"—") -> — | E62: 8. ✨ Electives (optional) | F62: Gen AI for Software Engineers | G62: • Text generation & LLM APIs (OpenAI API) • Eval pipelines for AI apps & observability • Prompt engineering: introduction & security | H62: 📖 OpenAI docs | I62: ▶ Text generation & LLM APIs (OpenAI… | J62: Build one RAG app and one agent; write evals for both | K62: =IF(B62="Yes",Overview!$C$5,0) -> 0 | L62: Not Started
... A78: =IF(B78="Yes",COUNTIF(B$6:B78,"Yes"),"—") -> — | B78: No | C78: =IF(B78="Yes",Overview!$C$4+7*(COUNTIF(B$6:B78,"Yes")-1),"—") -> — | D78: =IF(B78="Yes",C78+6,"—") -> — | E78: 8. ✨ Electives (optional) | F78: Product Management for Engineers | G78: • Concept development, validation & the role of developers 1 & 2 • Intro to product analytics | H78: 📖 Atlassian PM guide | I78: ▶ Concept development, validation & … | J78: Write a 1-page PRD for a feature of your own project ★ Milestone: 1-page PRD | K78: =IF(B78="Yes",Overview!$C$5,0) -> 0 | L78: Not Started

Sheet FullStack Plan
A1: 9-Month Full-Stack Web Developer Plan – HTML/CSS · JS · React · Node/Mongo · SQL (39 weeks)
A2: Based on the Scaler Fullstack specialisation, enriched with Besant Technologies syllabus topics (Bootstrap, jQuery, MongoDB, Angular, PHP/Laravel).
A3: Edit the blue cells: Include?, Status, Notes. Start date, hours & level live on Overview. Links: 📖 opens a docs/tutorial page, ▶ opens a YouTube search for that week's first topic.
A5: Plan Wk | B5: Include? | C5: Start (Mon) | D5: End (Sun) | E5: Phase | F5: Module | G5: Topics this week | H5: 📖 Where to read | I5: ▶ YouTube (this week) | J5: Practice & milestone | K5: Hrs target | L5: Status | M5: Notes
A6: =IF(B6="Yes",COUNTIF(B$6:B6,"Yes"),"—") -> 1 | B6: Yes | C6: =IF(B6="Yes",Overview!$C$4+7*(COUNTIF(B$6:B6,"Yes")-1),"—") -> 46307 | D6: =IF(B6="Yes",C6+6,"—") -> 46313 | E6: 1. 🌐 Web Foundations | F6: HTML & CSS Foundations | G6: • How the web works: browsers, HTML, DevTools & AI inspection • Semantic HTML, forms & structured user input • CSS foundations: cascade, selectors, box model & units • Layout I: display, positioning & Flexbox | H6: 📖 MDN Learn Web Dev | I6: ▶ browsers, HTML, DevTools & AI insp… | J6: Rebuild 2 real landing pages pixel-perfect; make both responsive | K6: =IF(B6="Yes",Overview!$C$5,0) -> 20 | L6: Not Started
A7: =IF(B7="Yes",COUNTIF(B$6:B7,"Yes"),"—") -> 2 | B7: Yes | C7: =IF(B7="Yes",Overview!$C$4+7*(COUNTIF(B$6:B7,"Yes")-1),"—") -> 46314 | D7: =IF(B7="Yes",C7+6,"—") -> 46320 | E7: 1. 🌐 Web Foundations | F7: HTML & CSS Foundations | G7: • Layout II: responsive design, media queries & Grid • CSS variables, transitions & visual polish • UI debugging: specificity, inheritance, stacking & DevTools • From design to code: AI-assisted UI build, review & refinement • HTML & CSS certification contest | H7: 📖 web.dev Learn CSS | I7: ▶ responsive design, media queries &… | J7: Rebuild 2 real landing pages pixel-perfect; make both responsive ★ Milestone: Responsive portfolio landing page | K7: =IF(B7="Yes",Overview!$C$5,0) -> 20 | L7: Not Started
A8: =IF(B8="Yes",COUNTIF(B$6:B8,"Yes"),"—") -> — | B8: No | C8: =IF(B8="Yes",Overview!$C$4+7*(COUNTIF(B$6:B8,"Yes")-1),"—") -> — | D8: =IF(B8="Yes",C8+6,"—") -> — | E8: 1. 🌐 Web Foundations | F8: Bootstrap (supplementary) | G8: • Introduction to Bootstrap & basics • Bootstrap grids • Bootstrap themes • Bootstrap CSS utilities • Bootstrap JS components | H8: 📖 Bootstrap docs | I8: ▶ Introduction to Bootstrap & basics | J8: Re-skin your landing page with Bootstrap ★ Milestone: Bootstrap dashboard layout | K8: =IF(B8="Yes",Overview!$C$5,0) -> 0 | L8: Not Started | M8: Source: Besant syllabus
A9: =IF(B9="Yes",COUNTIF(B$6:B9,"Yes"),"—") -> 3 | B9: Yes | C9: =IF(B9="Yes",Overview!$C$4+7*(COUNTIF(B$6:B9,"Yes")-1),"—") -> 46321 | D9: =IF(B9="Yes",C9+6,"—") -> 46327 | E9: 2. ⚡ JavaScript | F9: JavaScript Runtime Systems, Browser APIs & Product Labs | G9: • JS foundations: values, types, variables & control flow • Execution model: scope & hoisting • Closures, lexical scope & persistent state | H9: 📖 javascript.info | I9: ▶ values, types, variables & control… | J9: Daily 30-min JS drills (closures, promises, array HOFs); 2 machine-coding UIs/week | K9: =IF(B9="Yes",Overview!$C$5,0) -> 20 | L9: Not Started
A10: =IF(B10="Yes",COUNTIF(B$6:B10,"Yes"),"—") -> 4 | B10: Yes | C10: =IF(B10="Yes",Overview!$C$4+7*(COUNTIF(B$6:B10,"Yes")-1),"—") -> 46328 | D10: =IF(B10="Yes",C10+6,"—") -> 46334 | E10: 2. ⚡ JavaScript | F10: JavaScript Runtime Systems, Browser APIs & Product Labs | G10: • Runtime reasoning lab: predict output & debug • Functional JS: functions, callbacks & higher-order • Browser as a runtime: DOM & browser APIs | H10: 📖 MDN JavaScript | I10: ▶ predict output & debug | J10: Daily 30-min JS drills (closures, promises, array HOFs); 2 machine-coding UIs/week | K10: =IF(B10="Yes",Overview!$C$5,0) -> 20 | L10: Not Started
A11: =IF(B11="Yes",COUNTIF(B$6:B11,"Yes"),"—") -> 5 | B11: Yes | C11: =IF(B11="Yes",Overview!$C$4+7*(COUNTIF(B$6:B11,"Yes")-1),"—") -> 46335 | D11: =IF(B11="Yes",C11+6,"—") -> 46341 | E11: 2. ⚡ JavaScript | F11: JavaScript Runtime Systems, Browser APIs & Product Labs | G11: • Event systems: user interaction & handlers • Product Lab I: real-time Weather App (JSON, APIs, async, rendering) • Product Labs II–V: Kanban board (UI structure, DOM rendering, logic, localStorage, edge cases) | H11: 📖 JS30 projects | I11: ▶ user interaction & handlers | J11: Daily 30-min JS drills (closures, promises, array HOFs); 2 machine-coding UIs/week | K11: =IF(B11="Yes",Overview!$C$5,0) -> 20 | L11: Not Started
A12: =IF(B12="Yes",COUNTIF(B$6:B12,"Yes"),"—") -> 6 | B12: Yes | C12: =IF(B12="Yes",Overview!$C$4+7*(COUNTIF(B$6:B12,"Yes")-1),"—") -> 46342 | D12: =IF(B12="Yes",C12+6,"—") -> 46348 | E12: 2. ⚡ JavaScript | F12: JavaScript Runtime Systems, Browser APIs & Product Labs | G12: • Async I: callbacks, Web APIs & non-blocking execution • Async II: promises, microtasks & chaining • Async III: async/await & error handling | H12: 📖 javascript.info | I12: ▶ callbacks, Web APIs & non-blocking… | J12: Daily 30-min JS drills (closures, promises, array HOFs); 2 machine-coding UIs/week | K12: =IF(B12="Yes",Overview!$C$5,0) -> 20 | L12: Not Started
A13: =IF(B13="Yes",COUNTIF(B$6:B13,"Yes"),"—") -> 7 | B13: Yes | C13: =IF(B13="Yes",Overview!$C$4+7*(COUNTIF(B$6:B13,"Yes")-1),"—") -> 46349 | D13: =IF(B13="Yes",C13+6,"—") -> 46355 | E13: 2. ⚡ JavaScript | F13: JavaScript Runtime Systems, Browser APIs & Product Labs | G13: • Async IV: promise combinators & real-world patterns • Async debugging lab: race conditions & failure states • Browser event flow: bubbling, capturing & propagation | H13: 📖 MDN JavaScript | I13: ▶ promise combinators & real-world p… | J13: Daily 30-min JS drills (closures, promises, array HOFs); 2 machine-coding UIs/week | K13: =IF(B13="Yes",Overview!$C$5,0) -> 20 | L13: Not Started
A14: =IF(B14="Yes",COUNTIF(B$6:B14,"Yes"),"—") -> 8 | B14: Yes | C14: =IF(B14="Yes",Overview!$C$4+7*(COUNTIF(B$6:B14,"Yes")-1),"—") -> 46356 | D14: =IF(B14="Yes",C14+6,"—") -> 46362 | E14: 2. ⚡ JavaScript | F14: JavaScript Runtime Systems, Browser APIs & Product Labs | G14: • Interaction patterns: event delegation & machine coding • Performance patterns: debouncing & throttling • Object model I: this, method context & invocation • JS certification contest | H14: 📖 JS30 projects | I14: ▶ event delegation & machine coding | J14: Daily 30-min JS drills (closures, promises, array HOFs); 2 machine-coding UIs/week ★ Milestone: Weather App + Kanban board live | K14: =IF(B14="Yes",Overview!$C$5,0) -> 20 | L14: Not Started
A15: =IF(B15="Yes",COUNTIF(B$6:B15,"Yes"),"—") -> 9 | B15: Yes | C15: =IF(B15="Yes",Overview!$C$4+7*(COUNTIF(B$6:B15,"Yes")-1),"—") -> 46363 | D15: =IF(B15="Yes",C15+6,"—") -> 46369 | E15: 2. ⚡ JavaScript | F15: JavaScript Object System & Engineering Patterns | G15: • Object model II: classes, constructors & OO modelling • Object model III: prototypes, inheritance & reusable behaviour | H15: 📖 javascript.info prototypes | I15: ▶ classes, constructors & OO modelli… | J15: Write polyfills for map/filter/reduce/bind/Promise.all from scratch | K15: =IF(B15="Yes",Overview!$C$5,0) -> 20 | L15: Not Started
A16: =IF(B16="Yes",COUNTIF(B$6:B16,"Yes"),"—") -> 10 | B16: Yes | C16: =IF(B16="Yes",Overview!$C$4+7*(COUNTIF(B$6:B16,"Yes")-1),"—") -> 46370 | D16: =IF(B16="Yes",C16+6,"—") -> 46376 | E16: 2. ⚡ JavaScript | F16: JavaScript Object System & Engineering Patterns | G16: • Engineering lab: call, apply, bind & polyfill thinking • Polyfills lab: higher-order methods • Data handling lab: deep copy, shallow copy & reference behaviour | H16: 📖 javascript.info classes | I16: ▶ call, apply, bind & polyfill think… | J16: Write polyfills for map/filter/reduce/bind/Promise.all from scratch ★ Milestone: Own mini-utility library (lodash-style) | K16: =IF(B16="Yes",Overview!$C$5,0) -> 20 | L16: Not Started
A17: =IF(B17="Yes",COUNTIF(B$6:B17,"Yes"),"—") -> — | B17: No | C17: =IF(B17="Yes",Overview!$C$4+7*(COUNTIF(B$6:B17,"Yes")-1),"—") -> — | D17: =IF(B17="Yes",C17+6,"—") -> — | E17: 2. ⚡ JavaScript | F17: jQuery (legacy, optional) | G17: • Intro to jQuery & syntax • jQuery selectors • jQuery events & effects • jQuery HTML & traversing • jQuery AJAX & misc | H17: 📖 jQuery Learning Center | I17: ▶ Intro to jQuery & syntax | J17: Only needed for maintaining older codebases ★ Milestone: Convert one jQuery snippet to vanilla JS | K17: =IF(B17="Yes",Overview!$C$5,0) -> 0 | L17: Not Started | M17: Source: Besant syllabus
A18: =IF(B18="Yes",COUNTIF(B$6:B18,"Yes"),"—") -> 11 | B18: Yes | C18: =IF(B18="Yes",Overview!$C$4+7*(COUNTIF(B$6:B18,"Yes")-1),"—") -> 46377 | D18: =IF(B18="Yes",C18+6,"—") -> 46383 | E18: 3. ⚛️ React | F18: React & Frontend Product Architecture Fundamentals | G18: • React foundations: components, JSX & thinking in UI trees • React tooling & TypeScript setup: build tools, JSX, TS basics & project structure • Props, lists, forms & typed component composition | H18: 📖 React docs (react.dev) | I18: ▶ components, JSX & thinking in UI t… | J18: Build every lab from an empty folder; deploy to Netlify/Vercel | K18: =IF(B18="Yes",Overview!$C$5,0) -> 20 | L18: Not Started
A19: =IF(B19="Yes",COUNTIF(B$6:B19,"Yes"),"—") -> 12 | B19: Yes | C19: =IF(B19="Yes",Overview!$C$4+7*(COUNTIF(B$6:B19,"Yes")-1),"—") -> 46384 | D19: =IF(B19="Yes",C19+6,"—") -> 46390 | E19: 3. ⚛️ React | F19: React & Frontend Product Architecture Fundamentals | G19: • State, events & interactive UI • Lifting state up, useEffect & data flow • Product Lab 1: IMDB app – setup, routing & frontend structure | H19: 📖 Redux essentials | I19: ▶ State, events & interactive UI | J19: Build every lab from an empty folder; deploy to Netlify/Vercel | K19: =IF(B19="Yes",Overview!$C$5,0) -> 20 | L19: Not Started
A20: =IF(B20="Yes",COUNTIF(B$6:B20,"Yes"),"—") -> 13 | B20: Yes | C20: =IF(B20="Yes",Overview!$C$4+7*(COUNTIF(B$6:B20,"Yes")-1),"—") -> 46391 | D20: =IF(B20="Yes",C20+6,"—") -> 46397 | E20: 3. ⚛️ React | F20: React & Frontend Product Architecture Fundamentals | G20: • Product Lab 2: IMDB app – movies page, pagination & data rendering • Product Lab 3: IMDB app – API integration, watchlist & localStorage • Product Lab 4: IMDB app – search, sorting, filtering & shared state | H20: 📖 React Router | I20: ▶ IMDB app – movies page, pagination… | J20: Build every lab from an empty folder; deploy to Netlify/Vercel | K20: =IF(B20="Yes",Overview!$C$5,0) -> 20 | L20: Not Started
A21: =IF(B21="Yes",COUNTIF(B$6:B21,"Yes"),"—") -> 14 | B21: Yes | C21: =IF(B21="Yes",Overview!$C$4+7*(COUNTIF(B$6:B21,"Yes")-1),"—") -> 46398 | D21: =IF(B21="Yes",C21+6,"—") -> 46404 | E21: 3. ⚛️ React | F21: React & Frontend Product Architecture Fundamentals | G21: • Context API, state sharing & component communication • Redux foundations: store design, actions & predictable state • Redux integration lab: product-scale state management • React certification contest | H21: 📖 React docs (react.dev) | I21: ▶ Context API, state sharing & compo… | J21: Build every lab from an empty folder; deploy to Netlify/Vercel ★ Milestone: IMDB app deployed | K21: =IF(B21="Yes",Overview!$C$5,0) -> 20 | L21: Not Started
A22: =IF(B22="Yes",COUNTIF(B$6:B22,"Yes"),"—") -> 15 | B22: Yes | C22: =IF(B22="Yes",Overview!$C$4+7*(COUNTIF(B$6:B22,"Yes")-1),"—") -> 46405 | D22: =IF(B22="Yes",C22+6,"—") -> 46411 | E22: 4. 🛠️ Backend (MERN) | F22: Backend Product Systems, APIs & Production Engineering (MERN) | G22: • Backend foundations: Node.js, APIs, Express & service thinking • REST endpoints: GET/POST/PUT/DELETE tested with Postman; build a Genres API • Data systems: MongoDB, Mongoose, schema design & SQL vs NoSQL | H22: 📖 Node.js learn | I22: ▶ Node.js, APIs, Express & service t… | J22: Test every endpoint in Postman; add 1 new endpoint/day beyond the labs | K22: =IF(B22="Yes",Overview!$C$5,0) -> 20 | L22: Not Started
A23: =IF(B23="Yes",COUNTIF(B$6:B23,"Yes"),"—") -> 16 | B23: Yes | C23: =IF(B23="Yes",Overview!$C$4+7*(COUNTIF(B$6:B23,"Yes")-1),"—") -> 46412 | D23: =IF(B23="Yes",C23+6,"—") -> 46418 | E23: 4. 🛠️ Backend (MERN) | F23: Backend Product Systems, APIs & Production Engineering (MERN) | G23: • MongoDB: filters, indexing, aggregation, schema validation & embedded documents • Middleware, validation & MVC structure; Express advanced topics (config, debugging, structuring apps) • Product Lab 1: architecture, domain modelling & project setup • Product Lab 2: authentication, authorization & role-based access | H23: 📖 Express docs | I23: ▶ filters, indexing, aggregation, sc… | J23: Test every endpoint in Postman; add 1 new endpoint/day beyond the labs | K23: =IF(B23="Yes",Overview!$C$5,0) -> 20 | L23: Not Started
A24: =IF(B24="Yes",COUNTIF(B$6:B24,"Yes"),"—") -> 17 | B24: Yes | C24: =IF(B24="Yes",Overview!$C$4+7*(COUNTIF(B$6:B24,"Yes")-1),"—") -> 46419 | D24: =IF(B24="Yes",C24+6,"—") -> 46425 | E24: 4. 🛠️ Backend (MERN) | F24: Backend Product Systems, APIs & Production Engineering (MERN) | G24: • Product Lab 3: protected routes, tokens & session-aware flows (JWT) • Product Lab 4: movies, theatres & show APIs • Product Lab 5: partner workflows, admin approval & moderation • Product Lab 6: booking flow, seat management & transaction safety | H24: 📖 Mongoose docs | I24: ▶ protected routes, tokens & session… | J24: Test every endpoint in Postman; add 1 new endpoint/day beyond the labs | K24: =IF(B24="Yes",Overview!$C$5,0) -> 20 | L24: Not Started
A25: =IF(B25="Yes",COUNTIF(B$6:B25,"Yes"),"—") -> 18 | B25: Yes | C25: =IF(B25="Yes",Overview!$C$4+7*(COUNTIF(B$6:B25,"Yes")-1),"—") -> 46426 | D25: =IF(B25="Yes",C25+6,"—") -> 46432 | E25: 4. 🛠️ Backend (MERN) | F25: Backend Product Systems, APIs & Production Engineering (MERN) | G25: • Product Lab 7: payments, ticket generation & order lifecycle (payment gateway) • Product Lab 8: email workflows, password reset & user communication • Realtime backend: WebSockets, live updates & event-driven flows • MERN certification contest | H25: 📖 Node.js learn | I25: ▶ payments, ticket generation & orde… | J25: Test every endpoint in Postman; add 1 new endpoint/day beyond the labs ★ Milestone: Booking-platform API deployed | K25: =IF(B25="Yes",Overview!$C$5,0) -> 20 | L25: Not Started
A26: =IF(B26="Yes",COUNTIF(B$6:B26,"Yes"),"—") -> 19 | B26: Yes | C26: =IF(B26="Yes",Overview!$C$4+7*(COUNTIF(B$6:B26,"Yes")-1),"—") -> 46433 | D26: =IF(B26="Yes",C26+6,"—") -> 46439 | E26: 4. 🛠️ Backend (MERN) | F26: Databases & SQL | G26: • Intro to DBMS & keys • CRUD operations 1 & 2 | H26: 📖 SQLBolt interactive | I26: ▶ Intro to DBMS & keys | J26: 10 SQL problems/week; compare one feature in SQL vs MongoDB | K26: =IF(B26="Yes",Overview!$C$5,0) -> 20 | L26: Not Started
A27: =IF(B27="Yes",COUNTIF(B$6:B27,"Yes"),"—") -> 20 | B27: Yes | C27: =IF(B27="Yes",Overview!$C$4+7*(COUNTIF(B$6:B27,"Yes")-1),"—") -> 46440 | D27: =IF(B27="Yes",C27+6,"—") -> 46446 | E27: 4. 🛠️ Backend (MERN) | F27: Databases & SQL | G27: • Joins & aggregate queries • Subqueries & views | H27: 📖 W3Schools SQL | I27: ▶ Joins & aggregate queries | J27: 10 SQL problems/week; compare one feature in SQL vs MongoDB | K27: =IF(B27="Yes",Overview!$C$5,0) -> 20 | L27: Not Started
A28: =IF(B28="Yes",COUNTIF(B$6:B28,"Yes"),"—") -> 21 | B28: Yes | C28: =IF(B28="Yes",Overview!$C$4+7*(COUNTIF(B$6:B28,"Yes")-1),"—") -> 46447 | D28: =IF(B28="Yes",C28+6,"—") -> 46453 | E28: 4. 🛠️ Backend (MERN) | F28: Databases & SQL | G28: • Indexing & transactions • Window functions | H28: 📖 Mode SQL tutorial | I28: ▶ Indexing & transactions | J28: 10 SQL problems/week; compare one feature in SQL vs MongoDB | K28: =IF(B28="Yes",Overview!$C$5,0) -> 20 | L28: Not Started
A29: =IF(B29="Yes",COUNTIF(B$6:B29,"Yes"),"—") -> 22 | B29: Yes | C29: =IF(B29="Yes",Overview!$C$4+7*(COUNTIF(B$6:B29,"Yes")-1),"—") -> 46454 | D29: =IF(B29="Yes",C29+6,"—") -> 46460 | E29: 4. 🛠️ Backend (MERN) | F29: Databases & SQL | G29: • Schema design 1 & 2 • Contest: SQL & schema design | H29: 📖 SQLBolt interactive | I29: ▶ Schema design 1 & 2 | J29: 10 SQL problems/week; compare one feature in SQL vs MongoDB ★ Milestone: Pass the SQL contest | K29: =IF(B29="Yes",Overview!$C$5,0) -> 20 | L29: Not Started
... A37: =IF(B37="Yes",COUNTIF(B$6:B37,"Yes"),"—") -> 30 | B37: Yes | C37: =IF(B37="Yes",Overview!$C$4+7*(COUNTIF(B$6:B37,"Yes")-1),"—") -> 46510 | D37: =IF(B37="Yes",C37+6,"—") -> 46516 | E37: 5. 🚀 Advanced Frontend | F37: Foundations of AI-Assisted Full-Stack Development | G37: • Reviewing & validating AI-generated full-stack code • From screen to server: AI-assisted workflows • Building faster without losing fundamentals | H37: 📖 Anthropic docs | I37: ▶ Reviewing & validating AI-generate… | J37: Build a small feature with AI help, then review it line by line ★ Milestone: AI-assisted workflow checklist | K37: =IF(B37="Yes",Overview!$C$5,0) -> 20 | L37: Not Started
A38: =IF(B38="Yes",COUNTIF(B$6:B38,"Yes"),"—") -> 31 | B38: Yes | C38: =IF(B38="Yes",Overview!$C$4+7*(COUNTIF(B$6:B38,"Yes")-1),"—") -> 46517 | D38: =IF(B38="Yes",C38+6,"—") -> 46523 | E38: 6. 🏆 Capstone | F38: Full-Stack Capstone Project (suggested) | G38: • Scope, wireframes & data model | H38: 📖 GitHub docs | I38: ▶ Scope, wireframes & data model | J38: Pick an original idea (not a tutorial clone); commit daily | K38: =IF(B38="Yes",Overview!$C$5,0) -> 20 | L38: Not Started | M38: Source: Suggested (not in sources)
A39: =IF(B39="Yes",COUNTIF(B$6:B39,"Yes"),"—") -> 32 | B39: Yes | C39: =IF(B39="Yes",Overview!$C$4+7*(COUNTIF(B$6:B39,"Yes")-1),"—") -> 46524 | D39: =IF(B39="Yes",C39+6,"—") -> 46530 | E39: 6. 🏆 Capstone | F39: Full-Stack Capstone Project (suggested) | G39: • Build UI + authentication • Build APIs & connect frontend | H39: 📖 Vercel docs | I39: ▶ Build UI + authentication | J39: Pick an original idea (not a tutorial clone); commit daily | K39: =IF(B39="Yes",Overview!$C$5,0) -> 20 | L39: Not Started | M39: Source: Suggested (not in sources)
A40: =IF(B40="Yes",COUNTIF(B$6:B40,"Yes"),"—") -> 33 | B40: Yes | C40: =IF(B40="Yes",Overview!$C$4+7*(COUNTIF(B$6:B40,"Yes")-1),"—") -> 46531 | D40: =IF(B40="Yes",C40+6,"—") -> 46537 | E40: 6. 🏆 Capstone | F40: Full-Stack Capstone Project (suggested) | G40: • Add one AI feature (LLM API) • Testing, deployment, README & demo video | H40: 📖 Render docs | I40: ▶ Add one AI feature (LLM API) | J40: Pick an original idea (not a tutorial clone); commit daily ★ Milestone: Public GitHub repo + live demo + 2-min demo video | K40: =IF(B40="Yes",Overview!$C$5,0) -> 20 | L40: Not Started | M40: Source: Suggested (not in sources)
A41: =IF(B41="Yes",COUNTIF(B$6:B41,"Yes"),"—") -> 34 | B41: Yes | C41: =IF(B41="Yes",Overview!$C$4+7*(COUNTIF(B$6:B41,"Yes")-1),"—") -> 46538 | D41: =IF(B41="Yes",C41+6,"—") -> 46544 | E41: 7. 🎯 Interview Readiness | F41: Intermediate DSA: AI-Assisted Problem Solving | G41: • Time complexity • Arrays: prefix sum & carry forward | H41: 📖 NeetCode roadmap | I41: ▶ Time complexity | J41: 5–6 problems/week; start in parallel from the JavaScript phase if you can (30–45 min/day) | K41: =IF(B41="Yes",Overview!$C$5,0) -> 20 | L41: Not Started
A42: =IF(B42="Yes",COUNTIF(B$6:B42,"Yes"),"—") -> 35 | B42: Yes | C42: =IF(B42="Yes",Overview!$C$4+7*(COUNTIF(B$6:B42,"Yes")-1),"—") -> 46545 | D42: =IF(B42="Yes",C42+6,"—") -> 46551 | E42: 7. 🎯 Interview Readiness | F42: Intermediate DSA: AI-Assisted Problem Solving | G42: • Array techniques & smart prompting • Memory management & sorting basics | H42: 📖 GeeksforGeeks DSA | I42: ▶ Array techniques & smart prompting | J42: 5–6 problems/week; start in parallel from the JavaScript phase if you can (30–45 min/day) | K42: =IF(B42="Yes",Overview!$C$5,0) -> 20 | L42: Not Started
A43: =IF(B43="Yes",COUNTIF(B$6:B43,"Yes"),"—") -> 36 | B43: Yes | C43: =IF(B43="Yes",Overview!$C$4+7*(COUNTIF(B$6:B43,"Yes")-1),"—") -> 46552 | D43: =IF(B43="Yes",C43+6,"—") -> 46558 | E43: 7. 🎯 Interview Readiness | F43: Intermediate DSA: AI-Assisted Problem Solving | G43: • Bit manipulation basics • 2D matrices | H43: 📖 LeetCode problems | I43: ▶ Bit manipulation basics | J43: 5–6 problems/week; start in parallel from the JavaScript phase if you can (30–45 min/day) | K43: =IF(B43="Yes",Overview!$C$5,0) -> 20 | L43: Not Started
A44: =IF(B44="Yes",COUNTIF(B$6:B44,"Yes"),"—") -> 37 | B44: Yes | C44: =IF(B44="Yes",Overview!$C$4+7*(COUNTIF(B$6:B44,"Yes")-1),"—") -> 46559 | D44: =IF(B44="Yes",C44+6,"—") -> 46565 | E44: 7. 🎯 Interview Readiness | F44: Intermediate DSA: AI-Assisted Problem Solving | G44: • Strings & immutability • Contest | H44: 📖 NeetCode roadmap | I44: ▶ Strings & immutability | J44: 5–6 problems/week; start in parallel from the JavaScript phase if you can (30–45 min/day) ★ Milestone: Pass the module contest | K44: =IF(B44="Yes",Overview!$C$5,0) -> 20 | L44: Not Started
A45: =IF(B45="Yes",COUNTIF(B$6:B45,"Yes"),"—") -> 38 | B45: Yes | C45: =IF(B45="Yes",Overview!$C$4+7*(COUNTIF(B$6:B45,"Yes")-1),"—") -> 46566 | D45: =IF(B45="Yes",C45+6,"—") -> 46572 | E45: 7. 🎯 Interview Readiness | F45: Mastering LastMile – Interview Simulation | G45: • DSA interview simulation | H45: 📖 InterviewBit | I45: ▶ DSA interview simulation | J45: 2 mock interviews/week; polish resume, portfolio & LinkedIn | K45: =IF(B45="Yes",Overview!$C$5,0) -> 20 | L45: Not Started
A46: =IF(B46="Yes",COUNTIF(B$6:B46,"Yes"),"—") -> 39 | B46: Yes | C46: =IF(B46="Yes",Overview!$C$4+7*(COUNTIF(B$6:B46,"Yes")-1),"—") -> 46573 | D46: =IF(B46="Yes",C46+6,"—") -> 46579 | E46: 7. 🎯 Interview Readiness | F46: Mastering LastMile – Interview Simulation | G46: • LLD / machine-coding simulation (frontend focus) • HLD simulation: designing systems & communicating trade-offs | H46: 📖 LeetCode | I46: ▶ LLD / machine-coding simulation (f… | J46: 2 mock interviews/week; polish resume, portfolio & LinkedIn ★ Milestone: Offer-ready portfolio | K46: =IF(B46="Yes",Overview!$C$5,0) -> 20 | L46: Not Started
A47: =IF(B47="Yes",COUNTIF(B$6:B47,"Yes"),"—") -> — | B47: No | C47: =IF(B47="Yes",Overview!$C$4+7*(COUNTIF(B$6:B47,"Yes")-1),"—") -> — | D47: =IF(B47="Yes",C47+6,"—") -> — | E47: 8. ✨ Optional extensions | F47: Advanced DSA (all 4 modules, condensed) | G47: • Core techniques: arrays, bits, recursion, hashing & sorting | H47: 📖 NeetCode roadmap | I47: ▶ arrays, bits, recursion, hashing &… | J47: Choose this if targeting product-based companies | K47: =IF(B47="Yes",Overview!$C$5,0) -> 0 | L47: Not Started
A48: =IF(B48="Yes",COUNTIF(B$6:B48,"Yes"),"—") -> — | B48: No | C48: =IF(B48="Yes",Overview!$C$4+7*(COUNTIF(B$6:B48,"Yes")-1),"—") -> — | D48: =IF(B48="Yes",C48+6,"—") -> — | E48: 8. ✨ Optional extensions | F48: Advanced DSA (all 4 modules, condensed) | G48: • Core techniques: arrays, bits, recursion, hashing & sorting | H48: 📖 CP-Algorithms | I48: ▶ arrays, bits, recursion, hashing &… | J48: Choose this if targeting product-based companies | K48: =IF(B48="Yes",Overview!$C$5,0) -> 0 | L48: Not Started
A49: =IF(B49="Yes",COUNTIF(B$6:B49,"Yes"),"—") -> — | B49: No | C49: =IF(B49="Yes",Overview!$C$4+7*(COUNTIF(B$6:B49,"Yes")-1),"—") -> — | D49: =IF(B49="Yes",C49+6,"—") -> — | E49: 8. ✨ Optional extensions | F49: Advanced DSA (all 4 modules, condensed) | G49: • Core techniques: arrays, bits, recursion, hashing & sorting | H49: 📖 LeetCode problems | I49: ▶ arrays, bits, recursion, hashing &… | J49: Choose this if targeting product-based companies | K49: =IF(B49="Yes",Overview!$C$5,0) -> 0 | L49: Not Started
A50: =IF(B50="Yes",COUNTIF(B$6:B50,"Yes"),"—") -> — | B50: No | C50: =IF(B50="Yes",Overview!$C$4+7*(COUNTIF(B$6:B50,"Yes")-1),"—") -> — | D50: =IF(B50="Yes",C50+6,"—") -> — | E50: 8. ✨ Optional extensions | F50: Advanced DSA (all 4 modules, condensed) | G50: • Core techniques: arrays, bits, recursion, hashing & sorting | H50: 📖 NeetCode roadmap | I50: ▶ arrays, bits, recursion, hashing &… | J50: Choose this if targeting product-based companies | K50: =IF(B50="Yes",Overview!$C$5,0) -> 0 | L50: Not Started
A51: =IF(B51="Yes",COUNTIF(B$6:B51,"Yes"),"—") -> — | B51: No | C51: =IF(B51="Yes",Overview!$C$4+7*(COUNTIF(B$6:B51,"Yes")-1),"—") -> — | D51: =IF(B51="Yes",C51+6,"—") -> — | E51: 8. ✨ Optional extensions | F51: Advanced DSA (all 4 modules, condensed) | G51: • Linear & non-linear structures: searching, linked list, stacks, queues & trees | H51: 📖 CP-Algorithms | I51: ▶ searching, linked list, stacks, qu… | J51: Choose this if targeting product-based companies | K51: =IF(B51="Yes",Overview!$C$5,0) -> 0 | L51: Not Started
A52: =IF(B52="Yes",COUNTIF(B$6:B52,"Yes"),"—") -> — | B52: No | C52: =IF(B52="Yes",Overview!$C$4+7*(COUNTIF(B$6:B52,"Yes")-1),"—") -> — | D52: =IF(B52="Yes",C52+6,"—") -> — | E52: 8. ✨ Optional extensions | F52: Advanced DSA (all 4 modules, condensed) | G52: • Linear & non-linear structures: searching, linked list, stacks, queues & trees | H52: 📖 LeetCode problems | I52: ▶ searching, linked list, stacks, qu… | J52: Choose this if targeting product-based companies | K52: =IF(B52="Yes",Overview!$C$5,0) -> 0 | L52: Not Started
... A68: =IF(B68="Yes",COUNTIF(B$6:B68,"Yes"),"—") -> — | B68: No | C68: =IF(B68="Yes",Overview!$C$4+7*(COUNTIF(B$6:B68,"Yes")-1),"—") -> — | D68: =IF(B68="Yes",C68+6,"—") -> — | E68: 8. ✨ Optional extensions | F68: System Design Essentials | G68: • Case studies: Typeahead, messaging, Uber, e-commerce | H68: 📖 Kafka docs | I68: ▶ Typeahead, messaging, Uber, e-comm… | J68: Design 1 system/week on paper ★ Milestone: 3 HLD write-ups | K68: =IF(B68="Yes",Overview!$C$5,0) -> 0 | L68: Not Started
A69: =IF(B69="Yes",COUNTIF(B$6:B69,"Yes"),"—") -> — | B69: No | C69: =IF(B69="Yes",Overview!$C$4+7*(COUNTIF(B$6:B69,"Yes")-1),"—") -> — | D69: =IF(B69="Yes",C69+6,"—") -> — | E69: 8. ✨ Optional extensions | F69: Angular – MEAN Stack (alternative) | G69: • Intro to Angular & application architecture | H69: 📖 Angular tutorials | I69: ▶ Intro to Angular & application arc… | J69: Only if your target employers use Angular | K69: =IF(B69="Yes",Overview!$C$5,0) -> 0 | L69: Not Started | M69: Source: Besant syllabus
A70: =IF(B70="Yes",COUNTIF(B$6:B70,"Yes"),"—") -> — | B70: No | C70: =IF(B70="Yes",Overview!$C$4+7*(COUNTIF(B$6:B70,"Yes")-1),"—") -> — | D70: =IF(B70="Yes",C70+6,"—") -> — | E70: 8. ✨ Optional extensions | F70: Angular – MEAN Stack (alternative) | G70: • NgModules & components • Templates, data binding & directives | H70: 📖 Angular docs | I70: ▶ NgModules & components | J70: Only if your target employers use Angular | K70: =IF(B70="Yes",Overview!$C$5,0) -> 0 | L70: Not Started | M70: Source: Besant syllabus
A71: =IF(B71="Yes",COUNTIF(B$6:B71,"Yes"),"—") -> — | B71: No | C71: =IF(B71="Yes",Overview!$C$4+7*(COUNTIF(B$6:B71,"Yes")-1),"—") -> — | D71: =IF(B71="Yes",C71+6,"—") -> — | E71: 8. ✨ Optional extensions | F71: Angular – MEAN Stack (alternative) | G71: • Template routing & forms • Services & dependency injection | H71: 📖 Node.js learn | I71: ▶ Template routing & forms | J71: Only if your target employers use Angular | K71: =IF(B71="Yes",Overview!$C$5,0) -> 0 | L71: Not Started | M71: Source: Besant syllabus
A72: =IF(B72="Yes",COUNTIF(B$6:B72,"Yes"),"—") -> — | B72: No | C72: =IF(B72="Yes",Overview!$C$4+7*(COUNTIF(B$6:B72,"Yes")-1),"—") -> — | D72: =IF(B72="Yes",C72+6,"—") -> — | E72: 8. ✨ Optional extensions | F72: Angular – MEAN Stack (alternative) | G72: • Server communication (GET/POST/PUT/DELETE) • Complete web app in Angular | H72: 📖 Angular tutorials | I72: ▶ Server communication (GET/POST/PUT… | J72: Only if your target employers use Angular ★ Milestone: Angular CRUD app | K72: =IF(B72="Yes",Overview!$C$5,0) -> 0 | L72: Not Started | M72: Source: Besant syllabus
A73: =IF(B73="Yes",COUNTIF(B$6:B73,"Yes"),"—") -> — | B73: No | C73: =IF(B73="Yes",Overview!$C$4+7*(COUNTIF(B$6:B73,"Yes")-1),"—") -> — | D73: =IF(B73="Yes",C73+6,"—") -> — | E73: 8. ✨ Optional extensions | F73: PHP, MySQL & Laravel (alternative) | G73: • PHP crash course & embedding PHP in HTML | H73: 📖 PHP manual | I73: ▶ PHP crash course & embedding PHP i… | J73: Only if targeting PHP/WordPress/Laravel roles | K73: =IF(B73="Yes",Overview!$C$5,0) -> 0 | L73: Not Started | M73: Source: Besant syllabus
A74: =IF(B74="Yes",COUNTIF(B$6:B74,"Yes"),"—") -> — | B74: No | C74: =IF(B74="Yes",Overview!$C$4+7*(COUNTIF(B$6:B74,"Yes")-1),"—") -> — | D74: =IF(B74="Yes",C74+6,"—") -> — | E74: 8. ✨ Optional extensions | F74: PHP, MySQL & Laravel (alternative) | G74: • Storing & retrieving data; arrays • String manipulation & regular expressions | H74: 📖 Laravel docs | I74: ▶ Storing & retrieving data; arrays | J74: Only if targeting PHP/WordPress/Laravel roles | K74: =IF(B74="Yes",Overview!$C$5,0) -> 0 | L74: Not Started | M74: Source: Besant syllabus
A75: =IF(B75="Yes",COUNTIF(B$6:B75,"Yes"),"—") -> — | B75: No | C75: =IF(B75="Yes",Overview!$C$4+7*(COUNTIF(B$6:B75,"Yes")-1),"—") -> — | D75: =IF(B75="Yes",C75+6,"—") -> — | E75: 8. ✨ Optional extensions | F75: PHP, MySQL & Laravel (alternative) | G75: • Reusing code & writing functions | H75: 📖 MySQL docs | I75: ▶ Reusing code & writing functions | J75: Only if targeting PHP/WordPress/Laravel roles | K75: =IF(B75="Yes",Overview!$C$5,0) -> 0 | L75: Not Started | M75: Source: Besant syllabus
A76: =IF(B76="Yes",COUNTIF(B$6:B76,"Yes"),"—") -> — | B76: No | C76: =IF(B76="Yes",Overview!$C$4+7*(COUNTIF(B$6:B76,"Yes")-1),"—") -> — | D76: =IF(B76="Yes",C76+6,"—") -> — | E76: 8. ✨ Optional extensions | F76: PHP, MySQL & Laravel (alternative) | G76: • Object-oriented PHP • MVC with Laravel: forms, controllers, Blade, migrations, Eloquent ORM | H76: 📖 PHP manual | I76: ▶ Object-oriented PHP | J76: Only if targeting PHP/WordPress/Laravel roles | K76: =IF(B76="Yes",Overview!$C$5,0) -> 0 | L76: Not Started | M76: Source: Besant syllabus
A77: =IF(B77="Yes",COUNTIF(B$6:B77,"Yes"),"—") -> — | B77: No | C77: =IF(B77="Yes",Overview!$C$4+7*(COUNTIF(B$6:B77,"Yes")-1),"—") -> — | D77: =IF(B77="Yes",C77+6,"—") -> — | E77: 8. ✨ Optional extensions | F77: PHP, MySQL & Laravel (alternative) | G77: • Designing & creating your web database in MySQL | H77: 📖 Laravel docs | I77: ▶ Designing & creating your web data… | J77: Only if targeting PHP/WordPress/Laravel roles | K77: =IF(B77="Yes",Overview!$C$5,0) -> 0 | L77: Not Started | M77: Source: Besant syllabus
A78: =IF(B78="Yes",COUNTIF(B$6:B78,"Yes"),"—") -> — | B78: No | C78: =IF(B78="Yes",Overview!$C$4+7*(COUNTIF(B$6:B78,"Yes")-1),"—") -> — | D78: =IF(B78="Yes",C78+6,"—") -> — | E78: 8. ✨ Optional extensions | F78: PHP, MySQL & Laravel (alternative) | G78: • Accessing MySQL from the web with PHP • Build a complete Laravel app | H78: 📖 MySQL docs | I78: ▶ Accessing MySQL from the web with … | J78: Only if targeting PHP/WordPress/Laravel roles ★ Milestone: Laravel CRUD app | K78: =IF(B78="Yes",Overview!$C$5,0) -> 0 | L78: Not Started | M78: Source: Besant syllabus

Sheet Module Summary
A1: Module Summary – live roll-up from both plans
A2: All figures are formulas driven by the Include? and Status columns of the plan sheets.
A4: Track | B4: Phase | C4: Module | D4: Weeks planned | E4: Weeks done | F4: % done | G4: Start | H4: Finish | I4: Hours planned
A5: SDE | B5: 0. 🧱 Foundations | C5: Programming Fundamentals – Thinking with AI: Logics, Loops & Control Flow | D5: =COUNTIFS('SDE Plan'!$F$6:$F$78,$C5,'SDE Plan'!$B$6:$B$78,"Yes") -> 0 | E5: =COUNTIFS('SDE Plan'!$F$6:$F$78,$C5,'SDE Plan'!$B$6:$B$78,"Yes",'SDE Plan'!$L$6:$L$78,"Done") -> 0 | F5: =IF(D5=0,0,E5/D5) -> 0 | G5: =IF(D5=0,"—",_xlfn.MINIFS('SDE Plan'!$C$6:$C$78,'SDE Plan'!$F$6:$F$78,$C5,'SDE Plan'!$B$6:$B$78,"Yes")) -> — | H5: =IF(D5=0,"—",_xlfn.MAXIFS('SDE Plan'!$D$6:$D$78,'SDE Plan'!$F$6:$F$78,$C5,'SDE Plan'!$B$6:$B$78,"Yes")) -> — | I5: =D5*Overview!$C$5 -> 0
A6: SDE | B6: 0. 🧱 Foundations | C6: Programming Fundamentals – Code Smarter with AI: Functions & Arrays | D6: =COUNTIFS('SDE Plan'!$F$6:$F$78,$C6,'SDE Plan'!$B$6:$B$78,"Yes") -> 0 | E6: =COUNTIFS('SDE Plan'!$F$6:$F$78,$C6,'SDE Plan'!$B$6:$B$78,"Yes",'SDE Plan'!$L$6:$L$78,"Done") -> 0 | F6: =IF(D6=0,0,E6/D6) -> 0 | G6: =IF(D6=0,"—",_xlfn.MINIFS('SDE Plan'!$C$6:$C$78,'SDE Plan'!$F$6:$F$78,$C6,'SDE Plan'!$B$6:$B$78,"Yes")) -> — | H6: =IF(D6=0,"—",_xlfn.MAXIFS('SDE Plan'!$D$6:$D$78,'SDE Plan'!$F$6:$F$78,$C6,'SDE Plan'!$B$6:$B$78,"Yes")) -> — | I6: =D6*Overview!$C$5 -> 0
A7: SDE | B7: 1. 🧩 Problem Solving | C7: Intermediate DSA: AI-Assisted Problem Solving | D7: =COUNTIFS('SDE Plan'!$F$6:$F$78,$C7,'SDE Plan'!$B$6:$B$78,"Yes") -> 2 | E7: =COUNTIFS('SDE Plan'!$F$6:$F$78,$C7,'SDE Plan'!$B$6:$B$78,"Yes",'SDE Plan'!$L$6:$L$78,"Done") -> 0 | F7: =IF(D7=0,0,E7/D7) -> 0 | G7: =IF(D7=0,"—",_xlfn.MINIFS('SDE Plan'!$C$6:$C$78,'SDE Plan'!$F$6:$F$78,$C7,'SDE Plan'!$B$6:$B$78,"Yes")) -> 46307 | H7: =IF(D7=0,"—",_xlfn.MAXIFS('SDE Plan'!$D$6:$D$78,'SDE Plan'!$F$6:$F$78,$C7,'SDE Plan'!$B$6:$B$78,"Yes")) -> 46320 | I7: =D7*Overview!$C$5 -> 40
A8: SDE | B8: 2. 🤖 AI Skills | C8: Agentic AI: From Talking to AI to Building One | D8: =COUNTIFS('SDE Plan'!$F$6:$F$78,$C8,'SDE Plan'!$B$6:$B$78,"Yes") -> 2 | E8: =COUNTIFS('SDE Plan'!$F$6:$F$78,$C8,'SDE Plan'!$B$6:$B$78,"Yes",'SDE Plan'!$L$6:$L$78,"Done") -> 0 | F8: =IF(D8=0,0,E8/D8) -> 0 | G8: =IF(D8=0,"—",_xlfn.MINIFS('SDE Plan'!$C$6:$C$78,'SDE Plan'!$F$6:$F$78,$C8,'SDE Plan'!$B$6:$B$78,"Yes")) -> 46321 | H8: =IF(D8=0,"—",_xlfn.MAXIFS('SDE Plan'!$D$6:$D$78,'SDE Plan'!$F$6:$F$78,$C8,'SDE Plan'!$B$6:$B$78,"Yes")) -> 46334 | I8: =D8*Overview!$C$5 -> 40
A9: SDE | B9: 3. 🧠 DSA | C9: Advanced DSA: Foundations – Core Techniques & Optimization | D9: =COUNTIFS('SDE Plan'!$F$6:$F$78,$C9,'SDE Plan'!$B$6:$B$78,"Yes") -> 3 | E9: =COUNTIFS('SDE Plan'!$F$6:$F$78,$C9,'SDE Plan'!$B$6:$B$78,"Yes",'SDE Plan'!$L$6:$L$78,"Done") -> 0 | F9: =IF(D9=0,0,E9/D9) -> 0 | G9: =IF(D9=0,"—",_xlfn.MINIFS('SDE Plan'!$C$6:$C$78,'SDE Plan'!$F$6:$F$78,$C9,'SDE Plan'!$B$6:$B$78,"Yes")) -> 46335 | H9: =IF(D9=0,"—",_xlfn.MAXIFS('SDE Plan'!$D$6:$D$78,'SDE Plan'!$F$6:$F$78,$C9,'SDE Plan'!$B$6:$B$78,"Yes")) -> 46355 | I9: =D9*Overview!$C$5 -> 60
A10: SDE | B10: 3. 🧠 DSA | C10: Advanced DSA: Linear & Non-Linear Structures | D10: =COUNTIFS('SDE Plan'!$F$6:$F$78,$C10,'SDE Plan'!$B$6:$B$78,"Yes") -> 3 | E10: =COUNTIFS('SDE Plan'!$F$6:$F$78,$C10,'SDE Plan'!$B$6:$B$78,"Yes",'SDE Plan'!$L$6:$L$78,"Done") -> 0 | F10: =IF(D10=0,0,E10/D10) -> 0 | G10: =IF(D10=0,"—",_xlfn.MINIFS('SDE Plan'!$C$6:$C$78,'SDE Plan'!$F$6:$F$78,$C10,'SDE Plan'!$B$6:$B$78,"Yes")) -> 46356 | H10: =IF(D10=0,"—",_xlfn.MAXIFS('SDE Plan'!$D$6:$D$78,'SDE Plan'!$F$6:$F$78,$C10,'SDE Plan'!$B$6:$B$78,"Yes")) -> 46376 | I10: =D10*Overview!$C$5 -> 60
A11: SDE | B11: 3. 🧠 DSA | C11: Advanced DSA: Backtracking & Advanced Trees | D11: =COUNTIFS('SDE Plan'!$F$6:$F$78,$C11,'SDE Plan'!$B$6:$B$78,"Yes") -> 3 | E11: =COUNTIFS('SDE Plan'!$F$6:$F$78,$C11,'SDE Plan'!$B$6:$B$78,"Yes",'SDE Plan'!$L$6:$L$78,"Done") -> 0 | F11: =IF(D11=0,0,E11/D11) -> 0 | G11: =IF(D11=0,"—",_xlfn.MINIFS('SDE Plan'!$C$6:$C$78,'SDE Plan'!$F$6:$F$78,$C11,'SDE Plan'!$B$6:$B$78,"Yes")) -> 46377 | H11: =IF(D11=0,"—",_xlfn.MAXIFS('SDE Plan'!$D$6:$D$78,'SDE Plan'!$F$6:$F$78,$C11,'SDE Plan'!$B$6:$B$78,"Yes")) -> 46397 | I11: =D11*Overview!$C$5 -> 60
A12: SDE | B12: 3. 🧠 DSA | C12: Advanced DSA: DP, Heaps & Graphs – Crack It with AI Edge | D12: =COUNTIFS('SDE Plan'!$F$6:$F$78,$C12,'SDE Plan'!$B$6:$B$78,"Yes") -> 4 | E12: =COUNTIFS('SDE Plan'!$F$6:$F$78,$C12,'SDE Plan'!$B$6:$B$78,"Yes",'SDE Plan'!$L$6:$L$78,"Done") -> 0 | F12: =IF(D12=0,0,E12/D12) -> 0 | G12: =IF(D12=0,"—",_xlfn.MINIFS('SDE Plan'!$C$6:$C$78,'SDE Plan'!$F$6:$F$78,$C12,'SDE Plan'!$B$6:$B$78,"Yes")) -> 46398 | H12: =IF(D12=0,"—",_xlfn.MAXIFS('SDE Plan'!$D$6:$D$78,'SDE Plan'!$F$6:$F$78,$C12,'SDE Plan'!$B$6:$B$78,"Yes")) -> 46425 | I12: =D12*Overview!$C$5 -> 80
A13: SDE | B13: 4. 🗄️ Databases | C13: Databases & SQL | D13: =COUNTIFS('SDE Plan'!$F$6:$F$78,$C13,'SDE Plan'!$B$6:$B$78,"Yes") -> 2 | E13: =COUNTIFS('SDE Plan'!$F$6:$F$78,$C13,'SDE Plan'!$B$6:$B$78,"Yes",'SDE Plan'!$L$6:$L$78,"Done") -> 0 | F13: =IF(D13=0,0,E13/D13) -> 0 | G13: =IF(D13=0,"—",_xlfn.MINIFS('SDE Plan'!$C$6:$C$78,'SDE Plan'!$F$6:$F$78,$C13,'SDE Plan'!$B$6:$B$78,"Yes")) -> 46426 | H13: =IF(D13=0,"—",_xlfn.MAXIFS('SDE Plan'!$D$6:$D$78,'SDE Plan'!$F$6:$F$78,$C13,'SDE Plan'!$B$6:$B$78,"Yes")) -> 46439 | I13: =D13*Overview!$C$5 -> 40
A14: SDE | B14: 5. ⚙️ Backend & LLD | C14: Foundations of Object-Oriented Design & Scalable Systems | D14: =COUNTIFS('SDE Plan'!$F$6:$F$78,$C14,'SDE Plan'!$B$6:$B$78,"Yes") -> 3 | E14: =COUNTIFS('SDE Plan'!$F$6:$F$78,$C14,'SDE Plan'!$B$6:$B$78,"Yes",'SDE Plan'!$L$6:$L$78,"Done") -> 0 | F14: =IF(D14=0,0,E14/D14) -> 0 | G14: =IF(D14=0,"—",_xlfn.MINIFS('SDE Plan'!$C$6:$C$78,'SDE Plan'!$F$6:$F$78,$C14,'SDE Plan'!$B$6:$B$78,"Yes")) -> 46440 | H14: =IF(D14=0,"—",_xlfn.MAXIFS('SDE Plan'!$D$6:$D$78,'SDE Plan'!$F$6:$F$78,$C14,'SDE Plan'!$B$6:$B$78,"Yes")) -> 46460 | I14: =D14*Overview!$C$5 -> 60
A15: SDE | B15: 5. ⚙️ Backend & LLD | C15: Design Principles & Patterns for Extensible Systems | D15: =COUNTIFS('SDE Plan'!$F$6:$F$78,$C15,'SDE Plan'!$B$6:$B$78,"Yes") -> 2 | E15: =COUNTIFS('SDE Plan'!$F$6:$F$78,$C15,'SDE Plan'!$B$6:$B$78,"Yes",'SDE Plan'!$L$6:$L$78,"Done") -> 0 | F15: =IF(D15=0,0,E15/D15) -> 0 | G15: =IF(D15=0,"—",_xlfn.MINIFS('SDE Plan'!$C$6:$C$78,'SDE Plan'!$F$6:$F$78,$C15,'SDE Plan'!$B$6:$B$78,"Yes")) -> 46461 | H15: =IF(D15=0,"—",_xlfn.MAXIFS('SDE Plan'!$D$6:$D$78,'SDE Plan'!$F$6:$F$78,$C15,'SDE Plan'!$B$6:$B$78,"Yes")) -> 46474 | I15: =D15*Overview!$C$5 -> 40
A16: SDE | B16: 5. ⚙️ Backend & LLD | C16: Applied Design & Machine Coding | D16: =COUNTIFS('SDE Plan'!$F$6:$F$78,$C16,'SDE Plan'!$B$6:$B$78,"Yes") -> 3 | E16: =COUNTIFS('SDE Plan'!$F$6:$F$78,$C16,'SDE Plan'!$B$6:$B$78,"Yes",'SDE Plan'!$L$6:$L$78,"Done") -> 0 | F16: =IF(D16=0,0,E16/D16) -> 0 | G16: =IF(D16=0,"—",_xlfn.MINIFS('SDE Plan'!$C$6:$C$78,'SDE Plan'!$F$6:$F$78,$C16,'SDE Plan'!$B$6:$B$78,"Yes")) -> 46475 | H16: =IF(D16=0,"—",_xlfn.MAXIFS('SDE Plan'!$D$6:$D$78,'SDE Plan'!$F$6:$F$78,$C16,'SDE Plan'!$B$6:$B$78,"Yes")) -> 46495 | I16: =D16*Overview!$C$5 -> 60
... A25: SDE | B25: 8. ✨ Electives (optional) | C25: Product Management for Engineers | D25: =COUNTIFS('SDE Plan'!$F$6:$F$78,$C25,'SDE Plan'!$B$6:$B$78,"Yes") -> 0 | E25: =COUNTIFS('SDE Plan'!$F$6:$F$78,$C25,'SDE Plan'!$B$6:$B$78,"Yes",'SDE Plan'!$L$6:$L$78,"Done") -> 0 | F25: =IF(D25=0,0,E25/D25) -> 0 | G25: =IF(D25=0,"—",_xlfn.MINIFS('SDE Plan'!$C$6:$C$78,'SDE Plan'!$F$6:$F$78,$C25,'SDE Plan'!$B$6:$B$78,"Yes")) -> — | H25: =IF(D25=0,"—",_xlfn.MAXIFS('SDE Plan'!$D$6:$D$78,'SDE Plan'!$F$6:$F$78,$C25,'SDE Plan'!$B$6:$B$78,"Yes")) -> — | I25: =D25*Overview!$C$5 -> 0
A26: Full-Stack | B26: 1. 🌐 Web Foundations | C26: HTML & CSS Foundations | D26: =COUNTIFS('FullStack Plan'!$F$6:$F$78,$C26,'FullStack Plan'!$B$6:$B$78,"Yes") -> 2 | E26: =COUNTIFS('FullStack Plan'!$F$6:$F$78,$C26,'FullStack Plan'!$B$6:$B$78,"Yes",'FullStack Plan'!$L$6:$L$78,"Done") -> 0 | F26: =IF(D26=0,0,E26/D26) -> 0 | G26: =IF(D26=0,"—",_xlfn.MINIFS('FullStack Plan'!$C$6:$C$78,'FullStack Plan'!$F$6:$F$78,$C26,'FullStack Plan'!$B$6:$B$78,"Yes")) -> 46307 | H26: =IF(D26=0,"—",_xlfn.MAXIFS('FullStack Plan'!$D$6:$D$78,'FullStack Plan'!$F$6:$F$78,$C26,'FullStack Plan'!$B$6:$B$78,"Yes")) -> 46320 | I26: =D26*Overview!$C$5 -> 40
A27: Full-Stack | B27: 1. 🌐 Web Foundations | C27: Bootstrap (supplementary) | D27: =COUNTIFS('FullStack Plan'!$F$6:$F$78,$C27,'FullStack Plan'!$B$6:$B$78,"Yes") -> 0 | E27: =COUNTIFS('FullStack Plan'!$F$6:$F$78,$C27,'FullStack Plan'!$B$6:$B$78,"Yes",'FullStack Plan'!$L$6:$L$78,"Done") -> 0 | F27: =IF(D27=0,0,E27/D27) -> 0 | G27: =IF(D27=0,"—",_xlfn.MINIFS('FullStack Plan'!$C$6:$C$78,'FullStack Plan'!$F$6:$F$78,$C27,'FullStack Plan'!$B$6:$B$78,"Yes")) -> — | H27: =IF(D27=0,"—",_xlfn.MAXIFS('FullStack Plan'!$D$6:$D$78,'FullStack Plan'!$F$6:$F$78,$C27,'FullStack Plan'!$B$6:$B$78,"Yes")) -> — | I27: =D27*Overview!$C$5 -> 0
A28: Full-Stack | B28: 2. ⚡ JavaScript | C28: JavaScript Runtime Systems, Browser APIs & Product Labs | D28: =COUNTIFS('FullStack Plan'!$F$6:$F$78,$C28,'FullStack Plan'!$B$6:$B$78,"Yes") -> 6 | E28: =COUNTIFS('FullStack Plan'!$F$6:$F$78,$C28,'FullStack Plan'!$B$6:$B$78,"Yes",'FullStack Plan'!$L$6:$L$78,"Done") -> 0 | F28: =IF(D28=0,0,E28/D28) -> 0 | G28: =IF(D28=0,"—",_xlfn.MINIFS('FullStack Plan'!$C$6:$C$78,'FullStack Plan'!$F$6:$F$78,$C28,'FullStack Plan'!$B$6:$B$78,"Yes")) -> 46321 | H28: =IF(D28=0,"—",_xlfn.MAXIFS('FullStack Plan'!$D$6:$D$78,'FullStack Plan'!$F$6:$F$78,$C28,'FullStack Plan'!$B$6:$B$78,"Yes")) -> 46362 | I28: =D28*Overview!$C$5 -> 120
A29: Full-Stack | B29: 2. ⚡ JavaScript | C29: JavaScript Object System & Engineering Patterns | D29: =COUNTIFS('FullStack Plan'!$F$6:$F$78,$C29,'FullStack Plan'!$B$6:$B$78,"Yes") -> 2 | E29: =COUNTIFS('FullStack Plan'!$F$6:$F$78,$C29,'FullStack Plan'!$B$6:$B$78,"Yes",'FullStack Plan'!$L$6:$L$78,"Done") -> 0 | F29: =IF(D29=0,0,E29/D29) -> 0 | G29: =IF(D29=0,"—",_xlfn.MINIFS('FullStack Plan'!$C$6:$C$78,'FullStack Plan'!$F$6:$F$78,$C29,'FullStack Plan'!$B$6:$B$78,"Yes")) -> 46363 | H29: =IF(D29=0,"—",_xlfn.MAXIFS('FullStack Plan'!$D$6:$D$78,'FullStack Plan'!$F$6:$F$78,$C29,'FullStack Plan'!$B$6:$B$78,"Yes")) -> 46376 | I29: =D29*Overview!$C$5 -> 40
A30: Full-Stack | B30: 2. ⚡ JavaScript | C30: jQuery (legacy, optional) | D30: =COUNTIFS('FullStack Plan'!$F$6:$F$78,$C30,'FullStack Plan'!$B$6:$B$78,"Yes") -> 0 | E30: =COUNTIFS('FullStack Plan'!$F$6:$F$78,$C30,'FullStack Plan'!$B$6:$B$78,"Yes",'FullStack Plan'!$L$6:$L$78,"Done") -> 0 | F30: =IF(D30=0,0,E30/D30) -> 0 | G30: =IF(D30=0,"—",_xlfn.MINIFS('FullStack Plan'!$C$6:$C$78,'FullStack Plan'!$F$6:$F$78,$C30,'FullStack Plan'!$B$6:$B$78,"Yes")) -> — | H30: =IF(D30=0,"—",_xlfn.MAXIFS('FullStack Plan'!$D$6:$D$78,'FullStack Plan'!$F$6:$F$78,$C30,'FullStack Plan'!$B$6:$B$78,"Yes")) -> — | I30: =D30*Overview!$C$5 -> 0
A31: Full-Stack | B31: 3. ⚛️ React | C31: React & Frontend Product Architecture Fundamentals | D31: =COUNTIFS('FullStack Plan'!$F$6:$F$78,$C31,'FullStack Plan'!$B$6:$B$78,"Yes") -> 4 | E31: =COUNTIFS('FullStack Plan'!$F$6:$F$78,$C31,'FullStack Plan'!$B$6:$B$78,"Yes",'FullStack Plan'!$L$6:$L$78,"Done") -> 0 | F31: =IF(D31=0,0,E31/D31) -> 0 | G31: =IF(D31=0,"—",_xlfn.MINIFS('FullStack Plan'!$C$6:$C$78,'FullStack Plan'!$F$6:$F$78,$C31,'FullStack Plan'!$B$6:$B$78,"Yes")) -> 46377 | H31: =IF(D31=0,"—",_xlfn.MAXIFS('FullStack Plan'!$D$6:$D$78,'FullStack Plan'!$F$6:$F$78,$C31,'FullStack Plan'!$B$6:$B$78,"Yes")) -> 46404 | I31: =D31*Overview!$C$5 -> 80
A32: Full-Stack | B32: 4. 🛠️ Backend (MERN) | C32: Backend Product Systems, APIs & Production Engineering (MERN) | D32: =COUNTIFS('FullStack Plan'!$F$6:$F$78,$C32,'FullStack Plan'!$B$6:$B$78,"Yes") -> 4 | E32: =COUNTIFS('FullStack Plan'!$F$6:$F$78,$C32,'FullStack Plan'!$B$6:$B$78,"Yes",'FullStack Plan'!$L$6:$L$78,"Done") -> 0 | F32: =IF(D32=0,0,E32/D32) -> 0 | G32: =IF(D32=0,"—",_xlfn.MINIFS('FullStack Plan'!$C$6:$C$78,'FullStack Plan'!$F$6:$F$78,$C32,'FullStack Plan'!$B$6:$B$78,"Yes")) -> 46405 | H32: =IF(D32=0,"—",_xlfn.MAXIFS('FullStack Plan'!$D$6:$D$78,'FullStack Plan'!$F$6:$F$78,$C32,'FullStack Plan'!$B$6:$B$78,"Yes")) -> 46432 | I32: =D32*Overview!$C$5 -> 80
A33: Full-Stack | B33: 4. 🛠️ Backend (MERN) | C33: Databases & SQL | D33: =COUNTIFS('FullStack Plan'!$F$6:$F$78,$C33,'FullStack Plan'!$B$6:$B$78,"Yes") -> 4 | E33: =COUNTIFS('FullStack Plan'!$F$6:$F$78,$C33,'FullStack Plan'!$B$6:$B$78,"Yes",'FullStack Plan'!$L$6:$L$78,"Done") -> 0 | F33: =IF(D33=0,0,E33/D33) -> 0 | G33: =IF(D33=0,"—",_xlfn.MINIFS('FullStack Plan'!$C$6:$C$78,'FullStack Plan'!$F$6:$F$78,$C33,'FullStack Plan'!$B$6:$B$78,"Yes")) -> 46433 | H33: =IF(D33=0,"—",_xlfn.MAXIFS('FullStack Plan'!$D$6:$D$78,'FullStack Plan'!$F$6:$F$78,$C33,'FullStack Plan'!$B$6:$B$78,"Yes")) -> 46460 | I33: =D33*Overview!$C$5 -> 80
A34: Full-Stack | B34: 4. 🛠️ Backend (MERN) | C34: Backend Product Systems – Deep Dive | D34: =COUNTIFS('FullStack Plan'!$F$6:$F$78,$C34,'FullStack Plan'!$B$6:$B$78,"Yes") -> 2 | E34: =COUNTIFS('FullStack Plan'!$F$6:$F$78,$C34,'FullStack Plan'!$B$6:$B$78,"Yes",'FullStack Plan'!$L$6:$L$78,"Done") -> 0 | F34: =IF(D34=0,0,E34/D34) -> 0 | G34: =IF(D34=0,"—",_xlfn.MINIFS('FullStack Plan'!$C$6:$C$78,'FullStack Plan'!$F$6:$F$78,$C34,'FullStack Plan'!$B$6:$B$78,"Yes")) -> 46461 | H34: =IF(D34=0,"—",_xlfn.MAXIFS('FullStack Plan'!$D$6:$D$78,'FullStack Plan'!$F$6:$F$78,$C34,'FullStack Plan'!$B$6:$B$78,"Yes")) -> 46474 | I34: =D34*Overview!$C$5 -> 40
A35: Full-Stack | B35: 5. 🚀 Advanced Frontend | C35: React, TypeScript & Frontend Architecture – Deep Dive (incl. Next.js) | D35: =COUNTIFS('FullStack Plan'!$F$6:$F$78,$C35,'FullStack Plan'!$B$6:$B$78,"Yes") -> 4 | E35: =COUNTIFS('FullStack Plan'!$F$6:$F$78,$C35,'FullStack Plan'!$B$6:$B$78,"Yes",'FullStack Plan'!$L$6:$L$78,"Done") -> 0 | F35: =IF(D35=0,0,E35/D35) -> 0 | G35: =IF(D35=0,"—",_xlfn.MINIFS('FullStack Plan'!$C$6:$C$78,'FullStack Plan'!$F$6:$F$78,$C35,'FullStack Plan'!$B$6:$B$78,"Yes")) -> 46475 | H35: =IF(D35=0,"—",_xlfn.MAXIFS('FullStack Plan'!$D$6:$D$78,'FullStack Plan'!$F$6:$F$78,$C35,'FullStack Plan'!$B$6:$B$78,"Yes")) -> 46502 | I35: =D35*Overview!$C$5 -> 80
A36: Full-Stack | B36: 5. 🚀 Advanced Frontend | C36: Foundations of AI-Assisted Full-Stack Development | D36: =COUNTIFS('FullStack Plan'!$F$6:$F$78,$C36,'FullStack Plan'!$B$6:$B$78,"Yes") -> 2 | E36: =COUNTIFS('FullStack Plan'!$F$6:$F$78,$C36,'FullStack Plan'!$B$6:$B$78,"Yes",'FullStack Plan'!$L$6:$L$78,"Done") -> 0 | F36: =IF(D36=0,0,E36/D36) -> 0 | G36: =IF(D36=0,"—",_xlfn.MINIFS('FullStack Plan'!$C$6:$C$78,'FullStack Plan'!$F$6:$F$78,$C36,'FullStack Plan'!$B$6:$B$78,"Yes")) -> 46503 | H36: =IF(D36=0,"—",_xlfn.MAXIFS('FullStack Plan'!$D$6:$D$78,'FullStack Plan'!$F$6:$F$78,$C36,'FullStack Plan'!$B$6:$B$78,"Yes")) -> 46516 | I36: =D36*Overview!$C$5 -> 40
A37: Full-Stack | B37: 6. 🏆 Capstone | C37: Full-Stack Capstone Project (suggested) | D37: =COUNTIFS('FullStack Plan'!$F$6:$F$78,$C37,'FullStack Plan'!$B$6:$B$78,"Yes") -> 3 | E37: =COUNTIFS('FullStack Plan'!$F$6:$F$78,$C37,'FullStack Plan'!$B$6:$B$78,"Yes",'FullStack Plan'!$L$6:$L$78,"Done") -> 0 | F37: =IF(D37=0,0,E37/D37) -> 0 | G37: =IF(D37=0,"—",_xlfn.MINIFS('FullStack Plan'!$C$6:$C$78,'FullStack Plan'!$F$6:$F$78,$C37,'FullStack Plan'!$B$6:$B$78,"Yes")) -> 46517 | H37: =IF(D37=0,"—",_xlfn.MAXIFS('FullStack Plan'!$D$6:$D$78,'FullStack Plan'!$F$6:$F$78,$C37,'FullStack Plan'!$B$6:$B$78,"Yes")) -> 46537 | I37: =D37*Overview!$C$5 -> 60
... A43: Full-Stack | B43: 8. ✨ Optional extensions | C43: PHP, MySQL & Laravel (alternative) | D43: =COUNTIFS('FullStack Plan'!$F$6:$F$78,$C43,'FullStack Plan'!$B$6:$B$78,"Yes") -> 0 | E43: =COUNTIFS('FullStack Plan'!$F$6:$F$78,$C43,'FullStack Plan'!$B$6:$B$78,"Yes",'FullStack Plan'!$L$6:$L$78,"Done") -> 0 | F43: =IF(D43=0,0,E43/D43) -> 0 | G43: =IF(D43=0,"—",_xlfn.MINIFS('FullStack Plan'!$C$6:$C$78,'FullStack Plan'!$F$6:$F$78,$C43,'FullStack Plan'!$B$6:$B$78,"Yes")) -> — | H43: =IF(D43=0,"—",_xlfn.MAXIFS('FullStack Plan'!$D$6:$D$78,'FullStack Plan'!$F$6:$F$78,$C43,'FullStack Plan'!$B$6:$B$78,"Yes")) -> — | I43: =D43*Overview!$C$5 -> 0

Sheet Resources
A1: Where to Read & Watch – resource hub
A2: Docs/tutorial links are official or widely used references. YouTube links are search links (always valid) – channel names are suggestions; pick the playlist whose style suits you.
A4: Track | B4: Phase | C4: Module | D4: 📖 Read #1 | E4: 📖 Read #2 | F4: 📖 Read #3 | G4: ▶ YouTube search | H4: Channels to try
A5: SDE | B5: 0. 🧱 Foundations | C5: Programming Fundamentals – Thinking with AI: Logics, Loops & Control Flow | D5: freeCodeCamp Learn | E5: Java tutorials (dev.java) | F5: GeeksforGeeks | G5: ▶ programming loops conditions for beginners tutorial | H5: freeCodeCamp.org, Apna College, CodeWithHarry
A6: SDE | B6: 0. 🧱 Foundations | C6: Programming Fundamentals – Code Smarter with AI: Functions & Arrays | D6: freeCodeCamp Learn | E6: Java tutorials (dev.java) | F6: GeeksforGeeks | G6: ▶ programming functions arrays strings tutorial | H6: freeCodeCamp.org, Apna College, CodeWithHarry
A7: SDE + Full-Stack | B7: 1. 🧩 Problem Solving | C7: Intermediate DSA: AI-Assisted Problem Solving | D7: NeetCode roadmap | E7: GeeksforGeeks DSA | F7: LeetCode problems | G7: ▶ DSA arrays prefix sum tutorial | H7: Striver (take U forward), NeetCode, Apna College
A8: SDE | B8: 2. 🤖 AI Skills | C8: Agentic AI: From Talking to AI to Building One | D8: n8n docs | E8: Prompt engineering guide (Anthropic) | F8: OpenAI prompt engineering | G8: ▶ AI agents n8n RAG prompt engineering tutorial | H8: freeCodeCamp.org, Fireship, Andrej Karpathy
A9: SDE | B9: 3. 🧠 DSA | C9: Advanced DSA: Foundations – Core Techniques & Optimization | D9: GeeksforGeeks DSA | E9: CP-Algorithms | F9: LeetCode problems | G9: ▶ DSA tutorial | H9: Striver (take U forward), Abdul Bari, NeetCode
A10: SDE | B10: 3. 🧠 DSA | C10: Advanced DSA: Linear & Non-Linear Structures | D10: GeeksforGeeks DSA | E10: NeetCode roadmap | F10: LeetCode problems | G10: ▶ DSA tutorial | H10: Striver (take U forward), Abdul Bari, NeetCode
A11: SDE | B11: 3. 🧠 DSA | C11: Advanced DSA: Backtracking & Advanced Trees | D11: GeeksforGeeks DSA | E11: CP-Algorithms | F11: LeetCode problems | G11: ▶ DSA tutorial | H11: Striver (take U forward), Abdul Bari, NeetCode
A12: SDE | B12: 3. 🧠 DSA | C12: Advanced DSA: DP, Heaps & Graphs – Crack It with AI Edge | D12: CP-Algorithms | E12: NeetCode roadmap | F12: LeetCode problems | G12: ▶ DSA tutorial | H12: Striver (take U forward), William Fiset, NeetCode
A13: SDE + Full-Stack | B13: 4. 🗄️ Databases | C13: Databases & SQL | D13: SQLBolt interactive | E13: W3Schools SQL | F13: Mode SQL tutorial | G13: ▶ SQL tutorial | H13: freeCodeCamp.org, Alex The Analyst, CodeWithHarry
A14: SDE | B14: 5. ⚙️ Backend & LLD | C14: Foundations of Object-Oriented Design & Scalable Systems | D14: Java tutorials (dev.java) | E14: Oracle: Java concurrency | F14: Refactoring Guru | G14: ▶ Java tutorial | H14: Telusko, Kunal Kushwaha, Java Brains
A15: SDE | B15: 5. ⚙️ Backend & LLD | C15: Design Principles & Patterns for Extensible Systems | D15: Refactoring Guru patterns | E15: Refactoring Guru SOLID | F15: UML basics (Visual Paradigm) | G15: ▶ design patterns SOLID tutorial | H15: Christopher Okhravi, Concept && Coding, Telusko
... A40: Full-Stack | B40: 8. ✨ Optional extensions | C40: PHP, MySQL & Laravel (alternative) | D40: PHP manual | E40: Laravel docs | F40: MySQL docs | G40: ▶ PHP Laravel tutorial | H40: Traversy Media, Laravel Daily, freeCodeCamp.org
A42: Practice platforms
A43: LeetCode | B43: DSA problems & contests
A44: InterviewBit | B44: Structured interview practice (Scaler's platform)
A45: NeetCode 150 | B45: Curated DSA list with video solutions
A46: HackerRank SQL | B46: SQL practice
A47: Frontend Mentor | B47: HTML/CSS/JS/React UI challenges
A48: GreatFrontEnd | B48: Frontend interview questions
A49: The Odin Project | B49: Free full-stack JavaScript path
A50: roadmap.sh | B50: Visual roadmaps (frontend, backend, full-stack)

Sheet Projects
A1: Projects Portfolio Tracker
A2: Projects named in the Scaler curriculum / Besant syllabus plus a few suggested ones. Add your GitHub / live link and update Status.
A4: Track | B4: Project | C4: Phase / Module | D4: Skills shown | E4: Source | F4: Status | G4: GitHub / Live link
A5: SDE | B5: Social Network Analyzer | C5: 3. DSA – DP, Heaps & Graphs | D5: Graph algorithms, BFS/DFS, data modelling | E5: Scaler | F5: Not Started
A6: SDE | B6: Invoice Merger | C6: 3. DSA – DP, Heaps & Graphs | D6: Heaps, sorting, hashing on real data | E6: Scaler | F6: Not Started
A7: SDE | B7: TicTacToe (LLD + code) | C7: 5. Applied Design & Machine Coding | D7: OOP, class design, extensibility | E7: Scaler | F7: Not Started
A8: SDE | B8: Parking Lot (LLD + code) | C8: 5. Applied Design & Machine Coding | D8: Design patterns, strategy, concurrency | E8: Scaler | F8: Not Started
A9: SDE | B9: BookMyShow (LLD + code) | C9: 5. Applied Design & Machine Coding | D9: Complex domain modelling, locking | E9: Scaler | F9: Not Started
A10: SDE | B10: Splitwise (LLD + code) | C10: 5. Applied Design & Machine Coding | D10: Graph/heap of balances, clean APIs | E10: Scaler | F10: Not Started
A11: SDE | B11: UserAuthService microservice (Spring, JWT/OAuth2) | C11: 5. Backend Capstone Primer | D11: Spring Boot, JPA, auth, AWS deploy | E11: Scaler | F11: Not Started
A12: SDE | B12: Payment microservice (Stripe) + Redis/Kafka | C12: 5. Backend Capstone Advance | D12: Payments, async workloads, Docker | E12: Scaler | F12: Not Started
A13: SDE | B13: BookMyShow Chat Agent / Splitwise AI Receipt Processor | C13: 8. Elective – Production-Ready AI System | D13: LLM APIs, agents, backend orchestration | E13: Scaler | F13: Not Started
A14: SDE | B14: System-design portfolio (3 write-ups) | C14: 6. System Design | D14: HLD, trade-offs, estimation | E14: Suggested | F14: Not Started
A15: Full-Stack | B15: Responsive portfolio landing page | C15: 1. HTML & CSS | D15: Semantic HTML, Flexbox/Grid, responsive design | E15: Suggested | F15: Not Started
A16: Full-Stack | B16: Realtime Weather App | C16: 2. JavaScript – Product Lab I | D16: Fetch/async, JSON, DOM rendering | E16: Scaler | F16: Not Started
... A24: Full-Stack | B24: Capstone: original full-stack app with an AI feature | C24: 6. Capstone | D24: End-to-end ownership, deployment, demo | E24: Suggested | F24: Not Started

Sheet Sources & Notes
A1: Sources & Assumptions
A3: Sources
A4: 1 | B4: Scaler_Academy_Brochure.html – latest curriculum (module names, session lists, durations). Used as the primary source for both plans.
A5: 2 | B5: Academy-Broucher-12-05-24 PDFs (3 identical copies) – older Scaler brochure (e.g. Beginner 10.5 mo / Intermediate 12 mo / Advanced 10 mo, 'Gen AI for Software Engineers' elective, IIT-Roorkee add-on). Used to confirm structure and batch levels.
A6: 3 | B6: full-stack-developer-course-syllabus.pdf (Besant Technologies) – HTML, CSS, Bootstrap, JavaScript, jQuery, PHP/MySQL/Laravel, ReactJS, MEAN (Angular, Node, Express, MongoDB) and MERN topics. Items drawn from it are tagged 'Besant syllabus' or '(Besant)'.
A7: Assumptions
A8: A | B8: 1 month = 4 weeks. 'Mastering LastMile' (1.5 weeks in the brochure) is rounded up to 2 weeks.
A9: B | B9: Each module's session list is split evenly across its weeks. If a week is too heavy, spread it across 2 weeks (use Include? to re-flow dates).
A10: C | B10: Hours target per week is a planning input on Overview (default 15). The brochure does not specify hours; adjust to your schedule.
A11: D | B11: Module order follows the brochure: foundations → DSA → SQL → backend/LLD → system design → interview prep. Full-Stack order is JavaScript-first, then React, then Node/Mongo.
A12: E | B12: Rows tagged 'Suggested (not in sources)' (Full-Stack capstone, extra projects, practice targets) are my additions to make the plan actionable – edit freely.
A13: F | B13: 9-month target = 39 weeks. The SDE plan is the brochure curriculum compressed (e.g. DSA 16→13 wks, backend/LLD 22→14, system design 6→4, SQL 4→2, Agentic AI 4→2); compressed rows say so in Notes. Expect ~18–22 study hours/week. Full-Stack keeps the brochure durations and drops Bootstrap/jQuery/electives.
A14: G | B14: jQuery, Angular and PHP/Laravel (Besant) are legacy/alternative stacks and are switched off by default; turn them on only if your target roles need them.
A15: H | B15: Brochure placement/salary statistics are marketing figures and were not used in the plan.
A16: Study habits (suggested)
A17: • | B17: Daily: 1 hour DSA practice (any track) – consistency beats cramming.
A18: • | B18: Weekly: one timed mock contest or machine-coding round; review failures within 3 days.
A19: • | B19: End of every module: finish the milestone before moving on; push code to GitHub.
A20: I | B20: YouTube links are search URLs (youtube.com/results?search_query=…) built from each week's first topic, so they never break; channel names on the Resources sheet are suggestions, not endorsements, and I could not verify that each channel covers every topic. Docs links point to official/widely used references.
A22: Developed by | B22: Rajesh Kumar Singh
